Workbook
Name ArmourType: Helpers!$N$19
Name AttributeFilter: 'Build & Totals'!$B$2
Name BoonToggles: 'Build & Totals'!$F$57:$G$63
Name ChosenSpecs: Helpers!$A$24:$A$26
Name Class: 'Build & Totals'!$A$2
Name ConcentrationTotal: Helpers!$B$30
Name DerivedGain1: Helpers!$A$4
Name DerivedGain2: Helpers!$E$4
Name DerivedResult1: Helpers!$D$4
Name DerivedResult2: Helpers!$H$4
Name ExpertiseTotal: Helpers!$B$31
Name FlatGain: Helpers!$A$16
Name FlatResult: Helpers!$B$16
Name GearValues: 'Attributes & Prefixes'!$H$3:$S$1608
Name HealthyGain: Helpers!$A$8
Name HealthyResult: Helpers!$B$8
Name PowerSubtotal: Helpers!$A$20
Name PrecisionTotal: Helpers!$B$29
Name Rune1Bonus: Helpers!$N$3
Name Rune1Count: Helpers!$P$3
Name Rune1Stat: Helpers!$O$3
Name Rune2Bonus: Helpers!$N$4
Name Rune2Count: Helpers!$P$4
Name Rune2Stat: Helpers!$O$4
Name Rune3Bonus: Helpers!$N$5
Name Rune3Count: Helpers!$P$5
Name Rune3Stat: Helpers!$O$5
Name Rune4Bonus: Helpers!$N$6
Name Rune4Count: Helpers!$P$6
Name Rune4Stat: Helpers!$O$6
Name Rune5Bonus: Helpers!$N$7
Name Rune5Count: Helpers!$P$7
Name Rune5Stat: Helpers!$O$7
Name Rune6Bonus: Helpers!$N$8
Name Rune6Count: Helpers!$P$8
Name Rune6Stat: Helpers!$O$8
Name RuneTable: Runes!$A$2:$M$101
Name SharedGain1: Helpers!$B$12
Name SharedGain2: Helpers!$G$12
Name SharedResult1: Helpers!$E$12
Name SharedResult2: Helpers!$J$12
Name SigilTable: Sigils!$A:$B
Name Signet1: 'Build & Totals'!$A$46
Name Signet1Bonus: Helpers!$P$13
Name Signet1Check: Signets!$H$2
Name Signet1Stat: Helpers!$N$13
Name Signet2: 'Build & Totals'!$A$47
Name Signet2Bonus: Helpers!$P$14
Name Signet2Check: Signets!$H$3
Name Signet2Stat: Helpers!$N$14
Name Signet3: 'Build & Totals'!$A$48
Name Signet3Bonus: Helpers!$P$15
Name Signet3Check: Signets!$H$4
Name Signet3Stat: Helpers!$N$15
Name SignetPassives: Signets!$A$1:$D$16
Name SignetTable: Signets!$A$18:$D$61
Name Spec1: 'Build & Totals'!$B$4
Name Spec1MajorAdept: 'Build & Totals'!$B$5
Name Spec1MajorAdeptCondition: 'Trait Selection'!$C$4
Name Spec1MajorAdeptStacking: 'Trait Filters & Checks'!$E$19

Sheet Build & Totals
A1: Character Class | B1: Attribute Filter | C1: Attributes
A2: Engineer | B2: (Select)
A3: Specialisations & Traits | C3: Power | D3: Precision | E3: Toughness | F3: Vitality | G3: Concentration | H3: Condition Damage | I3: Expertise | J3: Ferocity | K3: Healing Power | L3: Defence
A4: Specialisation 1 | B4: Illusions | C4: {=_xlfn.LET(_xlpm.amount,'Conditionals Helper'!P128,IF(_xlpm.amount=0,"",_xlpm.amount))} | D4: {=_xlfn.LET(_xlpm.amount,'Conditionals Helper'!Q128,IF(_xlpm.amount=0,"",_xlpm.amount))} | E4: {=_xlfn.LET(_xlpm.amount,'Conditionals Helper'!R128,IF(_xlpm.amount=0,"",_xlpm.amount))} | F4: {=_xlfn.LET(_xlpm.amount,'Conditionals Helper'!S128,IF(_xlpm.amount=0,"",_xlpm.amount))} | G4: {=_xlfn.LET(_xlpm.amount,'Conditionals Helper'!T128,IF(_xlpm.amount=0,"",_xlpm.amount))} | H4: {=_xlfn.LET(_xlpm.amount,'Conditionals Helper'!U128,IF(_xlpm.amount=0,"",_xlpm.amount))} -> 9.6 | I4: {=_xlfn.LET(_xlpm.amount,'Conditionals Helper'!V128,IF(_xlpm.amount=0,"",_xlpm.amount))} | J4: {=_xlfn.LET(_xlpm.amount,'Conditionals Helper'!W128,IF(_xlpm.amount=0,"",_xlpm.amount))} | K4: {=_xlfn.LET(_xlpm.amount,'Conditionals Helper'!X128,IF(_xlpm.amount=0,"",_xlpm.amount))} | N4: Legend
A5: Major Adept | B5: Persistence of Memory | C5: {=_xlfn.LET(_xlpm.amount,'Conditionals Helper'!P$14,IF(_xlpm.amount=0,"",_xlpm.amount))} | D5: {=_xlfn.LET(_xlpm.amount,'Conditionals Helper'!Q$14,IF(_xlpm.amount=0,"",_xlpm.amount))} | E5: {=_xlfn.LET(_xlpm.amount,'Conditionals Helper'!R$14,IF(_xlpm.amount=0,"",_xlpm.amount))} | F5: {=_xlfn.LET(_xlpm.amount,'Conditionals Helper'!S$14,IF(_xlpm.amount=0,"",_xlpm.amount))} | G5: {=_xlfn.LET(_xlpm.amount,'Conditionals Helper'!T$14,IF(_xlpm.amount=0,"",_xlpm.amount))} | H5: {=_xlfn.LET(_xlpm.amount,'Conditionals Helper'!U$14,IF(_xlpm.amount=0,"",_xlpm.amount))} | I5: {=_xlfn.LET(_xlpm.amount,'Conditionals Helper'!V$14,IF(_xlpm.amount=0,"",_xlpm.amount))} | J5: {=_xlfn.LET(_xlpm.amount,'Conditionals Helper'!W$14,IF(_xlpm.amount=0,"",_xlpm.amount))} | K5: {=_xlfn.LET(_xlpm.amount,'Conditionals Helper'!X$14,IF(_xlpm.amount=0,"",_xlpm.amount))} | N5: Section Bar
A6: Major Master | B6: (Select) | C6: {=_xlfn.LET(_xlpm.amount,'Conditionals Helper'!P$28,IF(_xlpm.amount=0,"",_xlpm.amount))} | D6: {=_xlfn.LET(_xlpm.amount,'Conditionals Helper'!Q$28,IF(_xlpm.amount=0,"",_xlpm.amount))} | E6: {=_xlfn.LET(_xlpm.amount,'Conditionals Helper'!R$28,IF(_xlpm.amount=0,"",_xlpm.amount))} | F6: {=_xlfn.LET(_xlpm.amount,'Conditionals Helper'!S$28,IF(_xlpm.amount=0,"",_xlpm.amount))} | G6: {=_xlfn.LET(_xlpm.amount,'Conditionals Helper'!T$28,IF(_xlpm.amount=0,"",_xlpm.amount))} | H6: {=_xlfn.LET(_xlpm.amount,'Conditionals Helper'!U$28,IF(_xlpm.amount=0,"",_xlpm.amount))} | I6: {=_xlfn.LET(_xlpm.amount,'Conditionals Helper'!V$28,IF(_xlpm.amount=0,"",_xlpm.amount))} | J6: {=_xlfn.LET(_xlpm.amount,'Conditionals Helper'!W$28,IF(_xlpm.amount=0,"",_xlpm.amount))} | K6: {=_xlfn.LET(_xlpm.amount,'Conditionals Helper'!X$28,IF(_xlpm.amount=0,"",_xlpm.amount))} | N6: Subsection
A7: Major Grandmaster | B7: (Select) | C7: {=_xlfn.LET(_xlpm.amount,'Conditionals Helper'!P$42,IF(_xlpm.amount=0,"",_xlpm.amount))} | D7: {=_xlfn.LET(_xlpm.amount,'Conditionals Helper'!Q$42,IF(_xlpm.amount=0,"",_xlpm.amount))} | E7: {=_xlfn.LET(_xlpm.amount,'Conditionals Helper'!R$42,IF(_xlpm.amount=0,"",_xlpm.amount))} | F7: {=_xlfn.LET(_xlpm.amount,'Conditionals Helper'!S$42,IF(_xlpm.amount=0,"",_xlpm.amount))} | G7: {=_xlfn.LET(_xlpm.amount,'Conditionals Helper'!T$42,IF(_xlpm.amount=0,"",_xlpm.amount))} | H7: {=_xlfn.LET(_xlpm.amount,'Conditionals Helper'!U$42,IF(_xlpm.amount=0,"",_xlpm.amount))} | I7: {=_xlfn.LET(_xlpm.amount,'Conditionals Helper'!V$42,IF(_xlpm.amount=0,"",_xlpm.amount))} | J7: {=_xlfn.LET(_xlpm.amount,'Conditionals Helper'!W$42,IF(_xlpm.amount=0,"",_xlpm.amount))} | K7: {=_xlfn.LET(_xlpm.amount,'Conditionals Helper'!X$42,IF(_xlpm.amount=0,"",_xlpm.amount))} | N7: Category
A8: Specialisation 2 | B8: Inspiration | C8: {=_xlfn.LET(_xlpm.amount,'Conditionals Helper'!P129,IF(_xlpm.amount=0,"",_xlpm.amount))} | D8: {=_xlfn.LET(_xlpm.amount,'Conditionals Helper'!Q129,IF(_xlpm.amount=0,"",_xlpm.amount))} | E8: {=_xlfn.LET(_xlpm.amount,'Conditionals Helper'!R129,IF(_xlpm.amount=0,"",_xlpm.amount))} | F8: {=_xlfn.LET(_xlpm.amount,'Conditionals Helper'!S129,IF(_xlpm.amount=0,"",_xlpm.amount))} | G8: {=_xlfn.LET(_xlpm.amount,'Conditionals Helper'!T129,IF(_xlpm.amount=0,"",_xlpm.amount))} | H8: {=_xlfn.LET(_xlpm.amount,'Conditionals Helper'!U129,IF(_xlpm.amount=0,"",_xlpm.amount))} | I8: {=_xlfn.LET(_xlpm.amount,'Conditionals Helper'!V129,IF(_xlpm.amount=0,"",_xlpm.amount))} | J8: {=_xlfn.LET(_xlpm.amount,'Conditionals Helper'!W129,IF(_xlpm.amount=0,"",_xlpm.amount))} | K8: {=_xlfn.LET(_xlpm.amount,'Conditionals Helper'!X129,IF(_xlpm.amount=0,"",_xlpm.amount))} | N8: Input
A9: Major Adept | B9: (Select) | C9: {=_xlfn.LET(_xlpm.amount,'Conditionals Helper'!P$56,IF(_xlpm.amount=0,"",_xlpm.amount))} | D9: {=_xlfn.LET(_xlpm.amount,'Conditionals Helper'!Q$56,IF(_xlpm.amount=0,"",_xlpm.amount))} | E9: {=_xlfn.LET(_xlpm.amount,'Conditionals Helper'!R$56,IF(_xlpm.amount=0,"",_xlpm.amount))} | F9: {=_xlfn.LET(_xlpm.amount,'Conditionals Helper'!S$56,IF(_xlpm.amount=0,"",_xlpm.amount))} | G9: {=_xlfn.LET(_xlpm.amount,'Conditionals Helper'!T$56,IF(_xlpm.amount=0,"",_xlpm.amount))} | H9: {=_xlfn.LET(_xlpm.amount,'Conditionals Helper'!U$56,IF(_xlpm.amount=0,"",_xlpm.amount))} | I9: {=_xlfn.LET(_xlpm.amount,'Conditionals Helper'!V$56,IF(_xlpm.amount=0,"",_xlpm.amount))} | J9: {=_xlfn.LET(_xlpm.amount,'Conditionals Helper'!W$56,IF(_xlpm.amount=0,"",_xlpm.amount))} | K9: {=_xlfn.LET(_xlpm.amount,'Conditionals Helper'!X$56,IF(_xlpm.amount=0,"",_xlpm.amount))} | N9: Major Stat/Celestial
A10: Major Master | B10: Warden's Feedback | C10: {=_xlfn.LET(_xlpm.amount,'Conditionals Helper'!P$70,IF(_xlpm.amount=0,"",_xlpm.amount))} | D10: {=_xlfn.LET(_xlpm.amount,'Conditionals Helper'!Q$70,IF(_xlpm.amount=0,"",_xlpm.amount))} | E10: {=_xlfn.LET(_xlpm.amount,'Conditionals Helper'!R$70,IF(_xlpm.amount=0,"",_xlpm.amount))} | F10: {=_xlfn.LET(_xlpm.amount,'Conditionals Helper'!S$70,IF(_xlpm.amount=0,"",_xlpm.amount))} | G10: {=_xlfn.LET(_xlpm.amount,'Conditionals Helper'!T$70,IF(_xlpm.amount=0,"",_xlpm.amount))} | H10: {=_xlfn.LET(_xlpm.amount,'Conditionals Helper'!U$70,IF(_xlpm.amount=0,"",_xlpm.amount))} | I10: {=_xlfn.LET(_xlpm.amount,'Conditionals Helper'!V$70,IF(_xlpm.amount=0,"",_xlpm.amount))} | J10: {=_xlfn.LET(_xlpm.amount,'Conditionals Helper'!W$70,IF(_xlpm.amount=0,"",_xlpm.amount))} | K10: {=_xlfn.LET(_xlpm.amount,'Conditionals Helper'!X$70,IF(_xlpm.amount=0,"",_xlpm.amount))} | N10: Minor Stat
A11: Major Grandmaster | B11: (Select) | C11: {=_xlfn.LET(_xlpm.amount,'Conditionals Helper'!P$84,IF(_xlpm.amount=0,"",_xlpm.amount))} | D11: {=_xlfn.LET(_xlpm.amount,'Conditionals Helper'!Q$84,IF(_xlpm.amount=0,"",_xlpm.amount))} | E11: {=_xlfn.LET(_xlpm.amount,'Conditionals Helper'!R$84,IF(_xlpm.amount=0,"",_xlpm.amount))} | F11: {=_xlfn.LET(_xlpm.amount,'Conditionals Helper'!S$84,IF(_xlpm.amount=0,"",_xlpm.amount))} | G11: {=_xlfn.LET(_xlpm.amount,'Conditionals Helper'!T$84,IF(_xlpm.amount=0,"",_xlpm.amount))} | H11: {=_xlfn.LET(_xlpm.amount,'Conditionals Helper'!U$84,IF(_xlpm.amount=0,"",_xlpm.amount))} | I11: {=_xlfn.LET(_xlpm.amount,'Conditionals Helper'!V$84,IF(_xlpm.amount=0,"",_xlpm.amount))} | J11: {=_xlfn.LET(_xlpm.amount,'Conditionals Helper'!W$84,IF(_xlpm.amount=0,"",_xlpm.amount))} | K11: {=_xlfn.LET(_xlpm.amount,'Conditionals Helper'!X$84,IF(_xlpm.amount=0,"",_xlpm.amount))} | N11: Incompatible
A12: Specialisation 3 | B12: Troubadour | C12: {=_xlfn.LET(_xlpm.amount,'Conditionals Helper'!P130,IF(_xlpm.amount=0,"",_xlpm.amount))} | D12: {=_xlfn.LET(_xlpm.amount,'Conditionals Helper'!Q130,IF(_xlpm.amount=0,"",_xlpm.amount))} | E12: {=_xlfn.LET(_xlpm.amount,'Conditionals Helper'!R130,IF(_xlpm.amount=0,"",_xlpm.amount))} | F12: {=_xlfn.LET(_xlpm.amount,'Conditionals Helper'!S130,IF(_xlpm.amount=0,"",_xlpm.amount))} | G12: {=_xlfn.LET(_xlpm.amount,'Conditionals Helper'!T130,IF(_xlpm.amount=0,"",_xlpm.amount))} | H12: {=_xlfn.LET(_xlpm.amount,'Conditionals Helper'!U130,IF(_xlpm.amount=0,"",_xlpm.amount))} -> 62.4 | I12: {=_xlfn.LET(_xlpm.amount,'Conditionals Helper'!V130,IF(_xlpm.amount=0,"",_xlpm.amount))} | J12: {=_xlfn.LET(_xlpm.amount,'Conditionals Helper'!W130,IF(_xlpm.amount=0,"",_xlpm.amount))} | K12: {=_xlfn.LET(_xlpm.amount,'Conditionals Helper'!X130,IF(_xlpm.amount=0,"",_xlpm.amount))}
A13: Major Adept | B13: Illusionary Defense | C13: {=_xlfn.LET(_xlpm.amount,'Conditionals Helper'!P$98,IF(_xlpm.amount=0,"",_xlpm.amount))} | D13: {=_xlfn.LET(_xlpm.amount,'Conditionals Helper'!Q$98,IF(_xlpm.amount=0,"",_xlpm.amount))} | E13: {=_xlfn.LET(_xlpm.amount,'Conditionals Helper'!R$98,IF(_xlpm.amount=0,"",_xlpm.amount))} | F13: {=_xlfn.LET(_xlpm.amount,'Conditionals Helper'!S$98,IF(_xlpm.amount=0,"",_xlpm.amount))} | G13: {=_xlfn.LET(_xlpm.amount,'Conditionals Helper'!T$98,IF(_xlpm.amount=0,"",_xlpm.amount))} | H13: {=_xlfn.LET(_xlpm.amount,'Conditionals Helper'!U$98,IF(_xlpm.amount=0,"",_xlpm.amount))} | I13: {=_xlfn.LET(_xlpm.amount,'Conditionals Helper'!V$98,IF(_xlpm.amount=0,"",_xlpm.amount))} | J13: {=_xlfn.LET(_xlpm.amount,'Conditionals Helper'!W$98,IF(_xlpm.amount=0,"",_xlpm.amount))} | K13: {=_xlfn.LET(_xlpm.amount,'Conditionals Helper'!X$98,IF(_xlpm.amount=0,"",_xlpm.amount))}
A14: Major Master | B14: (Select) | C14: {=_xlfn.LET(_xlpm.amount,'Conditionals Helper'!P$112,IF(_xlpm.amount=0,"",_xlpm.amount))} | D14: {=_xlfn.LET(_xlpm.amount,'Conditionals Helper'!Q$112,IF(_xlpm.amount=0,"",_xlpm.amount))} | E14: {=_xlfn.LET(_xlpm.amount,'Conditionals Helper'!R$112,IF(_xlpm.amount=0,"",_xlpm.amount))} | F14: {=_xlfn.LET(_xlpm.amount,'Conditionals Helper'!S$112,IF(_xlpm.amount=0,"",_xlpm.amount))} | G14: {=_xlfn.LET(_xlpm.amount,'Conditionals Helper'!T$112,IF(_xlpm.amount=0,"",_xlpm.amount))} | H14: {=_xlfn.LET(_xlpm.amount,'Conditionals Helper'!U$112,IF(_xlpm.amount=0,"",_xlpm.amount))} | I14: {=_xlfn.LET(_xlpm.amount,'Conditionals Helper'!V$112,IF(_xlpm.amount=0,"",_xlpm.amount))} | J14: {=_xlfn.LET(_xlpm.amount,'Conditionals Helper'!W$112,IF(_xlpm.amount=0,"",_xlpm.amount))} | K14: {=_xlfn.LET(_xlpm.amount,'Conditionals Helper'!X$112,IF(_xlpm.amount=0,"",_xlpm.amount))}
A15: Major Grandmaster | B15: (Select) | C15: {=_xlfn.LET(_xlpm.amount,'Conditionals Helper'!P$126,IF(_xlpm.amount=0,"",_xlpm.amount))} | D15: {=_xlfn.LET(_xlpm.amount,'Conditionals Helper'!Q$126,IF(_xlpm.amount=0,"",_xlpm.amount))} | E15: {=_xlfn.LET(_xlpm.amount,'Conditionals Helper'!R$126,IF(_xlpm.amount=0,"",_xlpm.amount))} | F15: {=_xlfn.LET(_xlpm.amount,'Conditionals Helper'!S$126,IF(_xlpm.amount=0,"",_xlpm.amount))} | G15: {=_xlfn.LET(_xlpm.amount,'Conditionals Helper'!T$126,IF(_xlpm.amount=0,"",_xlpm.amount))} | H15: {=_xlfn.LET(_xlpm.amount,'Conditionals Helper'!U$126,IF(_xlpm.amount=0,"",_xlpm.amount))} | I15: {=_xlfn.LET(_xlpm.amount,'Conditionals Helper'!V$126,IF(_xlpm.amount=0,"",_xlpm.amount))} | J15: {=_xlfn.LET(_xlpm.amount,'Conditionals Helper'!W$126,IF(_xlpm.amount=0,"",_xlpm.amount))} | K15: {=_xlfn.LET(_xlpm.amount,'Conditionals Helper'!X$126,IF(_xlpm.amount=0,"",_xlpm.amount))}
A16: Gear | C16: Power | D16: Precision | E16: Toughness | F16: Vitality | G16: Concentration | H16: Condition Damage | I16: Expertise | J16: Ferocity | K16: Healing Power | L16: Defence
A17: Weapon (1H) | B17: Assassin | C17: =IF(AND(COUNTBLANK($B17)=0,NOT($B17="(Select)")), VLOOKUP(_xlfn.CONCAT($B17, $A17), GearValues, 4, 0), " ") -> 85 | D17: =IF(AND(COUNTBLANK($B17)=0,NOT($B17="(Select)")), VLOOKUP(_xlfn.CONCAT($B17, $A17), GearValues, 5, 0), " ") -> 120 | E17: =IF(AND(COUNTBLANK($B17)=0,NOT($B17="(Select)")), VLOOKUP(_xlfn.CONCAT($B17, $A17), GearValues, 6, 0), " ") | F17: =IF(AND(COUNTBLANK($B17)=0,NOT($B17="(Select)")), VLOOKUP(_xlfn.CONCAT($B17, $A17), GearValues, 7, 0), " ") | G17: =IF(AND(COUNTBLANK($B17)=0,NOT($B17="(Select)")), VLOOKUP(_xlfn.CONCAT($B17, $A17), GearValues, 8, 0), " ") | H17: =IF(AND(COUNTBLANK($B17)=0,NOT($B17="(Select)")), VLOOKUP(_xlfn.CONCAT($B17, $A17), GearValues, 9, 0), " ") | I17: =IF(AND(COUNTBLANK($B17)=0,NOT($B17="(Select)")), VLOOKUP(_xlfn.CONCAT($B17, $A17), GearValues, 10, 0), " ") | J17: =IF(AND(COUNTBLANK($B17)=0,NOT($B17="(Select)")), VLOOKUP(_xlfn.CONCAT($B17, $A17), GearValues, 11, 0), " ") -> 85 | K17: =IF(AND(COUNTBLANK($B17)=0,NOT($B17="(Select)")), VLOOKUP(_xlfn.CONCAT($B17, $A17), GearValues, 12, 0), " ")
A18: Weapon (1H) | B18: Assassin | C18: =IF(AND(COUNTBLANK($B18)=0,NOT($B18="(Select)")), VLOOKUP(_xlfn.CONCAT($B18, $A18), GearValues, 4, 0), " ") -> 85 | D18: =IF(AND(COUNTBLANK($B18)=0,NOT($B18="(Select)")), VLOOKUP(_xlfn.CONCAT($B18, $A18), GearValues, 5, 0), " ") -> 120 | E18: =IF(AND(COUNTBLANK($B18)=0,NOT($B18="(Select)")), VLOOKUP(_xlfn.CONCAT($B18, $A18), GearValues, 6, 0), " ") | F18: =IF(AND(COUNTBLANK($B18)=0,NOT($B18="(Select)")), VLOOKUP(_xlfn.CONCAT($B18, $A18), GearValues, 7, 0), " ") | G18: =IF(AND(COUNTBLANK($B18)=0,NOT($B18="(Select)")), VLOOKUP(_xlfn.CONCAT($B18, $A18), GearValues, 8, 0), " ") | H18: =IF(AND(COUNTBLANK($B18)=0,NOT($B18="(Select)")), VLOOKUP(_xlfn.CONCAT($B18, $A18), GearValues, 9, 0), " ") | I18: =IF(AND(COUNTBLANK($B18)=0,NOT($B18="(Select)")), VLOOKUP(_xlfn.CONCAT($B18, $A18), GearValues, 10, 0), " ") | J18: =IF(AND(COUNTBLANK($B18)=0,NOT($B18="(Select)")), VLOOKUP(_xlfn.CONCAT($B18, $A18), GearValues, 11, 0), " ") -> 85 | K18: =IF(AND(COUNTBLANK($B18)=0,NOT($B18="(Select)")), VLOOKUP(_xlfn.CONCAT($B18, $A18), GearValues, 12, 0), " ")
A19: Weapon (2H) | B19: (Select) | C19: =IF(AND(COUNTBLANK($B19)=0,NOT($B19="(Select)")), VLOOKUP(_xlfn.CONCAT($B19, $A19), GearValues, 4, 0), " ") | D19: =IF(AND(COUNTBLANK($B19)=0,NOT($B19="(Select)")), VLOOKUP(_xlfn.CONCAT($B19, $A19), GearValues, 5, 0), " ") | E19: =IF(AND(COUNTBLANK($B19)=0,NOT($B19="(Select)")), VLOOKUP(_xlfn.CONCAT($B19, $A19), GearValues, 6, 0), " ") | F19: =IF(AND(COUNTBLANK($B19)=0,NOT($B19="(Select)")), VLOOKUP(_xlfn.CONCAT($B19, $A19), GearValues, 7, 0), " ") | G19: =IF(AND(COUNTBLANK($B19)=0,NOT($B19="(Select)")), VLOOKUP(_xlfn.CONCAT($B19, $A19), GearValues, 8, 0), " ") | H19: =IF(AND(COUNTBLANK($B19)=0,NOT($B19="(Select)")), VLOOKUP(_xlfn.CONCAT($B19, $A19), GearValues, 9, 0), " ") | I19: =IF(AND(COUNTBLANK($B19)=0,NOT($B19="(Select)")), VLOOKUP(_xlfn.CONCAT($B19, $A19), GearValues, 10, 0), " ") | J19: =IF(AND(COUNTBLANK($B19)=0,NOT($B19="(Select)")), VLOOKUP(_xlfn.CONCAT($B19, $A19), GearValues, 11, 0), " ") | K19: =IF(AND(COUNTBLANK($B19)=0,NOT($B19="(Select)")), VLOOKUP(_xlfn.CONCAT($B19, $A19), GearValues, 12, 0), " ")
A20: Head | B20: Captain | C20: =IF(AND(COUNTBLANK($B20)=0,NOT($B20="(Select)")), VLOOKUP(_xlfn.CONCAT($B20, $A20), GearValues, 4, 0), " ") -> 43 | D20: =IF(AND(COUNTBLANK($B20)=0,NOT($B20="(Select)")), VLOOKUP(_xlfn.CONCAT($B20, $A20), GearValues, 5, 0), " ") -> 60 | E20: =IF(AND(COUNTBLANK($B20)=0,NOT($B20="(Select)")), VLOOKUP(_xlfn.CONCAT($B20, $A20), GearValues, 6, 0), " ") -> 43 | F20: =IF(AND(COUNTBLANK($B20)=0,NOT($B20="(Select)")), VLOOKUP(_xlfn.CONCAT($B20, $A20), GearValues, 7, 0), " ") | G20: =IF(AND(COUNTBLANK($B20)=0,NOT($B20="(Select)")), VLOOKUP(_xlfn.CONCAT($B20, $A20), GearValues, 8, 0), " ") | H20: =IF(AND(COUNTBLANK($B20)=0,NOT($B20="(Select)")), VLOOKUP(_xlfn.CONCAT($B20, $A20), GearValues, 9, 0), " ") | I20: =IF(AND(COUNTBLANK($B20)=0,NOT($B20="(Select)")), VLOOKUP(_xlfn.CONCAT($B20, $A20), GearValues, 10, 0), " ") | J20: =IF(AND(COUNTBLANK($B20)=0,NOT($B20="(Select)")), VLOOKUP(_xlfn.CONCAT($B20, $A20), GearValues, 11, 0), " ") | K20: =IF(AND(COUNTBLANK($B20)=0,NOT($B20="(Select)")), VLOOKUP(_xlfn.CONCAT($B20, $A20), GearValues, 12, 0), " ") | L20: =IF(AND(COUNTBLANK($B20)=0,NOT($B20="(Select)")),VLOOKUP($A20,'Gear Values'!$A$17:$D$23,MATCH(ArmourType,'Gear Values'!$A$16:$D$16,0),0),"") -> 97
A21: Shoulders | B21: Apostate | C21: =IF(AND(COUNTBLANK($B21)=0,NOT($B21="(Select)")), VLOOKUP(_xlfn.CONCAT($B21, $A21), GearValues, 4, 0), " ") | D21: =IF(AND(COUNTBLANK($B21)=0,NOT($B21="(Select)")), VLOOKUP(_xlfn.CONCAT($B21, $A21), GearValues, 5, 0), " ") | E21: =IF(AND(COUNTBLANK($B21)=0,NOT($B21="(Select)")), VLOOKUP(_xlfn.CONCAT($B21, $A21), GearValues, 6, 0), " ") -> 32 | F21: =IF(AND(COUNTBLANK($B21)=0,NOT($B21="(Select)")), VLOOKUP(_xlfn.CONCAT($B21, $A21), GearValues, 7, 0), " ") | G21: =IF(AND(COUNTBLANK($B21)=0,NOT($B21="(Select)")), VLOOKUP(_xlfn.CONCAT($B21, $A21), GearValues, 8, 0), " ") | H21: =IF(AND(COUNTBLANK($B21)=0,NOT($B21="(Select)")), VLOOKUP(_xlfn.CONCAT($B21, $A21), GearValues, 9, 0), " ") -> 45 | I21: =IF(AND(COUNTBLANK($B21)=0,NOT($B21="(Select)")), VLOOKUP(_xlfn.CONCAT($B21, $A21), GearValues, 10, 0), " ") | J21: =IF(AND(COUNTBLANK($B21)=0,NOT($B21="(Select)")), VLOOKUP(_xlfn.CONCAT($B21, $A21), GearValues, 11, 0), " ") | K21: =IF(AND(COUNTBLANK($B21)=0,NOT($B21="(Select)")), VLOOKUP(_xlfn.CONCAT($B21, $A21), GearValues, 12, 0), " ") -> 32 | L21: =IF(AND(COUNTBLANK($B21)=0,NOT($B21="(Select)")),VLOOKUP($A21,'Gear Values'!$A$17:$D$23,MATCH(ArmourType,'Gear Values'!$A$16:$D$16,0),0),"") -> 97
A22: Chest | B22: Captain | C22: =IF(AND(COUNTBLANK($B22)=0,NOT($B22="(Select)")), VLOOKUP(_xlfn.CONCAT($B22, $A22), GearValues, 4, 0), " ") -> 96 | D22: =IF(AND(COUNTBLANK($B22)=0,NOT($B22="(Select)")), VLOOKUP(_xlfn.CONCAT($B22, $A22), GearValues, 5, 0), " ") -> 134 | E22: =IF(AND(COUNTBLANK($B22)=0,NOT($B22="(Select)")), VLOOKUP(_xlfn.CONCAT($B22, $A22), GearValues, 6, 0), " ") -> 96 | F22: =IF(AND(COUNTBLANK($B22)=0,NOT($B22="(Select)")), VLOOKUP(_xlfn.CONCAT($B22, $A22), GearValues, 7, 0), " ") | G22: =IF(AND(COUNTBLANK($B22)=0,NOT($B22="(Select)")), VLOOKUP(_xlfn.CONCAT($B22, $A22), GearValues, 8, 0), " ") | H22: =IF(AND(COUNTBLANK($B22)=0,NOT($B22="(Select)")), VLOOKUP(_xlfn.CONCAT($B22, $A22), GearValues, 9, 0), " ") | I22: =IF(AND(COUNTBLANK($B22)=0,NOT($B22="(Select)")), VLOOKUP(_xlfn.CONCAT($B22, $A22), GearValues, 10, 0), " ") | J22: =IF(AND(COUNTBLANK($B22)=0,NOT($B22="(Select)")), VLOOKUP(_xlfn.CONCAT($B22, $A22), GearValues, 11, 0), " ") | K22: =IF(AND(COUNTBLANK($B22)=0,NOT($B22="(Select)")), VLOOKUP(_xlfn.CONCAT($B22, $A22), GearValues, 12, 0), " ") | L22: =IF(AND(COUNTBLANK($B22)=0,NOT($B22="(Select)")),VLOOKUP($A22,'Gear Values'!$A$17:$D$23,MATCH(ArmourType,'Gear Values'!$A$16:$D$16,0),0),"") -> 338
A23: Hands | B23: Marauder | C23: =IF(AND(COUNTBLANK($B23)=0,NOT($B23="(Select)")), VLOOKUP(_xlfn.CONCAT($B23, $A23), GearValues, 4, 0), " ") -> 38 | D23: =IF(AND(COUNTBLANK($B23)=0,NOT($B23="(Select)")), VLOOKUP(_xlfn.CONCAT($B23, $A23), GearValues, 5, 0), " ") -> 38 | E23: =IF(AND(COUNTBLANK($B23)=0,NOT($B23="(Select)")), VLOOKUP(_xlfn.CONCAT($B23, $A23), GearValues, 6, 0), " ") | F23: =IF(AND(COUNTBLANK($B23)=0,NOT($B23="(Select)")), VLOOKUP(_xlfn.CONCAT($B23, $A23), GearValues, 7, 0), " ") -> 21 | G23: =IF(AND(COUNTBLANK($B23)=0,NOT($B23="(Select)")), VLOOKUP(_xlfn.CONCAT($B23, $A23), GearValues, 8, 0), " ") | H23: =IF(AND(COUNTBLANK($B23)=0,NOT($B23="(Select)")), VLOOKUP(_xlfn.CONCAT($B23, $A23), GearValues, 9, 0), " ") | I23: =IF(AND(COUNTBLANK($B23)=0,NOT($B23="(Select)")), VLOOKUP(_xlfn.CONCAT($B23, $A23), GearValues, 10, 0), " ") | J23: =IF(AND(COUNTBLANK($B23)=0,NOT($B23="(Select)")), VLOOKUP(_xlfn.CONCAT($B23, $A23), GearValues, 11, 0), " ") -> 21 | K23: =IF(AND(COUNTBLANK($B23)=0,NOT($B23="(Select)")), VLOOKUP(_xlfn.CONCAT($B23, $A23), GearValues, 12, 0), " ") | L23: =IF(AND(COUNTBLANK($B23)=0,NOT($B23="(Select)")),VLOOKUP($A23,'Gear Values'!$A$17:$D$23,MATCH(ArmourType,'Gear Values'!$A$16:$D$16,0),0),"") -> 157
A24: Legs | B24: Marauder | C24: =IF(AND(COUNTBLANK($B24)=0,NOT($B24="(Select)")), VLOOKUP(_xlfn.CONCAT($B24, $A24), GearValues, 4, 0), " ") -> 77 | D24: =IF(AND(COUNTBLANK($B24)=0,NOT($B24="(Select)")), VLOOKUP(_xlfn.CONCAT($B24, $A24), GearValues, 5, 0), " ") -> 77 | E24: =IF(AND(COUNTBLANK($B24)=0,NOT($B24="(Select)")), VLOOKUP(_xlfn.CONCAT($B24, $A24), GearValues, 6, 0), " ") | F24: =IF(AND(COUNTBLANK($B24)=0,NOT($B24="(Select)")), VLOOKUP(_xlfn.CONCAT($B24, $A24), GearValues, 7, 0), " ") -> 42 | G24: =IF(AND(COUNTBLANK($B24)=0,NOT($B24="(Select)")), VLOOKUP(_xlfn.CONCAT($B24, $A24), GearValues, 8, 0), " ") | H24: =IF(AND(COUNTBLANK($B24)=0,NOT($B24="(Select)")), VLOOKUP(_xlfn.CONCAT($B24, $A24), GearValues, 9, 0), " ") | I24: =IF(AND(COUNTBLANK($B24)=0,NOT($B24="(Select)")), VLOOKUP(_xlfn.CONCAT($B24, $A24), GearValues, 10, 0), " ") | J24: =IF(AND(COUNTBLANK($B24)=0,NOT($B24="(Select)")), VLOOKUP(_xlfn.CONCAT($B24, $A24), GearValues, 11, 0), " ") -> 42 | K24: =IF(AND(COUNTBLANK($B24)=0,NOT($B24="(Select)")), VLOOKUP(_xlfn.CONCAT($B24, $A24), GearValues, 12, 0), " ") | L24: =IF(AND(COUNTBLANK($B24)=0,NOT($B24="(Select)")),VLOOKUP($A24,'Gear Values'!$A$17:$D$23,MATCH(ArmourType,'Gear Values'!$A$16:$D$16,0),0),"") -> 218
A25: Feet | B25: (Select) | C25: =IF(AND(COUNTBLANK($B25)=0,NOT($B25="(Select)")), VLOOKUP(_xlfn.CONCAT($B25, $A25), GearValues, 4, 0), " ") | D25: =IF(AND(COUNTBLANK($B25)=0,NOT($B25="(Select)")), VLOOKUP(_xlfn.CONCAT($B25, $A25), GearValues, 5, 0), " ") | E25: =IF(AND(COUNTBLANK($B25)=0,NOT($B25="(Select)")), VLOOKUP(_xlfn.CONCAT($B25, $A25), GearValues, 6, 0), " ") | F25: =IF(AND(COUNTBLANK($B25)=0,NOT($B25="(Select)")), VLOOKUP(_xlfn.CONCAT($B25, $A25), GearValues, 7, 0), " ") | G25: =IF(AND(COUNTBLANK($B25)=0,NOT($B25="(Select)")), VLOOKUP(_xlfn.CONCAT($B25, $A25), GearValues, 8, 0), " ") | H25: =IF(AND(COUNTBLANK($B25)=0,NOT($B25="(Select)")), VLOOKUP(_xlfn.CONCAT($B25, $A25), GearValues, 9, 0), " ") | I25: =IF(AND(COUNTBLANK($B25)=0,NOT($B25="(Select)")), VLOOKUP(_xlfn.CONCAT($B25, $A25), GearValues, 10, 0), " ") | J25: =IF(AND(COUNTBLANK($B25)=0,NOT($B25="(Select)")), VLOOKUP(_xlfn.CONCAT($B25, $A25), GearValues, 11, 0), " ") | K25: =IF(AND(COUNTBLANK($B25)=0,NOT($B25="(Select)")), VLOOKUP(_xlfn.CONCAT($B25, $A25), GearValues, 12, 0), " ") | L25: =IF(AND(COUNTBLANK($B25)=0,NOT($B25="(Select)")),VLOOKUP($A25,'Gear Values'!$A$17:$D$23,MATCH(ArmourType,'Gear Values'!$A$16:$D$16,0),0),"")
A26: Ear | B26: (Select) | C26: =IF(AND(COUNTBLANK($B26)=0,NOT($B26="(Select)")), VLOOKUP(_xlfn.CONCAT($B26, $A26), GearValues, 4, 0), " ") | D26: =IF(AND(COUNTBLANK($B26)=0,NOT($B26="(Select)")), VLOOKUP(_xlfn.CONCAT($B26, $A26), GearValues, 5, 0), " ") | E26: =IF(AND(COUNTBLANK($B26)=0,NOT($B26="(Select)")), VLOOKUP(_xlfn.CONCAT($B26, $A26), GearValues, 6, 0), " ") | F26: =IF(AND(COUNTBLANK($B26)=0,NOT($B26="(Select)")), VLOOKUP(_xlfn.CONCAT($B26, $A26), GearValues, 7, 0), " ") | G26: =IF(AND(COUNTBLANK($B26)=0,NOT($B26="(Select)")), VLOOKUP(_xlfn.CONCAT($B26, $A26), GearValues, 8, 0), " ") | H26: =IF(AND(COUNTBLANK($B26)=0,NOT($B26="(Select)")), VLOOKUP(_xlfn.CONCAT($B26, $A26), GearValues, 9, 0), " ") | I26: =IF(AND(COUNTBLANK($B26)=0,NOT($B26="(Select)")), VLOOKUP(_xlfn.CONCAT($B26, $A26), GearValues, 10, 0), " ") | J26: =IF(AND(COUNTBLANK($B26)=0,NOT($B26="(Select)")), VLOOKUP(_xlfn.CONCAT($B26, $A26), GearValues, 11, 0), " ") | K26: =IF(AND(COUNTBLANK($B26)=0,NOT($B26="(Select)")), VLOOKUP(_xlfn.CONCAT($B26, $A26), GearValues, 12, 0), " ")
A27: Ear | B27: Chrysocola | C27: =IF(AND(COUNTBLANK($B27)=0,NOT($B27="(Select)")), VLOOKUP(_xlfn.CONCAT($B27, $A27), GearValues, 4, 0), " ") -> 53 | D27: =IF(AND(COUNTBLANK($B27)=0,NOT($B27="(Select)")), VLOOKUP(_xlfn.CONCAT($B27, $A27), GearValues, 5, 0), " ") | E27: =IF(AND(COUNTBLANK($B27)=0,NOT($B27="(Select)")), VLOOKUP(_xlfn.CONCAT($B27, $A27), GearValues, 6, 0), " ") | F27: =IF(AND(COUNTBLANK($B27)=0,NOT($B27="(Select)")), VLOOKUP(_xlfn.CONCAT($B27, $A27), GearValues, 7, 0), " ") -> 53 | G27: =IF(AND(COUNTBLANK($B27)=0,NOT($B27="(Select)")), VLOOKUP(_xlfn.CONCAT($B27, $A27), GearValues, 8, 0), " ") | H27: =IF(AND(COUNTBLANK($B27)=0,NOT($B27="(Select)")), VLOOKUP(_xlfn.CONCAT($B27, $A27), GearValues, 9, 0), " ") -> 75 | I27: =IF(AND(COUNTBLANK($B27)=0,NOT($B27="(Select)")), VLOOKUP(_xlfn.CONCAT($B27, $A27), GearValues, 10, 0), " ") | J27: =IF(AND(COUNTBLANK($B27)=0,NOT($B27="(Select)")), VLOOKUP(_xlfn.CONCAT($B27, $A27), GearValues, 11, 0), " ") | K27: =IF(AND(COUNTBLANK($B27)=0,NOT($B27="(Select)")), VLOOKUP(_xlfn.CONCAT($B27, $A27), GearValues, 12, 0), " ")
A28: Finger | B28: (Select) | C28: =IF(AND(COUNTBLANK($B28)=0,NOT($B28="(Select)")), VLOOKUP(_xlfn.CONCAT($B28, $A28), GearValues, 4, 0), " ") | D28: =IF(AND(COUNTBLANK($B28)=0,NOT($B28="(Select)")), VLOOKUP(_xlfn.CONCAT($B28, $A28), GearValues, 5, 0), " ") | E28: =IF(AND(COUNTBLANK($B28)=0,NOT($B28="(Select)")), VLOOKUP(_xlfn.CONCAT($B28, $A28), GearValues, 6, 0), " ") | F28: =IF(AND(COUNTBLANK($B28)=0,NOT($B28="(Select)")), VLOOKUP(_xlfn.CONCAT($B28, $A28), GearValues, 7, 0), " ") | G28: =IF(AND(COUNTBLANK($B28)=0,NOT($B28="(Select)")), VLOOKUP(_xlfn.CONCAT($B28, $A28), GearValues, 8, 0), " ") | H28: =IF(AND(COUNTBLANK($B28)=0,NOT($B28="(Select)")), VLOOKUP(_xlfn.CONCAT($B28, $A28), GearValues, 9, 0), " ") | I28: =IF(AND(COUNTBLANK($B28)=0,NOT($B28="(Select)")), VLOOKUP(_xlfn.CONCAT($B28, $A28), GearValues, 10, 0), " ") | J28: =IF(AND(COUNTBLANK($B28)=0,NOT($B28="(Select)")), VLOOKUP(_xlfn.CONCAT($B28, $A28), GearValues, 11, 0), " ") | K28: =IF(AND(COUNTBLANK($B28)=0,NOT($B28="(Select)")), VLOOKUP(_xlfn.CONCAT($B28, $A28), GearValues, 12, 0), " ")
A29: Finger | B29: (Select) | C29: =IF(AND(COUNTBLANK($B29)=0,NOT($B29="(Select)")), VLOOKUP(_xlfn.CONCAT($B29, $A29), GearValues, 4, 0), " ") | D29: =IF(AND(COUNTBLANK($B29)=0,NOT($B29="(Select)")), VLOOKUP(_xlfn.CONCAT($B29, $A29), GearValues, 5, 0), " ") | E29: =IF(AND(COUNTBLANK($B29)=0,NOT($B29="(Select)")), VLOOKUP(_xlfn.CONCAT($B29, $A29), GearValues, 6, 0), " ") | F29: =IF(AND(COUNTBLANK($B29)=0,NOT($B29="(Select)")), VLOOKUP(_xlfn.CONCAT($B29, $A29), GearValues, 7, 0), " ") | G29: =IF(AND(COUNTBLANK($B29)=0,NOT($B29="(Select)")), VLOOKUP(_xlfn.CONCAT($B29, $A29), GearValues, 8, 0), " ") | H29: =IF(AND(COUNTBLANK($B29)=0,NOT($B29="(Select)")), VLOOKUP(_xlfn.CONCAT($B29, $A29), GearValues, 9, 0), " ") | I29: =IF(AND(COUNTBLANK($B29)=0,NOT($B29="(Select)")), VLOOKUP(_xlfn.CONCAT($B29, $A29), GearValues, 10, 0), " ") | J29: =IF(AND(COUNTBLANK($B29)=0,NOT($B29="(Select)")), VLOOKUP(_xlfn.CONCAT($B29, $A29), GearValues, 11, 0), " ") | K29: =IF(AND(COUNTBLANK($B29)=0,NOT($B29="(Select)")), VLOOKUP(_xlfn.CONCAT($B29, $A29), GearValues, 12, 0), " ")
A30: Neck | B30: (Select) | C30: =IF(AND(COUNTBLANK($B30)=0,NOT($B30="(Select)")), VLOOKUP(_xlfn.CONCAT($B30, $A30), GearValues, 4, 0), " ") | D30: =IF(AND(COUNTBLANK($B30)=0,NOT($B30="(Select)")), VLOOKUP(_xlfn.CONCAT($B30, $A30), GearValues, 5, 0), " ") | E30: =IF(AND(COUNTBLANK($B30)=0,NOT($B30="(Select)")), VLOOKUP(_xlfn.CONCAT($B30, $A30), GearValues, 6, 0), " ") | F30: =IF(AND(COUNTBLANK($B30)=0,NOT($B30="(Select)")), VLOOKUP(_xlfn.CONCAT($B30, $A30), GearValues, 7, 0), " ") | G30: =IF(AND(COUNTBLANK($B30)=0,NOT($B30="(Select)")), VLOOKUP(_xlfn.CONCAT($B30, $A30), GearValues, 8, 0), " ") | H30: =IF(AND(COUNTBLANK($B30)=0,NOT($B30="(Select)")), VLOOKUP(_xlfn.CONCAT($B30, $A30), GearValues, 9, 0), " ") | I30: =IF(AND(COUNTBLANK($B30)=0,NOT($B30="(Select)")), VLOOKUP(_xlfn.CONCAT($B30, $A30), GearValues, 10, 0), " ") | J30: =IF(AND(COUNTBLANK($B30)=0,NOT($B30="(Select)")), VLOOKUP(_xlfn.CONCAT($B30, $A30), GearValues, 11, 0), " ") | K30: =IF(AND(COUNTBLANK($B30)=0,NOT($B30="(Select)")), VLOOKUP(_xlfn.CONCAT($B30, $A30), GearValues, 12, 0), " ")
A31: Back | B31: (Select) | C31: =IF(AND(COUNTBLANK($B31)=0,NOT($B31="(Select)")), VLOOKUP(_xlfn.CONCAT($B31, $A31), GearValues, 4, 0), " ") | D31: =IF(AND(COUNTBLANK($B31)=0,NOT($B31="(Select)")), VLOOKUP(_xlfn.CONCAT($B31, $A31), GearValues, 5, 0), " ") | E31: =IF(AND(COUNTBLANK($B31)=0,NOT($B31="(Select)")), VLOOKUP(_xlfn.CONCAT($B31, $A31), GearValues, 6, 0), " ") | F31: =IF(AND(COUNTBLANK($B31)=0,NOT($B31="(Select)")), VLOOKUP(_xlfn.CONCAT($B31, $A31), GearValues, 7, 0), " ") | G31: =IF(AND(COUNTBLANK($B31)=0,NOT($B31="(Select)")), VLOOKUP(_xlfn.CONCAT($B31, $A31), GearValues, 8, 0), " ") | H31: =IF(AND(COUNTBLANK($B31)=0,NOT($B31="(Select)")), VLOOKUP(_xlfn.CONCAT($B31, $A31), GearValues, 9, 0), " ") | I31: =IF(AND(COUNTBLANK($B31)=0,NOT($B31="(Select)")), VLOOKUP(_xlfn.CONCAT($B31, $A31), GearValues, 10, 0), " ") | J31: =IF(AND(COUNTBLANK($B31)=0,NOT($B31="(Select)")), VLOOKUP(_xlfn.CONCAT($B31, $A31), GearValues, 11, 0), " ") | K31: =IF(AND(COUNTBLANK($B31)=0,NOT($B31="(Select)")), VLOOKUP(_xlfn.CONCAT($B31, $A31), GearValues, 12, 0), " ")
A32: Runes | C32: Power | D32: Precision | E32: Toughness | F32: Vitality | G32: Concentration | H32: Condition Damage | I32: Expertise | J32: Ferocity | K32: Healing Power | L32: Defence
A33: Superior Rune of the Pack | C33: =IF(OR(Rune1Stat=C$3,Rune1Stat="to All Stats"),Rune1Bonus,"") -> 25 | D33: =IF(OR(Rune1Stat=D$3,Rune1Stat="to All Stats"),Rune1Bonus,"") | E33: =IF(OR(Rune1Stat=E$3,Rune1Stat="to All Stats"),Rune1Bonus,"") | F33: =IF(OR(Rune1Stat=F$3,Rune1Stat="to All Stats"),Rune1Bonus,"") | G33: =IF(OR(Rune1Stat=G$3,Rune1Stat="to All Stats"),Rune1Bonus,"") | H33: =IF(OR(Rune1Stat=H$3,Rune1Stat="to All Stats"),Rune1Bonus,"") | I33: =IF(OR(Rune1Stat=I$3,Rune1Stat="to All Stats"),Rune1Bonus,"") | J33: =IF(OR(Rune1Stat=J$3,Rune1Stat="to All Stats"),Rune1Bonus,"") | K33: =IF(OR(Rune1Stat=K$3,Rune1Stat="to All Stats"),Rune1Bonus,"")
A34: Superior Rune of Strength | C34: =IF(OR(Rune2Stat=C$3,Rune2Stat="to All Stats"),Rune2Bonus,"") -> 25 | D34: =IF(OR(Rune2Stat=D$3,Rune2Stat="to All Stats"),Rune2Bonus,"") | E34: =IF(OR(Rune2Stat=E$3,Rune2Stat="to All Stats"),Rune2Bonus,"") | F34: =IF(OR(Rune2Stat=F$3,Rune2Stat="to All Stats"),Rune2Bonus,"") | G34: =IF(OR(Rune2Stat=G$3,Rune2Stat="to All Stats"),Rune2Bonus,"") | H34: =IF(OR(Rune2Stat=H$3,Rune2Stat="to All Stats"),Rune2Bonus,"") | I34: =IF(OR(Rune2Stat=I$3,Rune2Stat="to All Stats"),Rune2Bonus,"") | J34: =IF(OR(Rune2Stat=J$3,Rune2Stat="to All Stats"),Rune2Bonus,"") | ... L34: =IF(OR(Rune2Stat=L$3,Rune2Stat="to All Stats"),Rune2Bonus,"")
A35: Superior Rune of Strength | C35: =IF(OR(Rune3Stat=C$3,Rune3Stat="to All Stats"),Rune3Bonus,"") | D35: =IF(OR(Rune3Stat=D$3,Rune3Stat="to All Stats"),Rune3Bonus,"") | E35: =IF(OR(Rune3Stat=E$3,Rune3Stat="to All Stats"),Rune3Bonus,"") | F35: =IF(OR(Rune3Stat=F$3,Rune3Stat="to All Stats"),Rune3Bonus,"") | G35: =IF(OR(Rune3Stat=G$3,Rune3Stat="to All Stats"),Rune3Bonus,"") | H35: =IF(OR(Rune3Stat=H$3,Rune3Stat="to All Stats"),Rune3Bonus,"") | I35: =IF(OR(Rune3Stat=I$3,Rune3Stat="to All Stats"),Rune3Bonus,"") | J35: =IF(OR(Rune3Stat=J$3,Rune3Stat="to All Stats"),Rune3Bonus,"") | ... L35: =IF(OR(Rune3Stat=L$3,Rune3Stat="to All Stats"),Rune3Bonus,"")
A36: Superior Rune of Strength | C36: =IF(OR(Rune4Stat=C$3,Rune4Stat="to All Stats"),Rune4Bonus,"") -> 50 | D36: =IF(OR(Rune4Stat=D$3,Rune4Stat="to All Stats"),Rune4Bonus,"") | E36: =IF(OR(Rune4Stat=E$3,Rune4Stat="to All Stats"),Rune4Bonus,"") | F36: =IF(OR(Rune4Stat=F$3,Rune4Stat="to All Stats"),Rune4Bonus,"") | G36: =IF(OR(Rune4Stat=G$3,Rune4Stat="to All Stats"),Rune4Bonus,"") | H36: =IF(OR(Rune4Stat=H$3,Rune4Stat="to All Stats"),Rune4Bonus,"") | I36: =IF(OR(Rune4Stat=I$3,Rune4Stat="to All Stats"),Rune4Bonus,"") | J36: =IF(OR(Rune4Stat=J$3,Rune4Stat="to All Stats"),Rune4Bonus,"") | ... L36: =IF(OR(Rune4Stat=L$3,Rune4Stat="to All Stats"),Rune4Bonus,"")
A37: Superior Rune of Strength | C37: =IF(OR(Rune5Stat=C$3,Rune5Stat="to All Stats"),Rune5Bonus,"") | D37: =IF(OR(Rune5Stat=D$3,Rune5Stat="to All Stats"),Rune5Bonus,"") | E37: =IF(OR(Rune5Stat=E$3,Rune5Stat="to All Stats"),Rune5Bonus,"") | F37: =IF(OR(Rune5Stat=F$3,Rune5Stat="to All Stats"),Rune5Bonus,"") | G37: =IF(OR(Rune5Stat=G$3,Rune5Stat="to All Stats"),Rune5Bonus,"") | H37: =IF(OR(Rune5Stat=H$3,Rune5Stat="to All Stats"),Rune5Bonus,"") | I37: =IF(OR(Rune5Stat=I$3,Rune5Stat="to All Stats"),Rune5Bonus,"") | J37: =IF(OR(Rune5Stat=J$3,Rune5Stat="to All Stats"),Rune5Bonus,"") | ... L37: =IF(OR(Rune5Stat=L$3,Rune5Stat="to All Stats"),Rune5Bonus,"")
A38: (Select) | C38: =IF(OR(Rune6Stat=C$3,Rune6Stat="to All Stats"),Rune6Bonus,"") | D38: =IF(OR(Rune6Stat=D$3,Rune6Stat="to All Stats"),Rune6Bonus,"") | E38: =IF(OR(Rune6Stat=E$3,Rune6Stat="to All Stats"),Rune6Bonus,"") | F38: =IF(OR(Rune6Stat=F$3,Rune6Stat="to All Stats"),Rune6Bonus,"") | G38: =IF(OR(Rune6Stat=G$3,Rune6Stat="to All Stats"),Rune6Bonus,"") | H38: =IF(OR(Rune6Stat=H$3,Rune6Stat="to All Stats"),Rune6Bonus,"") | I38: =IF(OR(Rune6Stat=I$3,Rune6Stat="to All Stats"),Rune6Bonus,"") | J38: =IF(OR(Rune6Stat=J$3,Rune6Stat="to All Stats"),Rune6Bonus,"") | ... L38: =IF(OR(Rune6Stat=L$3,Rune6Stat="to All Stats"),Rune6Bonus,"")
A39: Jewels | C39: Power | D39: Precision | E39: Toughness | F39: Vitality | G39: Concentration | H39: Condition Damage | I39: Expertise | J39: Ferocity | K39: Healing Power | L39: Defence
A40: Exquisite Azurite Jewel | C40: {=_xlfn.LET(_xlpm.check,VLOOKUP($A40,Jewels!$A$1:$N$27,6,0),IF(AND(COUNTBLANK($A40)=0,NOT($A40="(Select)")),IF(_xlpm.check="","",_xlpm.check),""))} -> 15 | D40: {=_xlfn.LET(_xlpm.check,VLOOKUP($A40,Jewels!$A$1:$N$27,7,0),IF(AND(COUNTBLANK($A40)=0,NOT($A40="(Select)")),IF(_xlpm.check="","",_xlpm.check),""))} | E40: {=_xlfn.LET(_xlpm.check,VLOOKUP($A40,Jewels!$A$1:$N$27,8,0),IF(AND(COUNTBLANK($A40)=0,NOT($A40="(Select)")),IF(_xlpm.check="","",_xlpm.check),""))} -> 15 | F40: {=_xlfn.LET(_xlpm.check,VLOOKUP($A40,Jewels!$A$1:$N$27,9,0),IF(AND(COUNTBLANK($A40)=0,NOT($A40="(Select)")),IF(_xlpm.check="","",_xlpm.check),""))} -> 25 | G40: {=_xlfn.LET(_xlpm.check,VLOOKUP($A40,Jewels!$A$1:$N$27,10,0),IF(AND(COUNTBLANK($A40)=0,NOT($A40="(Select)")),IF(_xlpm.check="","",_xlpm.check),""))} | H40: {=_xlfn.LET(_xlpm.check,VLOOKUP($A40,Jewels!$A$1:$N$27,11,0),IF(AND(COUNTBLANK($A40)=0,NOT($A40="(Select)")),IF(_xlpm.check="","",_xlpm.check),""))} | I40: {=_xlfn.LET(_xlpm.check,VLOOKUP($A40,Jewels!$A$1:$N$27,12,0),IF(AND(COUNTBLANK($A40)=0,NOT($A40="(Select)")),IF(_xlpm.check="","",_xlpm.check),""))} | J40: {=_xlfn.LET(_xlpm.check,VLOOKUP($A40,Jewels!$A$1:$N$27,13,0),IF(AND(COUNTBLANK($A40)=0,NOT($A40="(Select)")),IF(_xlpm.check="","",_xlpm.check),""))} | K40: {=_xlfn.LET(_xlpm.check,VLOOKUP($A40,Jewels!$A$1:$N$27,14,0),IF(AND(COUNTBLANK($A40)=0,NOT($A40="(Select)")),IF(_xlpm.check="","",_xlpm.check),""))}
A41: Exquisite Black Diamond Jewel | C41: {=_xlfn.LET(_xlpm.check,VLOOKUP($A41,Jewels!$A$1:$N$27,6,0),IF(AND(COUNTBLANK($A41)=0,NOT($A41="(Select)")),IF(_xlpm.check="","",_xlpm.check),""))} -> 20 | D41: {=_xlfn.LET(_xlpm.check,VLOOKUP($A41,Jewels!$A$1:$N$27,7,0),IF(AND(COUNTBLANK($A41)=0,NOT($A41="(Select)")),IF(_xlpm.check="","",_xlpm.check),""))} -> 10 | E41: {=_xlfn.LET(_xlpm.check,VLOOKUP($A41,Jewels!$A$1:$N$27,8,0),IF(AND(COUNTBLANK($A41)=0,NOT($A41="(Select)")),IF(_xlpm.check="","",_xlpm.check),""))} | F41: {=_xlfn.LET(_xlpm.check,VLOOKUP($A41,Jewels!$A$1:$N$27,9,0),IF(AND(COUNTBLANK($A41)=0,NOT($A41="(Select)")),IF(_xlpm.check="","",_xlpm.check),""))} | G41: {=_xlfn.LET(_xlpm.check,VLOOKUP($A41,Jewels!$A$1:$N$27,10,0),IF(AND(COUNTBLANK($A41)=0,NOT($A41="(Select)")),IF(_xlpm.check="","",_xlpm.check),""))} | H41: {=_xlfn.LET(_xlpm.check,VLOOKUP($A41,Jewels!$A$1:$N$27,11,0),IF(AND(COUNTBLANK($A41)=0,NOT($A41="(Select)")),IF(_xlpm.check="","",_xlpm.check),""))} -> 20 | I41: {=_xlfn.LET(_xlpm.check,VLOOKUP($A41,Jewels!$A$1:$N$27,12,0),IF(AND(COUNTBLANK($A41)=0,NOT($A41="(Select)")),IF(_xlpm.check="","",_xlpm.check),""))} -> 10 | J41: {=_xlfn.LET(_xlpm.check,VLOOKUP($A41,Jewels!$A$1:$N$27,13,0),IF(AND(COUNTBLANK($A41)=0,NOT($A41="(Select)")),IF(_xlpm.check="","",_xlpm.check),""))} | K41: {=_xlfn.LET(_xlpm.check,VLOOKUP($A41,Jewels!$A$1:$N$27,14,0),IF(AND(COUNTBLANK($A41)=0,NOT($A41="(Select)")),IF(_xlpm.check="","",_xlpm.check),""))}
A42: Exquisite Ambrite Jewel | C42: {=_xlfn.LET(_xlpm.check,VLOOKUP($A42,Jewels!$A$1:$N$27,6,0),IF(AND(COUNTBLANK($A42)=0,NOT($A42="(Select)")),IF(_xlpm.check="","",_xlpm.check),""))} | D42: {=_xlfn.LET(_xlpm.check,VLOOKUP($A42,Jewels!$A$1:$N$27,7,0),IF(AND(COUNTBLANK($A42)=0,NOT($A42="(Select)")),IF(_xlpm.check="","",_xlpm.check),""))} | E42: {=_xlfn.LET(_xlpm.check,VLOOKUP($A42,Jewels!$A$1:$N$27,8,0),IF(AND(COUNTBLANK($A42)=0,NOT($A42="(Select)")),IF(_xlpm.check="","",_xlpm.check),""))} -> 25 | F42: {=_xlfn.LET(_xlpm.check,VLOOKUP($A42,Jewels!$A$1:$N$27,9,0),IF(AND(COUNTBLANK($A42)=0,NOT($A42="(Select)")),IF(_xlpm.check="","",_xlpm.check),""))} -> 15 | G42: {=_xlfn.LET(_xlpm.check,VLOOKUP($A42,Jewels!$A$1:$N$27,10,0),IF(AND(COUNTBLANK($A42)=0,NOT($A42="(Select)")),IF(_xlpm.check="","",_xlpm.check),""))} | H42: {=_xlfn.LET(_xlpm.check,VLOOKUP($A42,Jewels!$A$1:$N$27,11,0),IF(AND(COUNTBLANK($A42)=0,NOT($A42="(Select)")),IF(_xlpm.check="","",_xlpm.check),""))} | I42: {=_xlfn.LET(_xlpm.check,VLOOKUP($A42,Jewels!$A$1:$N$27,12,0),IF(AND(COUNTBLANK($A42)=0,NOT($A42="(Select)")),IF(_xlpm.check="","",_xlpm.check),""))} | J42: {=_xlfn.LET(_xlpm.check,VLOOKUP($A42,Jewels!$A$1:$N$27,13,0),IF(AND(COUNTBLANK($A42)=0,NOT($A42="(Select)")),IF(_xlpm.check="","",_xlpm.check),""))} | K42: {=_xlfn.LET(_xlpm.check,VLOOKUP($A42,Jewels!$A$1:$N$27,14,0),IF(AND(COUNTBLANK($A42)=0,NOT($A42="(Select)")),IF(_xlpm.check="","",_xlpm.check),""))} -> 15
A43: Exquisite Burl Jewel | C43: {=_xlfn.LET(_xlpm.check,VLOOKUP($A43,Jewels!$A$1:$N$27,6,0),IF(AND(COUNTBLANK($A43)=0,NOT($A43="(Select)")),IF(_xlpm.check="","",_xlpm.check),""))} -> 20 | D43: {=_xlfn.LET(_xlpm.check,VLOOKUP($A43,Jewels!$A$1:$N$27,7,0),IF(AND(COUNTBLANK($A43)=0,NOT($A43="(Select)")),IF(_xlpm.check="","",_xlpm.check),""))} -> 20 | E43: {=_xlfn.LET(_xlpm.check,VLOOKUP($A43,Jewels!$A$1:$N$27,8,0),IF(AND(COUNTBLANK($A43)=0,NOT($A43="(Select)")),IF(_xlpm.check="","",_xlpm.check),""))} -> 10 | F43: {=_xlfn.LET(_xlpm.check,VLOOKUP($A43,Jewels!$A$1:$N$27,9,0),IF(AND(COUNTBLANK($A43)=0,NOT($A43="(Select)")),IF(_xlpm.check="","",_xlpm.check),""))} | G43: {=_xlfn.LET(_xlpm.check,VLOOKUP($A43,Jewels!$A$1:$N$27,10,0),IF(AND(COUNTBLANK($A43)=0,NOT($A43="(Select)")),IF(_xlpm.check="","",_xlpm.check),""))} -> 10 | H43: {=_xlfn.LET(_xlpm.check,VLOOKUP($A43,Jewels!$A$1:$N$27,11,0),IF(AND(COUNTBLANK($A43)=0,NOT($A43="(Select)")),IF(_xlpm.check="","",_xlpm.check),""))} | I43: {=_xlfn.LET(_xlpm.check,VLOOKUP($A43,Jewels!$A$1:$N$27,12,0),IF(AND(COUNTBLANK($A43)=0,NOT($A43="(Select)")),IF(_xlpm.check="","",_xlpm.check),""))} | J43: {=_xlfn.LET(_xlpm.check,VLOOKUP($A43,Jewels!$A$1:$N$27,13,0),IF(AND(COUNTBLANK($A43)=0,NOT($A43="(Select)")),IF(_xlpm.check="","",_xlpm.check),""))} | K43: {=_xlfn.LET(_xlpm.check,VLOOKUP($A43,Jewels!$A$1:$N$27,14,0),IF(AND(COUNTBLANK($A43)=0,NOT($A43="(Select)")),IF(_xlpm.check="","",_xlpm.check),""))}
A44: Exquisite Ruby Jewel | C44: {=_xlfn.LET(_xlpm.check,VLOOKUP($A44,Jewels!$A$1:$N$27,6,0),IF(AND(COUNTBLANK($A44)=0,NOT($A44="(Select)")),IF(_xlpm.check="","",_xlpm.check),""))} -> 25 | D44: {=_xlfn.LET(_xlpm.check,VLOOKUP($A44,Jewels!$A$1:$N$27,7,0),IF(AND(COUNTBLANK($A44)=0,NOT($A44="(Select)")),IF(_xlpm.check="","",_xlpm.check),""))} -> 15 | E44: {=_xlfn.LET(_xlpm.check,VLOOKUP($A44,Jewels!$A$1:$N$27,8,0),IF(AND(COUNTBLANK($A44)=0,NOT($A44="(Select)")),IF(_xlpm.check="","",_xlpm.check),""))} | F44: {=_xlfn.LET(_xlpm.check,VLOOKUP($A44,Jewels!$A$1:$N$27,9,0),IF(AND(COUNTBLANK($A44)=0,NOT($A44="(Select)")),IF(_xlpm.check="","",_xlpm.check),""))} | G44: {=_xlfn.LET(_xlpm.check,VLOOKUP($A44,Jewels!$A$1:$N$27,10,0),IF(AND(COUNTBLANK($A44)=0,NOT($A44="(Select)")),IF(_xlpm.check="","",_xlpm.check),""))} | H44: {=_xlfn.LET(_xlpm.check,VLOOKUP($A44,Jewels!$A$1:$N$27,11,0),IF(AND(COUNTBLANK($A44)=0,NOT($A44="(Select)")),IF(_xlpm.check="","",_xlpm.check),""))} | I44: {=_xlfn.LET(_xlpm.check,VLOOKUP($A44,Jewels!$A$1:$N$27,12,0),IF(AND(COUNTBLANK($A44)=0,NOT($A44="(Select)")),IF(_xlpm.check="","",_xlpm.check),""))} | J44: {=_xlfn.LET(_xlpm.check,VLOOKUP($A44,Jewels!$A$1:$N$27,13,0),IF(AND(COUNTBLANK($A44)=0,NOT($A44="(Select)")),IF(_xlpm.check="","",_xlpm.check),""))} -> 15 | K44: {=_xlfn.LET(_xlpm.check,VLOOKUP($A44,Jewels!$A$1:$N$27,14,0),IF(AND(COUNTBLANK($A44)=0,NOT($A44="(Select)")),IF(_xlpm.check="","",_xlpm.check),""))}
A45: Signets | C45: Power | D45: Precision | E45: Toughness | F45: Vitality | G45: Concentration | H45: Condition Damage | I45: Expertise | J45: Ferocity | K45: Healing Power | L45: Defence
A46: Superconducting Signet | C46: =IF(C$3=Signet1Stat,Signet1Bonus,"") | D46: =IF(D$3=Signet1Stat,Signet1Bonus,"") | E46: =IF(E$3=Signet1Stat,Signet1Bonus,"") | F46: =IF(F$3=Signet1Stat,Signet1Bonus,"") | G46: =IF(G$3=Signet1Stat,Signet1Bonus,"") | H46: =IF(H$3=Signet1Stat,Signet1Bonus,"") -> 31.2 | I46: =IF(I$3=Signet1Stat,Signet1Bonus,"") | J46: =IF(J$3=Signet1Stat,Signet1Bonus,"") | K46: =IF(K$3=Signet1Stat,Signet1Bonus,"")
A47: Signet of Midnight | C47: =IF(C$3=Signet2Stat,Signet2Bonus,"") | D47: =IF(D$3=Signet2Stat,Signet2Bonus,"") | E47: =IF(E$3=Signet2Stat,Signet2Bonus,"") | F47: =IF(F$3=Signet2Stat,Signet2Bonus,"") | G47: =IF(G$3=Signet2Stat,Signet2Bonus,"") | H47: =IF(H$3=Signet2Stat,Signet2Bonus,"") | I47: =IF(I$3=Signet2Stat,Signet2Bonus,"") -> 180 | J47: =IF(J$3=Signet2Stat,Signet2Bonus,"") | K47: =IF(K$3=Signet2Stat,Signet2Bonus,"")
A48: (Select) | C48: =IF(C$3=Signet3Stat,Signet3Bonus,"") | D48: =IF(D$3=Signet3Stat,Signet3Bonus,"") | E48: =IF(E$3=Signet3Stat,Signet3Bonus,"") | F48: =IF(F$3=Signet3Stat,Signet3Bonus,"") | G48: =IF(G$3=Signet3Stat,Signet3Bonus,"") | H48: =IF(H$3=Signet3Stat,Signet3Bonus,"") | I48: =IF(I$3=Signet3Stat,Signet3Bonus,"") | J48: =IF(J$3=Signet3Stat,Signet3Bonus,"") | K48: =IF(K$3=Signet3Stat,Signet3Bonus,"")
A49: Consumables | C49: Power | D49: Precision | E49: Toughness | F49: Vitality | G49: Concentration | H49: Condition Damage | I49: Expertise | J49: Ferocity | K49: Healing Power | L49: Defence
A50: Food | B50: Clove-Spiced Pear and Cured Meat Flatbread | C50: =IF(AND(COUNTBLANK($B$50)=0,NOT(B50="(Select)")), IF(VLOOKUP($B$50, Food!$A$3:$J$611, 2, 0)="","",VLOOKUP($B$50, Food!$A$3:$J$611, 2, 0)),"") | D50: =IF(AND(COUNTBLANK($B$50)=0,NOT($B$50="(Select)")), IF(VLOOKUP($B$50, Food!$A$3:$J$611, 3, 0)="","",VLOOKUP($B$50, Food!$A$3:$J$611, 3, 0)),"") | E50: =IF(AND(COUNTBLANK($B$50)=0,NOT($B$50="(Select)")), IF(VLOOKUP($B$50, Food!$A$3:$J$611, 4, 0)="","",VLOOKUP($B$50, Food!$A$3:$J$611, 4, 0)),"") | F50: =IF(AND(COUNTBLANK($B$50)=0,NOT($B$50="(Select)")), IF(VLOOKUP($B$50, Food!$A$3:$J$611, 5, 0)="","",VLOOKUP($B$50, Food!$A$3:$J$611, 5, 0)),"") | G50: =IF(AND(COUNTBLANK($B$50)=0,NOT($B$50="(Select)")), IF(VLOOKUP($B$50, Food!$A$3:$J$611, 6, 0)="","",VLOOKUP($B$50, Food!$A$3:$J$611, 6, 0)),"") | H50: =IF(AND(COUNTBLANK($B$50)=0,NOT($B$50="(Select)")), IF(VLOOKUP($B$50, Food!$A$3:$J$611, 7, 0)="","",VLOOKUP($B$50, Food!$A$3:$J$611, 7, 0)),"") -> 100 | I50: =IF(AND(COUNTBLANK($B$50)=0,NOT($B$50="(Select)")), IF(VLOOKUP($B$50, Food!$A$3:$J$611, 8, 0)="","",VLOOKUP($B$50, Food!$A$3:$J$611, 8, 0)),"") -> 70 | J50: =IF(AND(COUNTBLANK($B$50)=0,NOT($B$50="(Select)")), IF(VLOOKUP($B$50, Food!$A$3:$J$611, 9, 0)="","",VLOOKUP($B$50, Food!$A$3:$J$611, 9, 0)),"") | K50: =IF(AND(COUNTBLANK($B$50)=0,NOT($B$50="(Select)")), IF(VLOOKUP($B$50, Food!$A$3:$J$611, 10, 0)="","",VLOOKUP($B$50, Food!$A$3:$J$611, 10, 0)),"")
A51: Utility | B51: Rough Sharpening Stone | C51: {=_xlfn.LET(_xlpm.val,IFERROR(IF(AND(COUNTBLANK($B$51)=0,NOT($B$51="(Select)")),_xlfn.IFS(UtilBonusType="Derived",_xlfn.IFS(AND(C$3=DerivedGain1,C$3=DerivedGain2),DerivedResult1+DerivedResult2,C$3=DerivedGain1,DerivedResult1,C$3=DerivedGain2,DerivedResult2),UtilBonusType="Healthy",IF(HealthyGain=C$3,HealthyResult),UtilBonusType="Flat",IF(C$3=FlatGain,FlatResult)),""),""),IF(OR(_xlpm.val=FALSE,_xlpm.val=""),"",_xlpm.val))} -> 15.94 | D51: {=_xlfn.LET(_xlpm.val,IFERROR(IF(AND(COUNTBLANK($B$51)=0,NOT($B$51="(Select)")),_xlfn.IFS(UtilBonusType="Derived",_xlfn.IFS(AND(D$3=DerivedGain1,D$3=DerivedGain2),DerivedResult1+DerivedResult2,D$3=DerivedGain1,DerivedResult1,D$3=DerivedGain2,DerivedResult2),UtilBonusType="Healthy",IF(HealthyGain=D$3,HealthyResult),UtilBonusType="Flat",IF(D$3=FlatGain,FlatResult)),""),""),IF(OR(_xlpm.val=FALSE,_xlpm.val=""),"",_xlpm.val))} | E51: {=_xlfn.LET(_xlpm.val,IFERROR(IF(AND(COUNTBLANK($B$51)=0,NOT($B$51="(Select)")),_xlfn.IFS(UtilBonusType="Derived",_xlfn.IFS(AND(E$3=DerivedGain1,E$3=DerivedGain2),DerivedResult1+DerivedResult2,E$3=DerivedGain1,DerivedResult1,E$3=DerivedGain2,DerivedResult2),UtilBonusType="Healthy",IF(HealthyGain=E$3,HealthyResult),UtilBonusType="Flat",IF(E$3=FlatGain,FlatResult)),""),""),IF(OR(_xlpm.val=FALSE,_xlpm.val=""),"",_xlpm.val))} | F51: {=_xlfn.LET(_xlpm.val,IFERROR(IF(AND(COUNTBLANK($B$51)=0,NOT($B$51="(Select)")),_xlfn.IFS(UtilBonusType="Derived",_xlfn.IFS(AND(F$3=DerivedGain1,F$3=DerivedGain2),DerivedResult1+DerivedResult2,F$3=DerivedGain1,DerivedResult1,F$3=DerivedGain2,DerivedResult2),UtilBonusType="Healthy",IF(HealthyGain=F$3,HealthyResult),UtilBonusType="Flat",IF(F$3=FlatGain,FlatResult)),""),""),IF(OR(_xlpm.val=FALSE,_xlpm.val=""),"",_xlpm.val))} | G51: {=_xlfn.LET(_xlpm.val,IFERROR(IF(AND(COUNTBLANK($B$51)=0,NOT($B$51="(Select)")),_xlfn.IFS(UtilBonusType="Derived",_xlfn.IFS(AND(G$3=DerivedGain1,G$3=DerivedGain2),DerivedResult1+DerivedResult2,G$3=DerivedGain1,DerivedResult1,G$3=DerivedGain2,DerivedResult2),UtilBonusType="Healthy",IF(HealthyGain=G$3,HealthyResult),UtilBonusType="Flat",IF(G$3=FlatGain,FlatResult)),""),""),IF(OR(_xlpm.val=FALSE,_xlpm.val=""),"",_xlpm.val))} | H51: {=_xlfn.LET(_xlpm.val,IFERROR(IF(AND(COUNTBLANK($B$51)=0,NOT($B$51="(Select)")),_xlfn.IFS(UtilBonusType="Derived",_xlfn.IFS(AND(H$3=DerivedGain1,H$3=DerivedGain2),DerivedResult1+DerivedResult2,H$3=DerivedGain1,DerivedResult1,H$3=DerivedGain2,DerivedResult2),UtilBonusType="Healthy",IF(HealthyGain=H$3,HealthyResult),UtilBonusType="Flat",IF(H$3=FlatGain,FlatResult)),""),""),IF(OR(_xlpm.val=FALSE,_xlpm.val=""),"",_xlpm.val))} | I51: {=_xlfn.LET(_xlpm.val,IFERROR(IF(AND(COUNTBLANK($B$51)=0,NOT($B$51="(Select)")),_xlfn.IFS(UtilBonusType="Derived",_xlfn.IFS(AND(I$3=DerivedGain1,I$3=DerivedGain2),DerivedResult1+DerivedResult2,I$3=DerivedGain1,DerivedResult1,I$3=DerivedGain2,DerivedResult2),UtilBonusType="Healthy",IF(HealthyGain=I$3,HealthyResult),UtilBonusType="Flat",IF(I$3=FlatGain,FlatResult)),""),""),IF(OR(_xlpm.val=FALSE,_xlpm.val=""),"",_xlpm.val))} | J51: {=_xlfn.LET(_xlpm.val,IFERROR(IF(AND(COUNTBLANK($B$51)=0,NOT($B$51="(Select)")),_xlfn.IFS(UtilBonusType="Derived",_xlfn.IFS(AND(J$3=DerivedGain1,J$3=DerivedGain2),DerivedResult1+DerivedResult2,J$3=DerivedGain1,DerivedResult1,J$3=DerivedGain2,DerivedResult2),UtilBonusType="Healthy",IF(HealthyGain=J$3,HealthyResult),UtilBonusType="Flat",IF(J$3=FlatGain,FlatResult)),""),""),IF(OR(_xlpm.val=FALSE,_xlpm.val=""),"",_xlpm.val))} | K51: {=_xlfn.LET(_xlpm.val,IFERROR(IF(AND(COUNTBLANK($B$51)=0,NOT($B$51="(Select)")),_xlfn.IFS(UtilBonusType="Derived",_xlfn.IFS(AND(K$3=DerivedGain1,K$3=DerivedGain2),DerivedResult1+DerivedResult2,K$3=DerivedGain1,DerivedResult1,K$3=DerivedGain2,DerivedResult2),UtilBonusType="Healthy",IF(HealthyGain=K$3,HealthyResult),UtilBonusType="Flat",IF(K$3=FlatGain,FlatResult)),""),""),IF(OR(_xlpm.val=FALSE,_xlpm.val=""),"",_xlpm.val))} | L51: =IF(UtilBonusType="Healthy","*When above 90% Health","") | M51: =IF(UtilBonusType="Healthy","*When above 90% Health","")
A52: Additional | C52: Power | D52: Precision | E52: Toughness | F52: Vitality | G52: Concentration | H52: Condition Damage | I52: Expertise | J52: Ferocity | K52: Healing Power | L52: Defence
A53: Offhand is Shield : | B53: FALSE
A54: Assassin's Signet active : | B54: FALSE | C54: =IF(AND(COUNTIF(A46:B48,"Assassin's Signet")>0,$B$54=1),"540","")
A55: Final Totals
A56: Power | B56: =SUM(C4:C54)+(G57*30)+1000 -> 1672.94 | C56: Health | D56: =VLOOKUP(Class, Helpers!M23:N31, 2, 0)+10*B59 -> 17482 | F56: Boons | G56: Stacks/Toggle
A57: Precision | B57: =_xlfn.CONCAT(TEXT(PrecisionTotal,0)," (",TEXT((100%-D58)*100*21,0),")") -> 1594 (876) | C57: Armor | D57: {=_xlfn.LET(_xlpm.sum,SUM(L20:L25)+B58,IF(B53=TRUE,_xlpm.sum+61,_xlpm.sum))} -> 2128 | F57: Might | G57: 0
A58: Toughness | B58: =SUM(E4:E54)+(G63*20)+1000 -> 1221 | C58: Critical Chance | D58: =((PrecisionTotal-1000)/21+5)/100+IF(G58=TRUE,0.25,0)+TraitCritChanceTotal -> 0.58285714 | E58: =IF(D58>100%, "Cap exceeded!","") | F58: Fury | G58: TRUE
A59: Vitality | B59: =SUM(F4:F54)+1000 -> 1156 | C59: Critical Damage | D59: =B63/15/100+1.5+TraitCritDamageTotal -> 1.6653333 | F59: Quickness | G59: FALSE
A60: Concentration | B60: =_xlfn.CONCAT(TEXT(ConcentrationTotal,0)," (",TEXT((100%-D60)*100*15,0),")") -> 10 (1490) | C60: Boon Duration | D60: =ConcentrationTotal/15/100 -> 0.0066666667 | E60: =IF(D60>100%, "Cap exceeded!","") | F60: Regeneration | G60: FALSE
A61: Condition Damage | B61: =SUM(H4:H54)+(G57*30) -> 343.2 | C61: Condition Duration | D61: =ExpertiseTotal/15/100+TraitConditionDurationTotal -> 0.17333333 | E61: =IF(D61>100%, "Cap exceeded!","") | F61: Vigor | G61: FALSE
A62: Expertise | B62: =_xlfn.CONCAT(TEXT(ExpertiseTotal,0)," (",TEXT((100%-D61)*100*15,0),")") -> 260 (1240) | F62: Alacrity | G62: FALSE
A63: Ferocity | B63: =SUM(J4:J54) -> 248 | F63: Death's Carapace | G63: 0
A64: Healing Power | B64: =SUM(K4:K54) -> 47

Sheet Trait Selection
B1: =Spec1 -> Illusions | F1: =Spec2 -> Inspiration | J1: =Spec3 -> Troubadour
B2: Name | C2: Apply Condition | D2: Stacks | E2: Effect | F2: Name | G2: Apply Condition | H2: Stacks | I2: Effect | J2: Name | K2: Apply Condition | L2: Stacks | M2: Effect
A3: Minor Adept | B3: =Spec1MinorAdept -> Cry of Pain | C3: (Select) | D3: 0 | E3: {=_xlfn.LET(_xlpm.val,VLOOKUP(Spec1MinorAdept,TraitTable,5,0),IF(ISNA(_xlpm.val),"",_xlpm.val))} -> Shatter skill 2 inflicts more stacks of confusion for an increased duration. | F3: =Spec2MinorAdept -> Mender's Purity | G3: (Select) | H3: 0 | I3: {=_xlfn.LET(_xlpm.val,VLOOKUP(Spec2MinorAdept,TraitTable,5,0),IF(ISNA(_xlpm.val),"",_xlpm.val))} -> Cast Lesser Power Cleanse when you use a healing skill. | J3: =Spec3MinorAdept -> Wandering Minstrel | K3: (Select) | L3: 0 | M3: {=_xlfn.LET(_xlpm.val,VLOOKUP(Spec3MinorAdept,TraitTable,5,0),IF(ISNA(_xlpm.val),"",_xlpm.val))} -> Build up notes instead of summoning illusions. Shatters are replaced by instrument skills, which consume notes to continue playing. Gain access to Tales. While out of combat, you will automatically stock a blade [ sic ] every 10 seconds.
A4: Major Adept | B4: =IF(Spec1MajorAdept=0,"",Spec1MajorAdept) -> Persistence of Memory | C4: (Select) | D4: 0 | E4: {=_xlfn.LET(_xlpm.val,VLOOKUP(Spec1MajorAdept,TraitTable,5,0),IF(ISNA(_xlpm.val),"",_xlpm.val))} -> When a phantasm becomes a clone, it transfers its boons to you. | F4: =IF(Spec2MajorAdept=0,"",Spec2MajorAdept) -> (Select) | G4: (Select) | H4: 0 | I4: {=_xlfn.LET(_xlpm.val,VLOOKUP(Spec2MajorAdept,TraitTable,5,0),IF(ISNA(_xlpm.val),"",_xlpm.val))} | J4: =IF(Spec3MajorAdept=0,"",Spec3MajorAdept) -> Illusionary Defense | K4: (Select) | L4: 0 | M4: {=_xlfn.LET(_xlpm.val,VLOOKUP(Spec3MajorAdept,TraitTable,5,0),IF(ISNA(_xlpm.val),"",_xlpm.val))} -> Grant protection to nearby allies when you use Shatter skill 2.
A5: Minor Master | B5: =Spec1MinorMaster -> Compounding Power | C5: Illusion created | D5: 2 | E5: {=_xlfn.LET(_xlpm.val,VLOOKUP(Spec1MinorMaster,TraitTable,5,0),IF(ISNA(_xlpm.val),"",_xlpm.val))} -> Creating an illusion increases your outgoing damage and condition damage for a short duration. Virtuoso : Triggers when stocking a blade. | F5: =Spec2MinorMaster -> Inspiring Distortion | G5: (Select) | H5: 0 | I5: {=_xlfn.LET(_xlpm.val,VLOOKUP(Spec2MinorMaster,TraitTable,5,0),IF(ISNA(_xlpm.val),"",_xlpm.val))} -> Grant aegis to other nearby allies whenever you give yourself distortion or use Shatter skill 4. | J5: =Spec3MinorMaster -> Symphonic Resonance | K5: Lute playing in background | L5: 0 | M5: {=_xlfn.LET(_xlpm.val,VLOOKUP(Spec3MinorMaster,TraitTable,5,0),IF(ISNA(_xlpm.val),"",_xlpm.val))} -> Instruments provide bonuses while playing in the background.
A6: Major Master | B6: =IF(Spec1MajorMaster=0,"",Spec1MajorMaster) -> (Select) | C6: (Select) | D6: 0 | E6: {=_xlfn.LET(_xlpm.val,VLOOKUP(Spec1MajorMaster,TraitTable,5,0),IF(ISNA(_xlpm.val),"",_xlpm.val))} | F6: =IF(Spec2MajorMaster=0,"",Spec2MajorMaster) -> Warden's Feedback | G6: (Select) | H6: 0 | I6: {=_xlfn.LET(_xlpm.val,VLOOKUP(Spec2MajorMaster,TraitTable,5,0),IF(ISNA(_xlpm.val),"",_xlpm.val))} -> Focus weapon skills reflect projectiles. Reduces recharge on focus weapon skills. | J6: =IF(Spec3MajorMaster=0,"",Spec3MajorMaster) -> (Select) | K6: (Select) | L6: 0 | M6: {=_xlfn.LET(_xlpm.val,VLOOKUP(Spec3MajorMaster,TraitTable,5,0),IF(ISNA(_xlpm.val),"",_xlpm.val))}
A7: Minor Grandmaster | B7: =Spec1MinorGrandmaster -> Master of Misdirection | C7: (Select) | D7: 0 | E7: {=_xlfn.LET(_xlpm.val,VLOOKUP(Spec1MinorGrandmaster,TraitTable,5,0),IF(ISNA(_xlpm.val),"",_xlpm.val))} -> Shatter skills gain recharge reduction. | F7: =Spec2MinorGrandmaster -> Illusionary Inspiration | G7: (Select) | H7: 0 | I7: {=_xlfn.LET(_xlpm.val,VLOOKUP(Spec2MinorGrandmaster,TraitTable,5,0),IF(ISNA(_xlpm.val),"",_xlpm.val))} -> Increase healing to other allies. Summoning an illusion heals all allies around you. Virtuoso : Triggers when stocking a blade. | J7: =Spec3MinorGrandmaster -> Harmonize | K7: (Select) | L7: 0 | M7: {=_xlfn.LET(_xlpm.val,VLOOKUP(Spec3MinorGrandmaster,TraitTable,5,0),IF(ISNA(_xlpm.val),"",_xlpm.val))} -> Gain a note when you use a phantasm skill.
A8: Major Grandmaster | B8: =IF(Spec1MajorGrandmaster=0,"",Spec1MajorGrandmaster) -> (Select) | C8: (Select) | D8: 0 | E8: {=_xlfn.LET(_xlpm.val,VLOOKUP(Spec1MajorGrandmaster,TraitTable,5,0),IF(ISNA(_xlpm.val),"",_xlpm.val))} | F8: =IF(Spec2MajorGrandmaster=0,"",Spec2MajorGrandmaster) -> (Select) | G8: (Select) | H8: 0 | I8: {=_xlfn.LET(_xlpm.val,VLOOKUP(Spec2MajorGrandmaster,TraitTable,5,0),IF(ISNA(_xlpm.val),"",_xlpm.val))} | J8: =IF(Spec3MajorGrandmaster=0,"",Spec3MajorGrandmaster) -> (Select) | K8: Instrument playing | L8: 0 | M8: {=_xlfn.LET(_xlpm.val,VLOOKUP(Spec3MajorGrandmaster,TraitTable,5,0),IF(ISNA(_xlpm.val),"",_xlpm.val))}
N9: Legend
N10: Condition/Stacks active
N11: Condition/Stacks available but inactive
A12: Power | B12: ='Build & Totals'!B56 -> 1672.94 | C12: Health | D12: ='Build & Totals'!D56 -> 17482
A13: Precision* | B13: ='Build & Totals'!B57 -> 1594 (876) | C13: Armor | D13: ='Build & Totals'!D57 -> 2128
A14: Toughness | B14: ='Build & Totals'!B58 -> 1221 | C14: Critical Chance | D14: ='Build & Totals'!D58 -> 0.58285714
A15: Vitality | B15: ='Build & Totals'!B59 -> 1156 | C15: Critical Damage | D15: ='Build & Totals'!D59 -> 1.6653333
A16: Concentration | B16: ='Build & Totals'!B60 -> 10 (1490) | C16: Boon Duration | D16: ='Build & Totals'!D60 -> 0.0066666667
A17: Condition Damage | B17: ='Build & Totals'!B61 -> 343.2 | C17: Condition Duration | D17: ='Build & Totals'!D61 -> 0.17333333
A18: Expertise | B18: ='Build & Totals'!B62 -> 260 (1240)
A19: Ferocity | B19: ='Build & Totals'!B63 -> 248
A20: Healing Power | B20: ='Build & Totals'!B64 -> 47

Sheet Full Traits
A1: Name | B1: Class | C1: Specialisation | D1: Tier | E1: Description | F1: Filter
A2: Zealot's Resolution | B2: Guardian | C2: Zeal | D2: Minor Adept | E2: Cast Lesser Symbol of Resolution when you are struck while below the health threshold. | F2: =IF(AND(COUNTIF('Build & Totals'!$A$4:$B$12,$C2)>=1,Class=$B2),$A2,"") | H2: Selected Major Trait
A3: Wrathful Spirit | B3: Guardian | C3: Zeal | D3: Major Adept | E3: Aegis grants boons when it ends. | F3: =IF(AND(COUNTIF('Build & Totals'!$A$4:$B$12,$C3)>=1,Class=$B3),$A3,"") | H3: Selected Minor Trait
A4: Fiery Wrath | B4: Guardian | C4: Zeal | D4: Major Adept | E4: Deal increased strike damage to burning foes. | F4: =IF(AND(COUNTIF('Build & Totals'!$A$4:$B$12,$C4)>=1,Class=$B4),$A4,"")
A5: Zealous Scepter | B5: Guardian | C5: Zeal | D5: Major Adept | E5: Gain might when your Virtue skill 1 passive effect triggers; gain more might while wielding a scepter. | F5: =IF(AND(COUNTIF('Build & Totals'!$A$4:$B$12,$C5)>=1,Class=$B5),$A5,"")
A6: Symbolic Exposure | B6: Guardian | C6: Zeal | D6: Minor Master | E6: Symbols inflict vulnerability on foes. Deal increased strike damage to vulnerable foes. | F6: =IF(AND(COUNTIF('Build & Totals'!$A$4:$B$12,$C6)>=1,Class=$B6),$A6,"")
A7: Furious Focus | B7: Guardian | C7: Zeal | D7: Major Master | E7: While you have fury, your attacks inflict vulnerability. | F7: =IF(AND(COUNTIF('Build & Totals'!$A$4:$B$12,$C7)>=1,Class=$B7),$A7,"")
A8: Zealous Blade | B8: Guardian | C8: Zeal | D8: Major Master | E8: Your power is increased. Gain additional power while wielding a greatsword. Your greatsword skills have reduced recharge. | F8: =IF(AND(COUNTIF('Build & Totals'!$A$4:$B$12,$C8)>=1,Class=$B8),$A8,"")
A9: Kindled Zeal | B9: Guardian | C9: Zeal | D9: Major Master | E9: Gain condition damage based on your power. | F9: =IF(AND(COUNTIF('Build & Totals'!$A$4:$B$12,$C9)>=1,Class=$B9),$A9,"")
A10: Symbolic Power | B10: Guardian | C10: Zeal | D10: Minor Grandmaster | E10: Symbols deal increased strike damage. | F10: =IF(AND(COUNTIF('Build & Totals'!$A$4:$B$12,$C10)>=1,Class=$B10),$A10,"")
A11: Eternal Armory | B11: Guardian | C11: Zeal | D11: Major Grandmaster | E11: Spirit Weapons gain additional casts and burn foes with their first strike. | F11: =IF(AND(COUNTIF('Build & Totals'!$A$4:$B$12,$C11)>=1,Class=$B11),$A11,"")
A12: Shattered Aegis | B12: Guardian | C12: Zeal | D12: Major Grandmaster | E12: When an aegis you applied blocks an attack, it unleashes a Mystic Rebuke. | F12: =IF(AND(COUNTIF('Build & Totals'!$A$4:$B$12,$C12)>=1,Class=$B12),$A12,"")
A13: Symbolic Avenger | B13: Guardian | C13: Zeal | D13: Major Grandmaster | E13: Your strike damage is increased whenever your Symbols hit a foe. | F13: =IF(AND(COUNTIF('Build & Totals'!$A$4:$B$12,$C13)>=1,Class=$B13),$A13,"")
A14: Justice is Blind | B14: Guardian | C14: Radiance | D14: Minor Adept | E14: Gain a light aura and blind nearby foes when you activate Virtue skill 1. | F14: =IF(AND(COUNTIF('Build & Totals'!$A$4:$B$12,$C14)>=1,Class=$B14),$A14,"")
A15: Inner Fire | B15: Guardian | C15: Radiance | D15: Major Adept | E15: Gain fury when you strike a foe that has burning stacks over the threshold. | F15: =IF(AND(COUNTIF('Build & Totals'!$A$4:$B$12,$C15)>=1,Class=$B15),$A15,"")
... A1000: Soul Twisting | B1000: Necromancer | C1000: Ritualist | D1000: Major Grandmaster | E1000: The first spirit skill you use when entering ritualist's shroud recharges instantly. | F1000: =IF(AND(COUNTIF('Build & Totals'!$A$4:$B$12,$C1000)>=1,Class=$B1000),$A1000,"")

Sheet Trait Stats
A1: Name | B1: Class | C1: Specialisation | D1: Tier | E1: Stat | F1: Amount | G1: Type 1 | H1: Type 2 | I1: Conditional? | J1: Condition | K1: Affecting Stat/Boon | L1: Note | M1: Max Stacks
A2: Aeromancer's Training | B2: Elementalist | C2: Air | D2: Minor Grandmaster | E2: Ferocity | F2: 150 | G2: Flat | L2: +150 Ferocity
A3: Aeromancer's Training | B3: Elementalist | C3: Air | D3: Minor Grandmaster | E3: Ferocity | F3: 150 | G3: Flat | L3: +150 Ferocity
A4: Arcane Lightning | B4: Elementalist | C4: Arcane | D4: Major Grandmaster | E4: Ferocity | F4: 150 | G4: Flat | I4: Yes | J4: Arcane Skill used | L4: +150 Ferocity on Arcane Skill use
A5: Burning Rage | B5: Elementalist | C5: Fire | D5: Major Master | E5: Condition Damage | F5: 180 | G5: Flat | L5: +180 Condition Damage
A6: Elemental Enhancement | B6: Elementalist | C6: Arcane | D6: Minor Grandmaster | E6: Concentration | F6: 180 | G6: Flat | L6: +180 Concentration
A7: Elemental Polyphony | B7: Elementalist | C7: Weaver | D7: Minor Grandmaster | E7: Power | F7: 200 | G7: Flat | I7: Yes | J7: Player attuned to Fire | L7: +200 Power while attuned to Fire
A8: Elemental Polyphony | B8: Elementalist | C8: Weaver | D8: Minor Grandmaster | E8: Healing Power | F8: 200 | G8: Flat | I8: Yes | J8: Player attuned to Water | L8: +200 Healing Power while attuned to Water
A9: Elemental Polyphony | B9: Elementalist | C9: Weaver | D9: Minor Grandmaster | E9: Ferocity | F9: 200 | G9: Flat | I9: Yes | J9: Player attuned to Air | L9: +200 Ferocity while attuned to Air
A10: Elemental Polyphony | B10: Elementalist | C10: Weaver | D10: Minor Grandmaster | E10: Vitality | F10: 200 | G10: Flat | I10: Yes | J10: Player attuned to Earth | L10: +200 Vitality while attuned to Earth
A11: Elements of Rage | B11: Elementalist | C11: Weaver | D11: Major Grandmaster | E11: Condition Damage | F11: 0.07 | G11: Percentage | I11: Yes | J11: Attuned to single element | L11: +7% Condition Damage when attuned to single element
A12: Elements of Rage | B12: Elementalist | C12: Weaver | D12: Major Grandmaster | E12: Precision | F12: 0.13 | G12: Percentage | H12: Derived | K12: Vitality | L12: +Precision, 13% of Vitality
A13: Enhanced Potency | B13: Elementalist | C13: Evoker | D13: Minor Master | E13: Condition Damage | F13: 5 | G13: Flat | H13: Boon Enhancement | I13: Yes | J13: Fox familiar | L13: +5 Condition Damage from Might stacks from Fox familiar
A14: Enhanced Potency | B14: Elementalist | C14: Evoker | D14: Minor Master | E14: Healing Power | F14: 0.2 | G14: Percentage | H14: Boon Enhancement | I14: Yes | J14: Otter familiar | K14: Regeneration | L14: +20% Healing Power from Regeneration from Otter familiar
A15: Enhanced Potency | B15: Elementalist | C15: Evoker | D15: Minor Master | E15: Crit Chance | F15: 0.15 | G15: Flat | H15: Boon Enhancement | I15: Yes | J15: Hare familiar | K15: Fury | L15: +15% Critical Chance from Fury from Hare familiar
A16: Familiar's Focus | B16: Elementalist | C16: Evoker | D16: Major Master | E16: Condition Damage | F16: 0.18 | G16: Percentage | I16: Yes | J16: Fox familiar | L16: +25% Condition Damage from Familiar's Prowess Fox familiar (overwrite)
A17: Familiar's Prowess | B17: Elementalist | C17: Evoker | D17: Minor Grandmaster | E17: Condition Damage | F17: 0.07 | G17: Percentage | I17: Yes | J17: Fox familiar | L17: +7% Condition Damage from Fox familiar
A18: Ferocious Winds | B18: Elementalist | C18: Air | D18: Major Adept | E18: Ferocity | F18: 0.07 | G18: Percentage | H18: Derived | K18: Precision | L18: +Ferocity, 7% of Precision
A19: Fresh Air | B19: Elementalist | C19: Air | D19: Major Grandmaster | E19: Ferocity | F19: 250 | G19: Flat | I19: Yes | J19: Player attuned to Air | L19: +250 Ferocity while attuned to Air
A20: Gathered Focus | B20: Elementalist | C20: Tempest | D20: Minor Master | E20: Concentration | F20: 240 | G20: Flat | L20: +240 Concentration
A21: Master's Fortitude | B21: Elementalist | C21: Weaver | D21: Major Adept | E21: Vitality | F21: 120 | G21: Flat | I21: Yes | J21: Sword equipped | L21: +120 Vitality with Sword equipped
A22: Master's Fortitude | B22: Elementalist | C22: Weaver | D22: Major Adept | E22: Vitality | F22: 0.05 | G22: Percentage | H22: Derived | K22: Power | L22: +Vitality, 5% of Power
A23: Master's Fortitude | B23: Elementalist | C23: Weaver | D23: Major Adept | E23: Vitality | F23: 0.05 | G23: Percentage | H23: Derived | K23: Condition Damage | L23: +Vitality, 5% of Condition Damage
A24: Power Overwhelming | B24: Elementalist | C24: Fire | D24: Major Master | E24: Power | F24: 150 | G24: Flat | I24: Yes | J24: 10+ stacks of Might | L24: +150 Power at 10 stacks of Might
A25: Raging Storm | B25: Elementalist | C25: Air | D25: Major Master | E25: Ferocity | F25: 180 | G25: Flat | H25: Boon Enhancement | K25: Fury | L25: +180 Ferocity from Fury
A26: Soothing Power | B26: Elementalist | C26: Water | D26: Major Grandmaster | E26: Vitality | F26: 300 | G26: Flat | L26: +300 Vitality
A27: Strength of Stone | B27: Elementalist | C27: Earth | D27: Major Master | E27: Condition Damage | F27: 0.1 | G27: Percentage | H27: Derived | K27: Toughness | L27: +Condition Damage, 10% of Toughness
A28: Weaver's Prowess | B28: Elementalist | C28: Weaver | D28: Major Master | E28: Condition Damage | F28: 0.05 | G28: Percentage | I28: Yes | J28: Recently attuned to different element | L28: +5% Condition Damage when attuning to different element
A29: Weaver's Prowess | B29: Elementalist | C29: Weaver | D29: Major Master | E29: Condition Duration | F29: 0.2 | G29: Flat | I29: Yes | J29: Recently attuned to different element | L29: +20% Condition Duration when attuning to different element
A30: Zephyr's Speed | B30: Elementalist | C30: Air | D30: Minor Adept | E30: Crit Chance | F30: 0.05 | G30: Flat | L30: +5% Critical Chance
A31: Applied Force | B31: Engineer | C31: Scrapper | D31: Major Grandmaster | E31: Power | F31: 30 | G31: Flat | H31: Boon Enhancement | K31: Might | L31: +30 Power from Might stacks
A32: Blast Shield | B32: Engineer | C32: Explosives | D32: Major Master | E32: Vitality | F32: 0.1 | G32: Percentage | H32: Derived | K32: Power | L32: +Vitality, 10% of Power
A33: Chemical Rounds | B33: Engineer | C33: Firearms | D33: Major Adept | E33: Condition Damage | F33: 120 | G33: Flat | L33: +120 Condition Damage
A34: Chemical Rounds | B34: Engineer | C34: Firearms | D34: Major Adept | E34: Condition Duration | F34: 0.33 | G34: Flat | I34: Yes | J34: Pistol Skill | L34: +33% Condition Duration on Pistol Skills
A35: Compounding Chemicals | B35: Engineer | C35: Alchemy | D35: Minor Grandmaster | E35: Concentration | F35: 240 | G35: Flat | L35: +240 Concentration
A36: Energy Amplifier | B36: Engineer | C36: Inventions | D36: Minor Grandmaster | E36: Power | F36: 250 | G36: Flat | H36: Boon Enhancement | K36: Regeneration | L36: +250 Power from Regeneration
A37: Energy Amplifier | B37: Engineer | C37: Inventions | D37: Minor Grandmaster | E37: Healing Power | F37: 250 | G37: Flat | H37: Boon Enhancement | K37: Regeneration | L37: +250 Healing Power from Regeneration
A38: Explosive Temper | B38: Engineer | C38: Explosives | D38: Major Master | E38: Ferocity | F38: 20 | G38: Flat | H38: Stacking | I38: Yes | J38: Explosion hit | L38: Stacking +20 Ferocity on Explosion hit | M38: 10
A39: Grand Entrance | B39: Engineer | C39: Explosives | D39: Major Grandmaster | E39: Crit Chance | F39: 0.1 | G39: Flat | I39: Yes | J39: Hit with Explosive Entrance | L39: +10% Critical Chance from Explosive Entrance
A40: Health Insurance | B40: Engineer | C40: Alchemy | D40: Major Adept | E40: Healing Power | F40: 0.2 | G40: Percentage | I40: Yes | J40: Med Kit equipped | L40: +20% Healing Power with Med Kit equipped
A41: Hematic Focus | B41: Engineer | C41: Firearms | D41: Minor Master | E41: Crit Damage | F41: 0.15 | G41: Flat | H41: Boon Enhancement | K41: Fury | L41: +15% Critical Chance from Fury
A42: High Caliber | B42: Engineer | C42: Firearms | D42: Major Adept | E42: Crit Chance | F42: 0.15 | G42: Flat | I42: Yes | J42: Foe within 450 distance units | L42: +15% Critical Chance within 450 distance units
A43: Hybrid Vigor | B43: Engineer | C43: Amalgam | D43: Minor Master | E43: Vitality | F43: 240 | G43: Flat | L43: +240 Vitality
A44: No Scope | B44: Engineer | C44: Firearms | D44: Major Master | E44: Ferocity | F44: 150 | G44: Flat | H44: Boon Enhancement | K44: Fury | L44: +150 Ferocity from Fury
A45: Thermal Vision | B45: Engineer | C45: Firearms | D45: Major Master | E45: Expertise | F45: 150 | G45: Flat | L45: +150 Expertise | U45: {=_xlfn._xlws.FILTER($A$2:$A$29,($C$2:$C$29='Trait Filters & Checks'!$A$3) * ($D$2:$D$29=U$43),"")} | W45: {=_xlfn._xlws.FILTER($A$2:$A$29,($C$2:$C$29='Trait Filters & Checks'!$A$3) * ($D$2:$D$29=W$43),"")}
A46: Thermal Vision | B46: Engineer | C46: Firearms | D46: Major Master | E46: Condition Damage | F46: 0.05 | G46: Percentage | I46: Yes | J46: Burning inflicted | L46: +5% Condition Damage when Burning inflicted
A47: Conceited Curate | B47: Guardian | C47: Willbender | D47: Major Adept | E47: Vitality | F47: 120 | G47: Flat | L47: +120 Vitality
A48: Defender's Dogma | B48: Guardian | C48: Dragonhunter | D48: Minor Master | E48: Vitality | F48: 180 | G48: Flat | L48: +180 Vitality
A49: Force of Will | B49: Guardian | C49: Honor | D49: Major Grandmaster | E49: Vitality | F49: 300 | G49: Flat | L49: +300 Vitality
A50: Honorable Staff | B50: Guardian | C50: Honor | D50: Major Master | E50: Concentration | F50: 120 | G50: Flat | L50: +120 Concentration
A51: Imbued Haste | B51: Guardian | C51: Firebrand | D51: Minor Grandmaster | E51: Condition Damage | F51: 250 | G51: Flat | H51: Boon Enhancement | K51: Quickness | L51: +250 Condition Damage from Quickness
A52: Imbued Haste | B52: Guardian | C52: Firebrand | D52: Minor Grandmaster | E52: Healing Power | F52: 250 | G52: Flat | H52: Boon Enhancement | K52: Quickness | L52: +250 Healing Power from Quickness
A53: Imbued Haste | B53: Guardian | C53: Firebrand | D53: Minor Grandmaster | E53: Vitality | F53: 250 | G53: Flat | H53: Boon Enhancement | K53: Quickness | L53: +250 Vitality from Quickness
A54: Kindled Zeal | B54: Guardian | C54: Zeal | D54: Major Master | E54: Condition Damage | F54: 0.1 | G54: Percentage | H54: Derived | K54: =_xlfn.TEXTAFTER(TraitStatsTable[[#This Row],[Note]], " ", -1) -> Power | L54: +Condition Damage, 10% of Power
A55: Light's Gift | B55: Guardian | C55: Luminary | D55: Minor Master | E55: Vitality | F55: 180 | G55: Flat | L55: +180 Vitality
A56: Power for Power | B56: Guardian | D56: Major Adept | E56: Power | F56: 120 | G56: Flat | L56: +120 Power
A57: Power of the Virtuous | B57: Guardian | C57: Virtues | D57: Minor Grandmaster | E57: Condition Damage | F57: 0.07 | G57: Percentage | H57: Derived | K57: =_xlfn.TEXTAFTER(TraitStatsTable[[#This Row],[Note]], " ", -1) -> Vitality | L57: +Condition Damage, 7% of Vitality
A58: Radiant Power | B58: Guardian | C58: Radiance | D58: Minor Grandmaster | E58: Ferocity | F58: 150 | G58: Flat | L58: +150 Ferocity
A59: Right-Hand Strength | B59: Guardian | C59: Radiance | D59: Major Adept | E59: Precision | F59: 80 | G59: Flat | L59: +80 Precision
A60: Right-Hand Strength | B60: Guardian | C60: Radiance | D60: Major Adept | E60: Power | F60: 80 | G60: Flat | I60: Yes | J60: One-Handed Weapon in Main Hand | L60: +80 Power with One-Handed Weapon in Main Hand
A61: Searing Pact | B61: Guardian | C61: Willbender | D61: Major Adept | E61: Condition Damage | F61: 120 | G61: Flat | L61: +120 Condition Damage
A62: Stalwart Defender | B62: Guardian | C62: Valor | D62: Major Master | E62: Toughness | F62: 240 | G62: Flat | I62: Yes | J62: Shield equipped | L62: +240 Toughness with Shield equipped
A63: Zealous Blade | B63: Guardian | C63: Zeal | D63: Major Master | E63: Power | F63: 120 | G63: Flat | L63: +120 Power
A64: Zealous Blade | B64: Guardian | C64: Zeal | D64: Major Master | E64: Power | F64: 120 | G64: Flat | I64: Yes | J64: Greatsword equipped | L64: +120 Power with Greatsword equipped
A65: Chaotic Persistence | B65: Mesmer | C65: Chaos | D65: Minor Grandmaster | E65: Concentration | F65: 250 | G65: Flat | H65: Boon Enhancement | K65: Regeneration | L65: +250 Concentration from Regeneration
A66: Chaotic Persistence | B66: Mesmer | C66: Chaos | D66: Minor Grandmaster | E66: Expertise | F66: 100 | G66: Flat | H66: Boon Enhancement | K66: Regeneration | L66: +100 Expertise from Regeneration
A67: Chaotic Potency | B67: Mesmer | C67: Chaos | D67: Major Master | E67: Condition Damage | F67: 120 | G67: Flat | L67: +120 Condition Damage
A68: Chaotic Potency | B68: Mesmer | C68: Chaos | D68: Major Master | E68: Condition Damage | F68: 120 | G68: Flat | I68: Yes | J68: Staff equipped | L68: +120 Condition Damage with Staff equipped
A69: Compounding Power | B69: Mesmer | C69: Illusions | D69: Minor Master | E69: Condition Damage | F69: 0.02 | G69: Percentage | H69: Stacking | I69: Yes | J69: Illusion created | L69: +2% Condition Damage per stack when creating Illusion | M69: 5
A70: Danger Time | B70: Mesmer | C70: Chronomancer | D70: Major Master | E70: Crit Chance | F70: 0.15 | G70: Flat | I70: Yes | J70: Hit on Slowed foe | L70: +15% Critical Chance against Slowed foes
A71: Deadly Blades | B71: Mesmer | C71: Virtuoso | D71: Minor Master | E71: Condition Damage | F71: 0.05 | G71: Percentage | I71: Yes | J71: Bladesong recently cast | L71: +5% Condition Damage after casting a Bladesong
A72: Fencer's Finesse | B72: Mesmer | C72: Dueling | D72: Major Master | E72: Ferocity | F72: 15 | G72: Flat | H72: Stacking | I72: Yes | J72: Hit with Sword or underwater Spear by Player or Player's Illusion | L72: +15 Ferocity per stack on hit or Illusion hit with Sword or underwater Spear | M72: 10
A73: Flow of Time | B73: Mesmer | C73: Chronomancer | D73: Minor Master | E73: Crit Chance | F73: 0.15 | G73: Flat | H73: Boon Enhancement | K73: Alacrity | L73: +15% Critical Chance from Alacrity
A74: Fortissimo | B74: Mesmer | C74: Troubadour | D74: Major Grandmaster | E74: All | F74: 0.04 | G74: Percentage | H74: Stacking | I74: Yes | J74: Instrument playing | L74: +4% to all attributes for each instrument playing | M74: 4
A75: Illusionary Membrane | B75: Mesmer | C75: Chaos | D75: Minor Master | E75: Condition Damage | F75: 0.07 | G75: Percentage | I75: Yes | J75: Chaos Aura active | L75: +7% Condition Damage from Chaos aura
A76: Nomad's Endurance | B76: Mesmer | C76: Mirage | D76: Minor Master | E76: Condition Damage | F76: 0.1 | G76: Percentage | H76: Boon Enhancement | K76: Vigor | L76: +10% Condition Damage from Vigor
A77: Quiet Intensity | B77: Mesmer | C77: Virtuoso | D77: Minor Grandmaster | E77: Crit Chance | F77: 0.15 | G77: Flat | H77: Boon Enhancement | K77: Fury | L77: +15% Critical Chance from Fury
A78: Quiet Intensity | B78: Mesmer | C78: Virtuoso | D78: Minor Grandmaster | E78: Ferocity | F78: 0.1 | G78: Percentage | H78: Derived | K78: Vitality | L78: +Ferocity, 10% of Vitality
A79: Sharpening Sorrow | B79: Mesmer | C79: Virtuoso | D79: Major Master | E79: Expertise | F79: 150 | G79: Flat | H79: Boon Enhancement | K79: Fury | L79: +150 Expertise from Fury
A80: Superiority Complex | B80: Mesmer | C80: Dueling | D80: Major Grandmaster | E80: Crit Damage | F80: 0.15 | G80: Flat | L80: +15% Critical Damage
A81: Superiority Complex | B81: Mesmer | C81: Dueling | D81: Major Grandmaster | E81: Crit Damage | F81: 0.1 | G81: Flat | I81: Yes | J81: Foe disabled or below 50% Health | L81: +10% Critical Damage against disabled foes or foes below 50% Health
A82: Symphonic Resonance | B82: Mesmer | C82: Troubadour | D82: Minor Master | E82: Condition Damage | F82: 0.25 | G82: Percentage | I82: Yes | J82: Lute playing in background | L82: +25% Condition Damage while Lute playing in background
A83: Alchemic Vigor | B83: Necromancer | C83: Harbinger | D83: Minor Master | E83: Vitality | F83: 240 | G83: Flat | L83: +240 Vitality
A84: Awaken the Pain | B84: Necromancer | C84: Spite | D84: Major Master | E84: Power | F84: 10 | G84: Flat | H84: Boon Enhancement | K84: Might | L84: +10 Power from Might stacks
A85: Awaken the Pain | B85: Necromancer | C85: Spite | D85: Major Master | E85: Condition Damage | F85: -10 | G85: Flat | H85: Boon Enhancement | K85: Might | L85: -10 Condition Damage from Might stacks
A86: Boon of Creation | B86: Necromancer | C86: Ritualist | D86: Minor Master | E86: Concentration | F86: 180 | G86: Flat | L86: +180 Concentration
A87: Cascading Corruption | B87: Necromancer | C87: Harbinger | D87: Major Grandmaster | E87: Power | F87: 240 | G87: Flat | L87: +240 Power
A88: Dark Gunslinger | B88: Necromancer | C88: Harbinger | D88: Major Master | E88: Expertise | F88: 0.13 | G88: Percentage | H88: Derived | K88: Vitality | L88: +Expertise, 13% of Vitality
A89: Deadly Strength | B89: Necromancer | C89: Death Magic | D89: Major Master | E89: Power | F89: 10 | G89: Flat | H89: Boon Enhancement | K89: Death's Carapace | L89: +10 Power per Death's Carapace stack
A90: Deadly Strength | B90: Necromancer | C90: Death Magic | D90: Major Master | E90: Condition Damage | F90: 10 | G90: Flat | H90: Boon Enhancement | K90: Death's Carapace | L90: +10 Condition Damage per Death's Carapace stack
A91: Death Perception | B91: Necromancer | C91: Soul Reaping | D91: Major Grandmaster | E91: Crit Chance | F91: 0.15 | G91: Flat | L91: +15% Critical Chance
A92: Death Perception | B92: Necromancer | C92: Soul Reaping | D92: Major Grandmaster | E92: Crit Damage | F92: 0.15 | G92: Flat | I92: Yes | J92: Shroud active | L92: +15% Critical Damage while in Shroud
A93: Decimate Defenses | B93: Necromancer | C93: Reaper | D93: Major Master | E93: Crit Chance | F93: 0.02 | G93: Flat | H93: Stacking | I93: Yes | J93: Foe is Vulnerable | L93: +2% Crit Chance on hit per Vulnerability stack on foe | M93: 25
A94: Doom Approaches | B94: Necromancer | C94: Harbinger | D94: Major Grandmaster | E94: Condition Damage | F94: 240 | G94: Flat | L94: +240 Condition Damage
A95: Fell Beacon | B95: Necromancer | C95: Scourge | D95: Major Master | E95: Expertise | F95: 0.07 | G95: Percentage | H95: Derived | K95: Condition Damage | L95: +Expertise, 7% of Condition Damage
A96: Furious Demise | B96: Necromancer | C96: Curses | D96: Minor Master | E96: Precision | F96: 180 | G96: Flat | L96: +180 Precision
A97: Implacable Foe | B97: Necromancer | C97: Harbinger | D97: Major Master | E97: Ferocity | F97: 0.13 | G97: Percentage | H97: Derived | K97: Vitality | L97: +Ferocity, 13% of Vitality
A98: Last Rites | B98: Necromancer | C98: Blood Magic | D98: Minor Grandmaster | E98: Healing Power | F98: 150 | G98: Flat | I98: Yes | J98: Player above 75% Health | L98: +150 Healing Power while player above 75% Health
A99: Last Rites | B99: Necromancer | C99: Blood Magic | D99: Minor Grandmaster | E99: Healing Power | F99: 300 | G99: Flat | I99: Yes | J99: Player below 75% Health | L99: +300 Healing Power while player below 75% Health
A100: Last Rites | B100: Necromancer | C100: Blood Magic | D100: Minor Grandmaster | E100: Healing Power | F100: 450 | G100: Flat | I100: Yes | J100: Player below 50% Health | L100: +450 Healing Power while player below 50% Health
...

Sheet Attributes & Prefixes
A1: Prefixes and Attributes | H1: Prefixes & Values
A2: Prefix | B2: Major | C2: Major 2 | D2: Minor | E2: Minor 2 | F2: Filtered | H2: Ref | I2: Prefix | J2: Slot | K2: Power | L2: Precision | M2: Toughness | N2: Vitality | O2: Concentration | P2: Condition Damage | Q2: Expertise | R2: Ferocity | S2: Healing Power
F3: (Select) | H3: =_xlfn.CONCAT(I$3,J3) -> ApostateWeapon (1H) | I3: =A4 -> Apostate | J3: Weapon (1H) | K3: {=IF(COUNTIF($B$4:$E$4, K$2)>0, _xlfn.IFS(COUNTIF($B$4:$C$4, K$2)>0, VLOOKUP($J3,'Gear Values'!$A$2:$E$13, IF(COUNTBLANK('Attributes & Prefixes'!$B$4:$C$4)>0, "2", "3"), 0), COUNTIF($D$4:$E$4, K$2)>0, VLOOKUP($J3,'Gear Values'!$A$2:$E$13, IF(COUNTBLANK('Attributes & Prefixes'!$B$4:$C$4)>0, "4", "5"), 0)), "")} | L3: {=IF(COUNTIF($B$4:$E$4, L$2)>0, _xlfn.IFS(COUNTIF($B$4:$C$4, L$2)>0, VLOOKUP($J3,'Gear Values'!$A$2:$E$13, IF(COUNTBLANK('Attributes & Prefixes'!$B$4:$C$4)>0, "2", "3"), 0), COUNTIF($D$4:$E$4, L$2)>0, VLOOKUP($J3,'Gear Values'!$A$2:$E$13, IF(COUNTBLANK('Attributes & Prefixes'!$B$4:$C$4)>0, "4", "5"), 0)), "")} | M3: {=IF(COUNTIF($B$4:$E$4, M$2)>0, _xlfn.IFS(COUNTIF($B$4:$C$4, M$2)>0, VLOOKUP($J3,'Gear Values'!$A$2:$E$13, IF(COUNTBLANK('Attributes & Prefixes'!$B$4:$C$4)>0, "2", "3"), 0), COUNTIF($D$4:$E$4, M$2)>0, VLOOKUP($J3,'Gear Values'!$A$2:$E$13, IF(COUNTBLANK('Attributes & Prefixes'!$B$4:$C$4)>0, "4", "5"), 0)), "")} -> 85 | N3: {=IF(COUNTIF($B$4:$E$4, N$2)>0, _xlfn.IFS(COUNTIF($B$4:$C$4, N$2)>0, VLOOKUP($J3,'Gear Values'!$A$2:$E$13, IF(COUNTBLANK('Attributes & Prefixes'!$B$4:$C$4)>0, "2", "3"), 0), COUNTIF($D$4:$E$4, N$2)>0, VLOOKUP($J3,'Gear Values'!$A$2:$E$13, IF(COUNTBLANK('Attributes & Prefixes'!$B$4:$C$4)>0, "4", "5"), 0)), "")} | O3: {=IF(COUNTIF($B$4:$E$4, O$2)>0, _xlfn.IFS(COUNTIF($B$4:$C$4, O$2)>0, VLOOKUP($J3,'Gear Values'!$A$2:$E$13, IF(COUNTBLANK('Attributes & Prefixes'!$B$4:$C$4)>0, "2", "3"), 0), COUNTIF($D$4:$E$4, O$2)>0, VLOOKUP($J3,'Gear Values'!$A$2:$E$13, IF(COUNTBLANK('Attributes & Prefixes'!$B$4:$C$4)>0, "4", "5"), 0)), "")} | P3: {=IF(COUNTIF($B$4:$E$4, P$2)>0, _xlfn.IFS(COUNTIF($B$4:$C$4, P$2)>0, VLOOKUP($J3,'Gear Values'!$A$2:$E$13, IF(COUNTBLANK('Attributes & Prefixes'!$B$4:$C$4)>0, "2", "3"), 0), COUNTIF($D$4:$E$4, P$2)>0, VLOOKUP($J3,'Gear Values'!$A$2:$E$13, IF(COUNTBLANK('Attributes & Prefixes'!$B$4:$C$4)>0, "4", "5"), 0)), "")} -> 120 | Q3: {=IF(COUNTIF($B$4:$E$4, Q$2)>0, _xlfn.IFS(COUNTIF($B$4:$C$4, Q$2)>0, VLOOKUP($J3,'Gear Values'!$A$2:$E$13, IF(COUNTBLANK('Attributes & Prefixes'!$B$4:$C$4)>0, "2", "3"), 0), COUNTIF($D$4:$E$4, Q$2)>0, VLOOKUP($J3,'Gear Values'!$A$2:$E$13, IF(COUNTBLANK('Attributes & Prefixes'!$B$4:$C$4)>0, "4", "5"), 0)), "")} | R3: {=IF(COUNTIF($B$4:$E$4, R$2)>0, _xlfn.IFS(COUNTIF($B$4:$C$4, R$2)>0, VLOOKUP($J3,'Gear Values'!$A$2:$E$13, IF(COUNTBLANK('Attributes & Prefixes'!$B$4:$C$4)>0, "2", "3"), 0), COUNTIF($D$4:$E$4, R$2)>0, VLOOKUP($J3,'Gear Values'!$A$2:$E$13, IF(COUNTBLANK('Attributes & Prefixes'!$B$4:$C$4)>0, "4", "5"), 0)), "")} | S3: {=IF(COUNTIF($B$4:$E$4, S$2)>0, _xlfn.IFS(COUNTIF($B$4:$C$4, S$2)>0, VLOOKUP($J3,'Gear Values'!$A$2:$E$13, IF(COUNTBLANK('Attributes & Prefixes'!$B$4:$C$4)>0, "2", "3"), 0), COUNTIF($D$4:$E$4, S$2)>0, VLOOKUP($J3,'Gear Values'!$A$2:$E$13, IF(COUNTBLANK('Attributes & Prefixes'!$B$4:$C$4)>0, "4", "5"), 0)), "")} -> 85
A4: Apostate | B4: Condition Damage | D4: Toughness | E4: Healing Power | F4: =IF(OR(COUNTBLANK(AttributeFilter) = 1,AttributeFilter="(Select)"), A4, IF(COUNTIF(B4:E4, AttributeFilter)>0, A4, "")) -> Apostate | H4: =_xlfn.CONCAT(I$3,J4) -> ApostateWeapon (2H) | J4: Weapon (2H) | K4: {=IF(COUNTIF($B$4:$E$4, K$2)>0, _xlfn.IFS(COUNTIF($B$4:$C$4, K$2)>0, VLOOKUP($J4,'Gear Values'!$A$2:$E$13, IF(COUNTBLANK('Attributes & Prefixes'!$B$4:$C$4)>0, "2", "3"), 0), COUNTIF($D$4:$E$4, K$2)>0, VLOOKUP($J4,'Gear Values'!$A$2:$E$13, IF(COUNTBLANK('Attributes & Prefixes'!$B$4:$C$4)>0, "4", "5"), 0)), "")} | L4: {=IF(COUNTIF($B$4:$E$4, L$2)>0, _xlfn.IFS(COUNTIF($B$4:$C$4, L$2)>0, VLOOKUP($J4,'Gear Values'!$A$2:$E$13, IF(COUNTBLANK('Attributes & Prefixes'!$B$4:$C$4)>0, "2", "3"), 0), COUNTIF($D$4:$E$4, L$2)>0, VLOOKUP($J4,'Gear Values'!$A$2:$E$13, IF(COUNTBLANK('Attributes & Prefixes'!$B$4:$C$4)>0, "4", "5"), 0)), "")} | M4: {=IF(COUNTIF($B$4:$E$4, M$2)>0, _xlfn.IFS(COUNTIF($B$4:$C$4, M$2)>0, VLOOKUP($J4,'Gear Values'!$A$2:$E$13, IF(COUNTBLANK('Attributes & Prefixes'!$B$4:$C$4)>0, "2", "3"), 0), COUNTIF($D$4:$E$4, M$2)>0, VLOOKUP($J4,'Gear Values'!$A$2:$E$13, IF(COUNTBLANK('Attributes & Prefixes'!$B$4:$C$4)>0, "4", "5"), 0)), "")} -> 171 | N4: {=IF(COUNTIF($B$4:$E$4, N$2)>0, _xlfn.IFS(COUNTIF($B$4:$C$4, N$2)>0, VLOOKUP($J4,'Gear Values'!$A$2:$E$13, IF(COUNTBLANK('Attributes & Prefixes'!$B$4:$C$4)>0, "2", "3"), 0), COUNTIF($D$4:$E$4, N$2)>0, VLOOKUP($J4,'Gear Values'!$A$2:$E$13, IF(COUNTBLANK('Attributes & Prefixes'!$B$4:$C$4)>0, "4", "5"), 0)), "")} | O4: {=IF(COUNTIF($B$4:$E$4, O$2)>0, _xlfn.IFS(COUNTIF($B$4:$C$4, O$2)>0, VLOOKUP($J4,'Gear Values'!$A$2:$E$13, IF(COUNTBLANK('Attributes & Prefixes'!$B$4:$C$4)>0, "2", "3"), 0), COUNTIF($D$4:$E$4, O$2)>0, VLOOKUP($J4,'Gear Values'!$A$2:$E$13, IF(COUNTBLANK('Attributes & Prefixes'!$B$4:$C$4)>0, "4", "5"), 0)), "")} | P4: {=IF(COUNTIF($B$4:$E$4, P$2)>0, _xlfn.IFS(COUNTIF($B$4:$C$4, P$2)>0, VLOOKUP($J4,'Gear Values'!$A$2:$E$13, IF(COUNTBLANK('Attributes & Prefixes'!$B$4:$C$4)>0, "2", "3"), 0), COUNTIF($D$4:$E$4, P$2)>0, VLOOKUP($J4,'Gear Values'!$A$2:$E$13, IF(COUNTBLANK('Attributes & Prefixes'!$B$4:$C$4)>0, "4", "5"), 0)), "")} -> 239 | Q4: {=IF(COUNTIF($B$4:$E$4, Q$2)>0, _xlfn.IFS(COUNTIF($B$4:$C$4, Q$2)>0, VLOOKUP($J4,'Gear Values'!$A$2:$E$13, IF(COUNTBLANK('Attributes & Prefixes'!$B$4:$C$4)>0, "2", "3"), 0), COUNTIF($D$4:$E$4, Q$2)>0, VLOOKUP($J4,'Gear Values'!$A$2:$E$13, IF(COUNTBLANK('Attributes & Prefixes'!$B$4:$C$4)>0, "4", "5"), 0)), "")} | R4: {=IF(COUNTIF($B$4:$E$4, R$2)>0, _xlfn.IFS(COUNTIF($B$4:$C$4, R$2)>0, VLOOKUP($J4,'Gear Values'!$A$2:$E$13, IF(COUNTBLANK('Attributes & Prefixes'!$B$4:$C$4)>0, "2", "3"), 0), COUNTIF($D$4:$E$4, R$2)>0, VLOOKUP($J4,'Gear Values'!$A$2:$E$13, IF(COUNTBLANK('Attributes & Prefixes'!$B$4:$C$4)>0, "4", "5"), 0)), "")} | S4: {=IF(COUNTIF($B$4:$E$4, S$2)>0, _xlfn.IFS(COUNTIF($B$4:$C$4, S$2)>0, VLOOKUP($J4,'Gear Values'!$A$2:$E$13, IF(COUNTBLANK('Attributes & Prefixes'!$B$4:$C$4)>0, "2", "3"), 0), COUNTIF($D$4:$E$4, S$2)>0, VLOOKUP($J4,'Gear Values'!$A$2:$E$13, IF(COUNTBLANK('Attributes & Prefixes'!$B$4:$C$4)>0, "4", "5"), 0)), "")} -> 171
A5: Apothecary | B5: Healing Power | D5: Toughness | E5: Condition Damage | F5: =IF(OR(COUNTBLANK(AttributeFilter) = 1,AttributeFilter="(Select)"), A5, IF(COUNTIF(B5:E5, AttributeFilter)>0, A5, "")) -> Apothecary | H5: =_xlfn.CONCAT(I$3,J5) -> ApostateHead | J5: Head | K5: {=IF(COUNTIF($B$4:$E$4, K$2)>0, _xlfn.IFS(COUNTIF($B$4:$C$4, K$2)>0, VLOOKUP($J5,'Gear Values'!$A$2:$E$13, IF(COUNTBLANK('Attributes & Prefixes'!$B$4:$C$4)>0, "2", "3"), 0), COUNTIF($D$4:$E$4, K$2)>0, VLOOKUP($J5,'Gear Values'!$A$2:$E$13, IF(COUNTBLANK('Attributes & Prefixes'!$B$4:$C$4)>0, "4", "5"), 0)), "")} | L5: {=IF(COUNTIF($B$4:$E$4, L$2)>0, _xlfn.IFS(COUNTIF($B$4:$C$4, L$2)>0, VLOOKUP($J5,'Gear Values'!$A$2:$E$13, IF(COUNTBLANK('Attributes & Prefixes'!$B$4:$C$4)>0, "2", "3"), 0), COUNTIF($D$4:$E$4, L$2)>0, VLOOKUP($J5,'Gear Values'!$A$2:$E$13, IF(COUNTBLANK('Attributes & Prefixes'!$B$4:$C$4)>0, "4", "5"), 0)), "")} | M5: {=IF(COUNTIF($B$4:$E$4, M$2)>0, _xlfn.IFS(COUNTIF($B$4:$C$4, M$2)>0, VLOOKUP($J5,'Gear Values'!$A$2:$E$13, IF(COUNTBLANK('Attributes & Prefixes'!$B$4:$C$4)>0, "2", "3"), 0), COUNTIF($D$4:$E$4, M$2)>0, VLOOKUP($J5,'Gear Values'!$A$2:$E$13, IF(COUNTBLANK('Attributes & Prefixes'!$B$4:$C$4)>0, "4", "5"), 0)), "")} -> 43 | N5: {=IF(COUNTIF($B$4:$E$4, N$2)>0, _xlfn.IFS(COUNTIF($B$4:$C$4, N$2)>0, VLOOKUP($J5,'Gear Values'!$A$2:$E$13, IF(COUNTBLANK('Attributes & Prefixes'!$B$4:$C$4)>0, "2", "3"), 0), COUNTIF($D$4:$E$4, N$2)>0, VLOOKUP($J5,'Gear Values'!$A$2:$E$13, IF(COUNTBLANK('Attributes & Prefixes'!$B$4:$C$4)>0, "4", "5"), 0)), "")} | O5: {=IF(COUNTIF($B$4:$E$4, O$2)>0, _xlfn.IFS(COUNTIF($B$4:$C$4, O$2)>0, VLOOKUP($J5,'Gear Values'!$A$2:$E$13, IF(COUNTBLANK('Attributes & Prefixes'!$B$4:$C$4)>0, "2", "3"), 0), COUNTIF($D$4:$E$4, O$2)>0, VLOOKUP($J5,'Gear Values'!$A$2:$E$13, IF(COUNTBLANK('Attributes & Prefixes'!$B$4:$C$4)>0, "4", "5"), 0)), "")} | P5: {=IF(COUNTIF($B$4:$E$4, P$2)>0, _xlfn.IFS(COUNTIF($B$4:$C$4, P$2)>0, VLOOKUP($J5,'Gear Values'!$A$2:$E$13, IF(COUNTBLANK('Attributes & Prefixes'!$B$4:$C$4)>0, "2", "3"), 0), COUNTIF($D$4:$E$4, P$2)>0, VLOOKUP($J5,'Gear Values'!$A$2:$E$13, IF(COUNTBLANK('Attributes & Prefixes'!$B$4:$C$4)>0, "4", "5"), 0)), "")} -> 60 | Q5: {=IF(COUNTIF($B$4:$E$4, Q$2)>0, _xlfn.IFS(COUNTIF($B$4:$C$4, Q$2)>0, VLOOKUP($J5,'Gear Values'!$A$2:$E$13, IF(COUNTBLANK('Attributes & Prefixes'!$B$4:$C$4)>0, "2", "3"), 0), COUNTIF($D$4:$E$4, Q$2)>0, VLOOKUP($J5,'Gear Values'!$A$2:$E$13, IF(COUNTBLANK('Attributes & Prefixes'!$B$4:$C$4)>0, "4", "5"), 0)), "")} | R5: {=IF(COUNTIF($B$4:$E$4, R$2)>0, _xlfn.IFS(COUNTIF($B$4:$C$4, R$2)>0, VLOOKUP($J5,'Gear Values'!$A$2:$E$13, IF(COUNTBLANK('Attributes & Prefixes'!$B$4:$C$4)>0, "2", "3"), 0), COUNTIF($D$4:$E$4, R$2)>0, VLOOKUP($J5,'Gear Values'!$A$2:$E$13, IF(COUNTBLANK('Attributes & Prefixes'!$B$4:$C$4)>0, "4", "5"), 0)), "")} | S5: {=IF(COUNTIF($B$4:$E$4, S$2)>0, _xlfn.IFS(COUNTIF($B$4:$C$4, S$2)>0, VLOOKUP($J5,'Gear Values'!$A$2:$E$13, IF(COUNTBLANK('Attributes & Prefixes'!$B$4:$C$4)>0, "2", "3"), 0), COUNTIF($D$4:$E$4, S$2)>0, VLOOKUP($J5,'Gear Values'!$A$2:$E$13, IF(COUNTBLANK('Attributes & Prefixes'!$B$4:$C$4)>0, "4", "5"), 0)), "")} -> 43
A6: Assassin | B6: Precision | D6: Power | E6: Ferocity | F6: =IF(OR(COUNTBLANK(AttributeFilter) = 1,AttributeFilter="(Select)"), A6, IF(COUNTIF(B6:E6, AttributeFilter)>0, A6, "")) -> Assassin | H6: =_xlfn.CONCAT(I$3,J6) -> ApostateShoulders | J6: Shoulders | K6: {=IF(COUNTIF($B$4:$E$4, K$2)>0, _xlfn.IFS(COUNTIF($B$4:$C$4, K$2)>0, VLOOKUP($J6,'Gear Values'!$A$2:$E$13, IF(COUNTBLANK('Attributes & Prefixes'!$B$4:$C$4)>0, "2", "3"), 0), COUNTIF($D$4:$E$4, K$2)>0, VLOOKUP($J6,'Gear Values'!$A$2:$E$13, IF(COUNTBLANK('Attributes & Prefixes'!$B$4:$C$4)>0, "4", "5"), 0)), "")} | L6: {=IF(COUNTIF($B$4:$E$4, L$2)>0, _xlfn.IFS(COUNTIF($B$4:$C$4, L$2)>0, VLOOKUP($J6,'Gear Values'!$A$2:$E$13, IF(COUNTBLANK('Attributes & Prefixes'!$B$4:$C$4)>0, "2", "3"), 0), COUNTIF($D$4:$E$4, L$2)>0, VLOOKUP($J6,'Gear Values'!$A$2:$E$13, IF(COUNTBLANK('Attributes & Prefixes'!$B$4:$C$4)>0, "4", "5"), 0)), "")} | M6: {=IF(COUNTIF($B$4:$E$4, M$2)>0, _xlfn.IFS(COUNTIF($B$4:$C$4, M$2)>0, VLOOKUP($J6,'Gear Values'!$A$2:$E$13, IF(COUNTBLANK('Attributes & Prefixes'!$B$4:$C$4)>0, "2", "3"), 0), COUNTIF($D$4:$E$4, M$2)>0, VLOOKUP($J6,'Gear Values'!$A$2:$E$13, IF(COUNTBLANK('Attributes & Prefixes'!$B$4:$C$4)>0, "4", "5"), 0)), "")} -> 32 | N6: {=IF(COUNTIF($B$4:$E$4, N$2)>0, _xlfn.IFS(COUNTIF($B$4:$C$4, N$2)>0, VLOOKUP($J6,'Gear Values'!$A$2:$E$13, IF(COUNTBLANK('Attributes & Prefixes'!$B$4:$C$4)>0, "2", "3"), 0), COUNTIF($D$4:$E$4, N$2)>0, VLOOKUP($J6,'Gear Values'!$A$2:$E$13, IF(COUNTBLANK('Attributes & Prefixes'!$B$4:$C$4)>0, "4", "5"), 0)), "")} | O6: {=IF(COUNTIF($B$4:$E$4, O$2)>0, _xlfn.IFS(COUNTIF($B$4:$C$4, O$2)>0, VLOOKUP($J6,'Gear Values'!$A$2:$E$13, IF(COUNTBLANK('Attributes & Prefixes'!$B$4:$C$4)>0, "2", "3"), 0), COUNTIF($D$4:$E$4, O$2)>0, VLOOKUP($J6,'Gear Values'!$A$2:$E$13, IF(COUNTBLANK('Attributes & Prefixes'!$B$4:$C$4)>0, "4", "5"), 0)), "")} | P6: {=IF(COUNTIF($B$4:$E$4, P$2)>0, _xlfn.IFS(COUNTIF($B$4:$C$4, P$2)>0, VLOOKUP($J6,'Gear Values'!$A$2:$E$13, IF(COUNTBLANK('Attributes & Prefixes'!$B$4:$C$4)>0, "2", "3"), 0), COUNTIF($D$4:$E$4, P$2)>0, VLOOKUP($J6,'Gear Values'!$A$2:$E$13, IF(COUNTBLANK('Attributes & Prefixes'!$B$4:$C$4)>0, "4", "5"), 0)), "")} -> 45 | Q6: {=IF(COUNTIF($B$4:$E$4, Q$2)>0, _xlfn.IFS(COUNTIF($B$4:$C$4, Q$2)>0, VLOOKUP($J6,'Gear Values'!$A$2:$E$13, IF(COUNTBLANK('Attributes & Prefixes'!$B$4:$C$4)>0, "2", "3"), 0), COUNTIF($D$4:$E$4, Q$2)>0, VLOOKUP($J6,'Gear Values'!$A$2:$E$13, IF(COUNTBLANK('Attributes & Prefixes'!$B$4:$C$4)>0, "4", "5"), 0)), "")} | R6: {=IF(COUNTIF($B$4:$E$4, R$2)>0, _xlfn.IFS(COUNTIF($B$4:$C$4, R$2)>0, VLOOKUP($J6,'Gear Values'!$A$2:$E$13, IF(COUNTBLANK('Attributes & Prefixes'!$B$4:$C$4)>0, "2", "3"), 0), COUNTIF($D$4:$E$4, R$2)>0, VLOOKUP($J6,'Gear Values'!$A$2:$E$13, IF(COUNTBLANK('Attributes & Prefixes'!$B$4:$C$4)>0, "4", "5"), 0)), "")} | S6: {=IF(COUNTIF($B$4:$E$4, S$2)>0, _xlfn.IFS(COUNTIF($B$4:$C$4, S$2)>0, VLOOKUP($J6,'Gear Values'!$A$2:$E$13, IF(COUNTBLANK('Attributes & Prefixes'!$B$4:$C$4)>0, "2", "3"), 0), COUNTIF($D$4:$E$4, S$2)>0, VLOOKUP($J6,'Gear Values'!$A$2:$E$13, IF(COUNTBLANK('Attributes & Prefixes'!$B$4:$C$4)>0, "4", "5"), 0)), "")} -> 32
A7: Avatar | B7: Power | C7: Precision | D7: Vitality | E7: Healing Power | F7: =IF(OR(COUNTBLANK(AttributeFilter) = 1,AttributeFilter="(Select)"), A7, IF(COUNTIF(B7:E7, AttributeFilter)>0, A7, "")) -> Avatar | H7: =_xlfn.CONCAT(I$3,J7) -> ApostateChest | J7: Chest | K7: {=IF(COUNTIF($B$4:$E$4, K$2)>0, _xlfn.IFS(COUNTIF($B$4:$C$4, K$2)>0, VLOOKUP($J7,'Gear Values'!$A$2:$E$13, IF(COUNTBLANK('Attributes & Prefixes'!$B$4:$C$4)>0, "2", "3"), 0), COUNTIF($D$4:$E$4, K$2)>0, VLOOKUP($J7,'Gear Values'!$A$2:$E$13, IF(COUNTBLANK('Attributes & Prefixes'!$B$4:$C$4)>0, "4", "5"), 0)), "")} | L7: {=IF(COUNTIF($B$4:$E$4, L$2)>0, _xlfn.IFS(COUNTIF($B$4:$C$4, L$2)>0, VLOOKUP($J7,'Gear Values'!$A$2:$E$13, IF(COUNTBLANK('Attributes & Prefixes'!$B$4:$C$4)>0, "2", "3"), 0), COUNTIF($D$4:$E$4, L$2)>0, VLOOKUP($J7,'Gear Values'!$A$2:$E$13, IF(COUNTBLANK('Attributes & Prefixes'!$B$4:$C$4)>0, "4", "5"), 0)), "")} | M7: {=IF(COUNTIF($B$4:$E$4, M$2)>0, _xlfn.IFS(COUNTIF($B$4:$C$4, M$2)>0, VLOOKUP($J7,'Gear Values'!$A$2:$E$13, IF(COUNTBLANK('Attributes & Prefixes'!$B$4:$C$4)>0, "2", "3"), 0), COUNTIF($D$4:$E$4, M$2)>0, VLOOKUP($J7,'Gear Values'!$A$2:$E$13, IF(COUNTBLANK('Attributes & Prefixes'!$B$4:$C$4)>0, "4", "5"), 0)), "")} -> 96 | N7: {=IF(COUNTIF($B$4:$E$4, N$2)>0, _xlfn.IFS(COUNTIF($B$4:$C$4, N$2)>0, VLOOKUP($J7,'Gear Values'!$A$2:$E$13, IF(COUNTBLANK('Attributes & Prefixes'!$B$4:$C$4)>0, "2", "3"), 0), COUNTIF($D$4:$E$4, N$2)>0, VLOOKUP($J7,'Gear Values'!$A$2:$E$13, IF(COUNTBLANK('Attributes & Prefixes'!$B$4:$C$4)>0, "4", "5"), 0)), "")} | O7: {=IF(COUNTIF($B$4:$E$4, O$2)>0, _xlfn.IFS(COUNTIF($B$4:$C$4, O$2)>0, VLOOKUP($J7,'Gear Values'!$A$2:$E$13, IF(COUNTBLANK('Attributes & Prefixes'!$B$4:$C$4)>0, "2", "3"), 0), COUNTIF($D$4:$E$4, O$2)>0, VLOOKUP($J7,'Gear Values'!$A$2:$E$13, IF(COUNTBLANK('Attributes & Prefixes'!$B$4:$C$4)>0, "4", "5"), 0)), "")} | P7: {=IF(COUNTIF($B$4:$E$4, P$2)>0, _xlfn.IFS(COUNTIF($B$4:$C$4, P$2)>0, VLOOKUP($J7,'Gear Values'!$A$2:$E$13, IF(COUNTBLANK('Attributes & Prefixes'!$B$4:$C$4)>0, "2", "3"), 0), COUNTIF($D$4:$E$4, P$2)>0, VLOOKUP($J7,'Gear Values'!$A$2:$E$13, IF(COUNTBLANK('Attributes & Prefixes'!$B$4:$C$4)>0, "4", "5"), 0)), "")} -> 134 | Q7: {=IF(COUNTIF($B$4:$E$4, Q$2)>0, _xlfn.IFS(COUNTIF($B$4:$C$4, Q$2)>0, VLOOKUP($J7,'Gear Values'!$A$2:$E$13, IF(COUNTBLANK('Attributes & Prefixes'!$B$4:$C$4)>0, "2", "3"), 0), COUNTIF($D$4:$E$4, Q$2)>0, VLOOKUP($J7,'Gear Values'!$A$2:$E$13, IF(COUNTBLANK('Attributes & Prefixes'!$B$4:$C$4)>0, "4", "5"), 0)), "")} | R7: {=IF(COUNTIF($B$4:$E$4, R$2)>0, _xlfn.IFS(COUNTIF($B$4:$C$4, R$2)>0, VLOOKUP($J7,'Gear Values'!$A$2:$E$13, IF(COUNTBLANK('Attributes & Prefixes'!$B$4:$C$4)>0, "2", "3"), 0), COUNTIF($D$4:$E$4, R$2)>0, VLOOKUP($J7,'Gear Values'!$A$2:$E$13, IF(COUNTBLANK('Attributes & Prefixes'!$B$4:$C$4)>0, "4", "5"), 0)), "")} | S7: {=IF(COUNTIF($B$4:$E$4, S$2)>0, _xlfn.IFS(COUNTIF($B$4:$C$4, S$2)>0, VLOOKUP($J7,'Gear Values'!$A$2:$E$13, IF(COUNTBLANK('Attributes & Prefixes'!$B$4:$C$4)>0, "2", "3"), 0), COUNTIF($D$4:$E$4, S$2)>0, VLOOKUP($J7,'Gear Values'!$A$2:$E$13, IF(COUNTBLANK('Attributes & Prefixes'!$B$4:$C$4)>0, "4", "5"), 0)), "")} -> 96
A8: Berserker | B8: Power | D8: Precision | E8: Ferocity | F8: =IF(OR(COUNTBLANK(AttributeFilter) = 1,AttributeFilter="(Select)"), A8, IF(COUNTIF(B8:E8, AttributeFilter)>0, A8, "")) -> Berserker | H8: =_xlfn.CONCAT(I$3,J8) -> ApostateHands | J8: Hands | K8: {=IF(COUNTIF($B$4:$E$4, K$2)>0, _xlfn.IFS(COUNTIF($B$4:$C$4, K$2)>0, VLOOKUP($J8,'Gear Values'!$A$2:$E$13, IF(COUNTBLANK('Attributes & Prefixes'!$B$4:$C$4)>0, "2", "3"), 0), COUNTIF($D$4:$E$4, K$2)>0, VLOOKUP($J8,'Gear Values'!$A$2:$E$13, IF(COUNTBLANK('Attributes & Prefixes'!$B$4:$C$4)>0, "4", "5"), 0)), "")} | L8: {=IF(COUNTIF($B$4:$E$4, L$2)>0, _xlfn.IFS(COUNTIF($B$4:$C$4, L$2)>0, VLOOKUP($J8,'Gear Values'!$A$2:$E$13, IF(COUNTBLANK('Attributes & Prefixes'!$B$4:$C$4)>0, "2", "3"), 0), COUNTIF($D$4:$E$4, L$2)>0, VLOOKUP($J8,'Gear Values'!$A$2:$E$13, IF(COUNTBLANK('Attributes & Prefixes'!$B$4:$C$4)>0, "4", "5"), 0)), "")} | M8: {=IF(COUNTIF($B$4:$E$4, M$2)>0, _xlfn.IFS(COUNTIF($B$4:$C$4, M$2)>0, VLOOKUP($J8,'Gear Values'!$A$2:$E$13, IF(COUNTBLANK('Attributes & Prefixes'!$B$4:$C$4)>0, "2", "3"), 0), COUNTIF($D$4:$E$4, M$2)>0, VLOOKUP($J8,'Gear Values'!$A$2:$E$13, IF(COUNTBLANK('Attributes & Prefixes'!$B$4:$C$4)>0, "4", "5"), 0)), "")} -> 32 | N8: {=IF(COUNTIF($B$4:$E$4, N$2)>0, _xlfn.IFS(COUNTIF($B$4:$C$4, N$2)>0, VLOOKUP($J8,'Gear Values'!$A$2:$E$13, IF(COUNTBLANK('Attributes & Prefixes'!$B$4:$C$4)>0, "2", "3"), 0), COUNTIF($D$4:$E$4, N$2)>0, VLOOKUP($J8,'Gear Values'!$A$2:$E$13, IF(COUNTBLANK('Attributes & Prefixes'!$B$4:$C$4)>0, "4", "5"), 0)), "")} | O8: {=IF(COUNTIF($B$4:$E$4, O$2)>0, _xlfn.IFS(COUNTIF($B$4:$C$4, O$2)>0, VLOOKUP($J8,'Gear Values'!$A$2:$E$13, IF(COUNTBLANK('Attributes & Prefixes'!$B$4:$C$4)>0, "2", "3"), 0), COUNTIF($D$4:$E$4, O$2)>0, VLOOKUP($J8,'Gear Values'!$A$2:$E$13, IF(COUNTBLANK('Attributes & Prefixes'!$B$4:$C$4)>0, "4", "5"), 0)), "")} | P8: {=IF(COUNTIF($B$4:$E$4, P$2)>0, _xlfn.IFS(COUNTIF($B$4:$C$4, P$2)>0, VLOOKUP($J8,'Gear Values'!$A$2:$E$13, IF(COUNTBLANK('Attributes & Prefixes'!$B$4:$C$4)>0, "2", "3"), 0), COUNTIF($D$4:$E$4, P$2)>0, VLOOKUP($J8,'Gear Values'!$A$2:$E$13, IF(COUNTBLANK('Attributes & Prefixes'!$B$4:$C$4)>0, "4", "5"), 0)), "")} -> 45 | Q8: {=IF(COUNTIF($B$4:$E$4, Q$2)>0, _xlfn.IFS(COUNTIF($B$4:$C$4, Q$2)>0, VLOOKUP($J8,'Gear Values'!$A$2:$E$13, IF(COUNTBLANK('Attributes & Prefixes'!$B$4:$C$4)>0, "2", "3"), 0), COUNTIF($D$4:$E$4, Q$2)>0, VLOOKUP($J8,'Gear Values'!$A$2:$E$13, IF(COUNTBLANK('Attributes & Prefixes'!$B$4:$C$4)>0, "4", "5"), 0)), "")} | R8: {=IF(COUNTIF($B$4:$E$4, R$2)>0, _xlfn.IFS(COUNTIF($B$4:$C$4, R$2)>0, VLOOKUP($J8,'Gear Values'!$A$2:$E$13, IF(COUNTBLANK('Attributes & Prefixes'!$B$4:$C$4)>0, "2", "3"), 0), COUNTIF($D$4:$E$4, R$2)>0, VLOOKUP($J8,'Gear Values'!$A$2:$E$13, IF(COUNTBLANK('Attributes & Prefixes'!$B$4:$C$4)>0, "4", "5"), 0)), "")} | S8: {=IF(COUNTIF($B$4:$E$4, S$2)>0, _xlfn.IFS(COUNTIF($B$4:$C$4, S$2)>0, VLOOKUP($J8,'Gear Values'!$A$2:$E$13, IF(COUNTBLANK('Attributes & Prefixes'!$B$4:$C$4)>0, "2", "3"), 0), COUNTIF($D$4:$E$4, S$2)>0, VLOOKUP($J8,'Gear Values'!$A$2:$E$13, IF(COUNTBLANK('Attributes & Prefixes'!$B$4:$C$4)>0, "4", "5"), 0)), "")} -> 32
A9: Bringer | B9: Expertise | D9: Precision | E9: Vitality | F9: =IF(OR(COUNTBLANK(AttributeFilter) = 1,AttributeFilter="(Select)"), A9, IF(COUNTIF(B9:E9, AttributeFilter)>0, A9, "")) -> Bringer | H9: =_xlfn.CONCAT(I$3,J9) -> ApostateLegs | J9: Legs | K9: {=IF(COUNTIF($B$4:$E$4, K$2)>0, _xlfn.IFS(COUNTIF($B$4:$C$4, K$2)>0, VLOOKUP($J9,'Gear Values'!$A$2:$E$13, IF(COUNTBLANK('Attributes & Prefixes'!$B$4:$C$4)>0, "2", "3"), 0), COUNTIF($D$4:$E$4, K$2)>0, VLOOKUP($J9,'Gear Values'!$A$2:$E$13, IF(COUNTBLANK('Attributes & Prefixes'!$B$4:$C$4)>0, "4", "5"), 0)), "")} | L9: {=IF(COUNTIF($B$4:$E$4, L$2)>0, _xlfn.IFS(COUNTIF($B$4:$C$4, L$2)>0, VLOOKUP($J9,'Gear Values'!$A$2:$E$13, IF(COUNTBLANK('Attributes & Prefixes'!$B$4:$C$4)>0, "2", "3"), 0), COUNTIF($D$4:$E$4, L$2)>0, VLOOKUP($J9,'Gear Values'!$A$2:$E$13, IF(COUNTBLANK('Attributes & Prefixes'!$B$4:$C$4)>0, "4", "5"), 0)), "")} | M9: {=IF(COUNTIF($B$4:$E$4, M$2)>0, _xlfn.IFS(COUNTIF($B$4:$C$4, M$2)>0, VLOOKUP($J9,'Gear Values'!$A$2:$E$13, IF(COUNTBLANK('Attributes & Prefixes'!$B$4:$C$4)>0, "2", "3"), 0), COUNTIF($D$4:$E$4, M$2)>0, VLOOKUP($J9,'Gear Values'!$A$2:$E$13, IF(COUNTBLANK('Attributes & Prefixes'!$B$4:$C$4)>0, "4", "5"), 0)), "")} -> 64 | N9: {=IF(COUNTIF($B$4:$E$4, N$2)>0, _xlfn.IFS(COUNTIF($B$4:$C$4, N$2)>0, VLOOKUP($J9,'Gear Values'!$A$2:$E$13, IF(COUNTBLANK('Attributes & Prefixes'!$B$4:$C$4)>0, "2", "3"), 0), COUNTIF($D$4:$E$4, N$2)>0, VLOOKUP($J9,'Gear Values'!$A$2:$E$13, IF(COUNTBLANK('Attributes & Prefixes'!$B$4:$C$4)>0, "4", "5"), 0)), "")} | O9: {=IF(COUNTIF($B$4:$E$4, O$2)>0, _xlfn.IFS(COUNTIF($B$4:$C$4, O$2)>0, VLOOKUP($J9,'Gear Values'!$A$2:$E$13, IF(COUNTBLANK('Attributes & Prefixes'!$B$4:$C$4)>0, "2", "3"), 0), COUNTIF($D$4:$E$4, O$2)>0, VLOOKUP($J9,'Gear Values'!$A$2:$E$13, IF(COUNTBLANK('Attributes & Prefixes'!$B$4:$C$4)>0, "4", "5"), 0)), "")} | P9: {=IF(COUNTIF($B$4:$E$4, P$2)>0, _xlfn.IFS(COUNTIF($B$4:$C$4, P$2)>0, VLOOKUP($J9,'Gear Values'!$A$2:$E$13, IF(COUNTBLANK('Attributes & Prefixes'!$B$4:$C$4)>0, "2", "3"), 0), COUNTIF($D$4:$E$4, P$2)>0, VLOOKUP($J9,'Gear Values'!$A$2:$E$13, IF(COUNTBLANK('Attributes & Prefixes'!$B$4:$C$4)>0, "4", "5"), 0)), "")} -> 90 | Q9: {=IF(COUNTIF($B$4:$E$4, Q$2)>0, _xlfn.IFS(COUNTIF($B$4:$C$4, Q$2)>0, VLOOKUP($J9,'Gear Values'!$A$2:$E$13, IF(COUNTBLANK('Attributes & Prefixes'!$B$4:$C$4)>0, "2", "3"), 0), COUNTIF($D$4:$E$4, Q$2)>0, VLOOKUP($J9,'Gear Values'!$A$2:$E$13, IF(COUNTBLANK('Attributes & Prefixes'!$B$4:$C$4)>0, "4", "5"), 0)), "")} | R9: {=IF(COUNTIF($B$4:$E$4, R$2)>0, _xlfn.IFS(COUNTIF($B$4:$C$4, R$2)>0, VLOOKUP($J9,'Gear Values'!$A$2:$E$13, IF(COUNTBLANK('Attributes & Prefixes'!$B$4:$C$4)>0, "2", "3"), 0), COUNTIF($D$4:$E$4, R$2)>0, VLOOKUP($J9,'Gear Values'!$A$2:$E$13, IF(COUNTBLANK('Attributes & Prefixes'!$B$4:$C$4)>0, "4", "5"), 0)), "")} | S9: {=IF(COUNTIF($B$4:$E$4, S$2)>0, _xlfn.IFS(COUNTIF($B$4:$C$4, S$2)>0, VLOOKUP($J9,'Gear Values'!$A$2:$E$13, IF(COUNTBLANK('Attributes & Prefixes'!$B$4:$C$4)>0, "2", "3"), 0), COUNTIF($D$4:$E$4, S$2)>0, VLOOKUP($J9,'Gear Values'!$A$2:$E$13, IF(COUNTBLANK('Attributes & Prefixes'!$B$4:$C$4)>0, "4", "5"), 0)), "")} -> 64
A10: Captain | B10: Precision | D10: Power | E10: Toughness | F10: =IF(OR(COUNTBLANK(AttributeFilter) = 1,AttributeFilter="(Select)"), A10, IF(COUNTIF(B10:E10, AttributeFilter)>0, A10, "")) -> Captain | H10: =_xlfn.CONCAT(I$3,J10) -> ApostateFeet | J10: Feet | K10: {=IF(COUNTIF($B$4:$E$4, K$2)>0, _xlfn.IFS(COUNTIF($B$4:$C$4, K$2)>0, VLOOKUP($J10,'Gear Values'!$A$2:$E$13, IF(COUNTBLANK('Attributes & Prefixes'!$B$4:$C$4)>0, "2", "3"), 0), COUNTIF($D$4:$E$4, K$2)>0, VLOOKUP($J10,'Gear Values'!$A$2:$E$13, IF(COUNTBLANK('Attributes & Prefixes'!$B$4:$C$4)>0, "4", "5"), 0)), "")} | L10: {=IF(COUNTIF($B$4:$E$4, L$2)>0, _xlfn.IFS(COUNTIF($B$4:$C$4, L$2)>0, VLOOKUP($J10,'Gear Values'!$A$2:$E$13, IF(COUNTBLANK('Attributes & Prefixes'!$B$4:$C$4)>0, "2", "3"), 0), COUNTIF($D$4:$E$4, L$2)>0, VLOOKUP($J10,'Gear Values'!$A$2:$E$13, IF(COUNTBLANK('Attributes & Prefixes'!$B$4:$C$4)>0, "4", "5"), 0)), "")} | M10: {=IF(COUNTIF($B$4:$E$4, M$2)>0, _xlfn.IFS(COUNTIF($B$4:$C$4, M$2)>0, VLOOKUP($J10,'Gear Values'!$A$2:$E$13, IF(COUNTBLANK('Attributes & Prefixes'!$B$4:$C$4)>0, "2", "3"), 0), COUNTIF($D$4:$E$4, M$2)>0, VLOOKUP($J10,'Gear Values'!$A$2:$E$13, IF(COUNTBLANK('Attributes & Prefixes'!$B$4:$C$4)>0, "4", "5"), 0)), "")} -> 32 | N10: {=IF(COUNTIF($B$4:$E$4, N$2)>0, _xlfn.IFS(COUNTIF($B$4:$C$4, N$2)>0, VLOOKUP($J10,'Gear Values'!$A$2:$E$13, IF(COUNTBLANK('Attributes & Prefixes'!$B$4:$C$4)>0, "2", "3"), 0), COUNTIF($D$4:$E$4, N$2)>0, VLOOKUP($J10,'Gear Values'!$A$2:$E$13, IF(COUNTBLANK('Attributes & Prefixes'!$B$4:$C$4)>0, "4", "5"), 0)), "")} | O10: {=IF(COUNTIF($B$4:$E$4, O$2)>0, _xlfn.IFS(COUNTIF($B$4:$C$4, O$2)>0, VLOOKUP($J10,'Gear Values'!$A$2:$E$13, IF(COUNTBLANK('Attributes & Prefixes'!$B$4:$C$4)>0, "2", "3"), 0), COUNTIF($D$4:$E$4, O$2)>0, VLOOKUP($J10,'Gear Values'!$A$2:$E$13, IF(COUNTBLANK('Attributes & Prefixes'!$B$4:$C$4)>0, "4", "5"), 0)), "")} | P10: {=IF(COUNTIF($B$4:$E$4, P$2)>0, _xlfn.IFS(COUNTIF($B$4:$C$4, P$2)>0, VLOOKUP($J10,'Gear Values'!$A$2:$E$13, IF(COUNTBLANK('Attributes & Prefixes'!$B$4:$C$4)>0, "2", "3"), 0), COUNTIF($D$4:$E$4, P$2)>0, VLOOKUP($J10,'Gear Values'!$A$2:$E$13, IF(COUNTBLANK('Attributes & Prefixes'!$B$4:$C$4)>0, "4", "5"), 0)), "")} -> 45 | Q10: {=IF(COUNTIF($B$4:$E$4, Q$2)>0, _xlfn.IFS(COUNTIF($B$4:$C$4, Q$2)>0, VLOOKUP($J10,'Gear Values'!$A$2:$E$13, IF(COUNTBLANK('Attributes & Prefixes'!$B$4:$C$4)>0, "2", "3"), 0), COUNTIF($D$4:$E$4, Q$2)>0, VLOOKUP($J10,'Gear Values'!$A$2:$E$13, IF(COUNTBLANK('Attributes & Prefixes'!$B$4:$C$4)>0, "4", "5"), 0)), "")} | R10: {=IF(COUNTIF($B$4:$E$4, R$2)>0, _xlfn.IFS(COUNTIF($B$4:$C$4, R$2)>0, VLOOKUP($J10,'Gear Values'!$A$2:$E$13, IF(COUNTBLANK('Attributes & Prefixes'!$B$4:$C$4)>0, "2", "3"), 0), COUNTIF($D$4:$E$4, R$2)>0, VLOOKUP($J10,'Gear Values'!$A$2:$E$13, IF(COUNTBLANK('Attributes & Prefixes'!$B$4:$C$4)>0, "4", "5"), 0)), "")} | S10: {=IF(COUNTIF($B$4:$E$4, S$2)>0, _xlfn.IFS(COUNTIF($B$4:$C$4, S$2)>0, VLOOKUP($J10,'Gear Values'!$A$2:$E$13, IF(COUNTBLANK('Attributes & Prefixes'!$B$4:$C$4)>0, "2", "3"), 0), COUNTIF($D$4:$E$4, S$2)>0, VLOOKUP($J10,'Gear Values'!$A$2:$E$13, IF(COUNTBLANK('Attributes & Prefixes'!$B$4:$C$4)>0, "4", "5"), 0)), "")} -> 32
A11: Carrion | B11: Condition Damage | D11: Power | E11: Vitality | F11: =IF(OR(COUNTBLANK(AttributeFilter) = 1,AttributeFilter="(Select)"), A11, IF(COUNTIF(B11:E11, AttributeFilter)>0, A11, "")) -> Carrion | H11: =_xlfn.CONCAT(I$3,J11) -> ApostateEar | J11: Ear | K11: {=IF(COUNTIF($B$4:$E$4, K$2)>0, _xlfn.IFS(COUNTIF($B$4:$C$4, K$2)>0, VLOOKUP($J11,'Gear Values'!$A$2:$E$13, IF(COUNTBLANK('Attributes & Prefixes'!$B$4:$C$4)>0, "2", "3"), 0), COUNTIF($D$4:$E$4, K$2)>0, VLOOKUP($J11,'Gear Values'!$A$2:$E$13, IF(COUNTBLANK('Attributes & Prefixes'!$B$4:$C$4)>0, "4", "5"), 0)), "")} | L11: {=IF(COUNTIF($B$4:$E$4, L$2)>0, _xlfn.IFS(COUNTIF($B$4:$C$4, L$2)>0, VLOOKUP($J11,'Gear Values'!$A$2:$E$13, IF(COUNTBLANK('Attributes & Prefixes'!$B$4:$C$4)>0, "2", "3"), 0), COUNTIF($D$4:$E$4, L$2)>0, VLOOKUP($J11,'Gear Values'!$A$2:$E$13, IF(COUNTBLANK('Attributes & Prefixes'!$B$4:$C$4)>0, "4", "5"), 0)), "")} | M11: {=IF(COUNTIF($B$4:$E$4, M$2)>0, _xlfn.IFS(COUNTIF($B$4:$C$4, M$2)>0, VLOOKUP($J11,'Gear Values'!$A$2:$E$13, IF(COUNTBLANK('Attributes & Prefixes'!$B$4:$C$4)>0, "2", "3"), 0), COUNTIF($D$4:$E$4, M$2)>0, VLOOKUP($J11,'Gear Values'!$A$2:$E$13, IF(COUNTBLANK('Attributes & Prefixes'!$B$4:$C$4)>0, "4", "5"), 0)), "")} -> 53 | N11: {=IF(COUNTIF($B$4:$E$4, N$2)>0, _xlfn.IFS(COUNTIF($B$4:$C$4, N$2)>0, VLOOKUP($J11,'Gear Values'!$A$2:$E$13, IF(COUNTBLANK('Attributes & Prefixes'!$B$4:$C$4)>0, "2", "3"), 0), COUNTIF($D$4:$E$4, N$2)>0, VLOOKUP($J11,'Gear Values'!$A$2:$E$13, IF(COUNTBLANK('Attributes & Prefixes'!$B$4:$C$4)>0, "4", "5"), 0)), "")} | O11: {=IF(COUNTIF($B$4:$E$4, O$2)>0, _xlfn.IFS(COUNTIF($B$4:$C$4, O$2)>0, VLOOKUP($J11,'Gear Values'!$A$2:$E$13, IF(COUNTBLANK('Attributes & Prefixes'!$B$4:$C$4)>0, "2", "3"), 0), COUNTIF($D$4:$E$4, O$2)>0, VLOOKUP($J11,'Gear Values'!$A$2:$E$13, IF(COUNTBLANK('Attributes & Prefixes'!$B$4:$C$4)>0, "4", "5"), 0)), "")} | P11: {=IF(COUNTIF($B$4:$E$4, P$2)>0, _xlfn.IFS(COUNTIF($B$4:$C$4, P$2)>0, VLOOKUP($J11,'Gear Values'!$A$2:$E$13, IF(COUNTBLANK('Attributes & Prefixes'!$B$4:$C$4)>0, "2", "3"), 0), COUNTIF($D$4:$E$4, P$2)>0, VLOOKUP($J11,'Gear Values'!$A$2:$E$13, IF(COUNTBLANK('Attributes & Prefixes'!$B$4:$C$4)>0, "4", "5"), 0)), "")} -> 75 | Q11: {=IF(COUNTIF($B$4:$E$4, Q$2)>0, _xlfn.IFS(COUNTIF($B$4:$C$4, Q$2)>0, VLOOKUP($J11,'Gear Values'!$A$2:$E$13, IF(COUNTBLANK('Attributes & Prefixes'!$B$4:$C$4)>0, "2", "3"), 0), COUNTIF($D$4:$E$4, Q$2)>0, VLOOKUP($J11,'Gear Values'!$A$2:$E$13, IF(COUNTBLANK('Attributes & Prefixes'!$B$4:$C$4)>0, "4", "5"), 0)), "")} | R11: {=IF(COUNTIF($B$4:$E$4, R$2)>0, _xlfn.IFS(COUNTIF($B$4:$C$4, R$2)>0, VLOOKUP($J11,'Gear Values'!$A$2:$E$13, IF(COUNTBLANK('Attributes & Prefixes'!$B$4:$C$4)>0, "2", "3"), 0), COUNTIF($D$4:$E$4, R$2)>0, VLOOKUP($J11,'Gear Values'!$A$2:$E$13, IF(COUNTBLANK('Attributes & Prefixes'!$B$4:$C$4)>0, "4", "5"), 0)), "")} | S11: {=IF(COUNTIF($B$4:$E$4, S$2)>0, _xlfn.IFS(COUNTIF($B$4:$C$4, S$2)>0, VLOOKUP($J11,'Gear Values'!$A$2:$E$13, IF(COUNTBLANK('Attributes & Prefixes'!$B$4:$C$4)>0, "2", "3"), 0), COUNTIF($D$4:$E$4, S$2)>0, VLOOKUP($J11,'Gear Values'!$A$2:$E$13, IF(COUNTBLANK('Attributes & Prefixes'!$B$4:$C$4)>0, "4", "5"), 0)), "")} -> 53
A12: Cavalier | B12: Toughness | D12: Power | E12: Ferocity | F12: =IF(OR(COUNTBLANK(AttributeFilter) = 1,AttributeFilter="(Select)"), A12, IF(COUNTIF(B12:E12, AttributeFilter)>0, A12, "")) -> Cavalier | H12: =_xlfn.CONCAT(I$3,J12) -> ApostateFinger | J12: Finger | K12: {=IF(COUNTIF($B$4:$E$4, K$2)>0, _xlfn.IFS(COUNTIF($B$4:$C$4, K$2)>0, VLOOKUP($J12,'Gear Values'!$A$2:$E$13, IF(COUNTBLANK('Attributes & Prefixes'!$B$4:$C$4)>0, "2", "3"), 0), COUNTIF($D$4:$E$4, K$2)>0, VLOOKUP($J12,'Gear Values'!$A$2:$E$13, IF(COUNTBLANK('Attributes & Prefixes'!$B$4:$C$4)>0, "4", "5"), 0)), "")} | L12: {=IF(COUNTIF($B$4:$E$4, L$2)>0, _xlfn.IFS(COUNTIF($B$4:$C$4, L$2)>0, VLOOKUP($J12,'Gear Values'!$A$2:$E$13, IF(COUNTBLANK('Attributes & Prefixes'!$B$4:$C$4)>0, "2", "3"), 0), COUNTIF($D$4:$E$4, L$2)>0, VLOOKUP($J12,'Gear Values'!$A$2:$E$13, IF(COUNTBLANK('Attributes & Prefixes'!$B$4:$C$4)>0, "4", "5"), 0)), "")} | M12: {=IF(COUNTIF($B$4:$E$4, M$2)>0, _xlfn.IFS(COUNTIF($B$4:$C$4, M$2)>0, VLOOKUP($J12,'Gear Values'!$A$2:$E$13, IF(COUNTBLANK('Attributes & Prefixes'!$B$4:$C$4)>0, "2", "3"), 0), COUNTIF($D$4:$E$4, M$2)>0, VLOOKUP($J12,'Gear Values'!$A$2:$E$13, IF(COUNTBLANK('Attributes & Prefixes'!$B$4:$C$4)>0, "4", "5"), 0)), "")} -> 64 | N12: {=IF(COUNTIF($B$4:$E$4, N$2)>0, _xlfn.IFS(COUNTIF($B$4:$C$4, N$2)>0, VLOOKUP($J12,'Gear Values'!$A$2:$E$13, IF(COUNTBLANK('Attributes & Prefixes'!$B$4:$C$4)>0, "2", "3"), 0), COUNTIF($D$4:$E$4, N$2)>0, VLOOKUP($J12,'Gear Values'!$A$2:$E$13, IF(COUNTBLANK('Attributes & Prefixes'!$B$4:$C$4)>0, "4", "5"), 0)), "")} | O12: {=IF(COUNTIF($B$4:$E$4, O$2)>0, _xlfn.IFS(COUNTIF($B$4:$C$4, O$2)>0, VLOOKUP($J12,'Gear Values'!$A$2:$E$13, IF(COUNTBLANK('Attributes & Prefixes'!$B$4:$C$4)>0, "2", "3"), 0), COUNTIF($D$4:$E$4, O$2)>0, VLOOKUP($J12,'Gear Values'!$A$2:$E$13, IF(COUNTBLANK('Attributes & Prefixes'!$B$4:$C$4)>0, "4", "5"), 0)), "")} | P12: {=IF(COUNTIF($B$4:$E$4, P$2)>0, _xlfn.IFS(COUNTIF($B$4:$C$4, P$2)>0, VLOOKUP($J12,'Gear Values'!$A$2:$E$13, IF(COUNTBLANK('Attributes & Prefixes'!$B$4:$C$4)>0, "2", "3"), 0), COUNTIF($D$4:$E$4, P$2)>0, VLOOKUP($J12,'Gear Values'!$A$2:$E$13, IF(COUNTBLANK('Attributes & Prefixes'!$B$4:$C$4)>0, "4", "5"), 0)), "")} -> 90 | Q12: {=IF(COUNTIF($B$4:$E$4, Q$2)>0, _xlfn.IFS(COUNTIF($B$4:$C$4, Q$2)>0, VLOOKUP($J12,'Gear Values'!$A$2:$E$13, IF(COUNTBLANK('Attributes & Prefixes'!$B$4:$C$4)>0, "2", "3"), 0), COUNTIF($D$4:$E$4, Q$2)>0, VLOOKUP($J12,'Gear Values'!$A$2:$E$13, IF(COUNTBLANK('Attributes & Prefixes'!$B$4:$C$4)>0, "4", "5"), 0)), "")} | R12: {=IF(COUNTIF($B$4:$E$4, R$2)>0, _xlfn.IFS(COUNTIF($B$4:$C$4, R$2)>0, VLOOKUP($J12,'Gear Values'!$A$2:$E$13, IF(COUNTBLANK('Attributes & Prefixes'!$B$4:$C$4)>0, "2", "3"), 0), COUNTIF($D$4:$E$4, R$2)>0, VLOOKUP($J12,'Gear Values'!$A$2:$E$13, IF(COUNTBLANK('Attributes & Prefixes'!$B$4:$C$4)>0, "4", "5"), 0)), "")} | S12: {=IF(COUNTIF($B$4:$E$4, S$2)>0, _xlfn.IFS(COUNTIF($B$4:$C$4, S$2)>0, VLOOKUP($J12,'Gear Values'!$A$2:$E$13, IF(COUNTBLANK('Attributes & Prefixes'!$B$4:$C$4)>0, "2", "3"), 0), COUNTIF($D$4:$E$4, S$2)>0, VLOOKUP($J12,'Gear Values'!$A$2:$E$13, IF(COUNTBLANK('Attributes & Prefixes'!$B$4:$C$4)>0, "4", "5"), 0)), "")} -> 64
A13: Celestial | B13: All attributes Minor | F13: =IF(OR(COUNTBLANK(AttributeFilter) = 1,AttributeFilter="(Select)"), A13, IF(COUNTIF(B13:E13, AttributeFilter)>0, A13, "")) -> Celestial | H13: =_xlfn.CONCAT(I$3,J13) -> ApostateNeck | J13: Neck | K13: {=IF(COUNTIF($B$4:$E$4, K$2)>0, _xlfn.IFS(COUNTIF($B$4:$C$4, K$2)>0, VLOOKUP($J13,'Gear Values'!$A$2:$E$13, IF(COUNTBLANK('Attributes & Prefixes'!$B$4:$C$4)>0, "2", "3"), 0), COUNTIF($D$4:$E$4, K$2)>0, VLOOKUP($J13,'Gear Values'!$A$2:$E$13, IF(COUNTBLANK('Attributes & Prefixes'!$B$4:$C$4)>0, "4", "5"), 0)), "")} | L13: {=IF(COUNTIF($B$4:$E$4, L$2)>0, _xlfn.IFS(COUNTIF($B$4:$C$4, L$2)>0, VLOOKUP($J13,'Gear Values'!$A$2:$E$13, IF(COUNTBLANK('Attributes & Prefixes'!$B$4:$C$4)>0, "2", "3"), 0), COUNTIF($D$4:$E$4, L$2)>0, VLOOKUP($J13,'Gear Values'!$A$2:$E$13, IF(COUNTBLANK('Attributes & Prefixes'!$B$4:$C$4)>0, "4", "5"), 0)), "")} | M13: {=IF(COUNTIF($B$4:$E$4, M$2)>0, _xlfn.IFS(COUNTIF($B$4:$C$4, M$2)>0, VLOOKUP($J13,'Gear Values'!$A$2:$E$13, IF(COUNTBLANK('Attributes & Prefixes'!$B$4:$C$4)>0, "2", "3"), 0), COUNTIF($D$4:$E$4, M$2)>0, VLOOKUP($J13,'Gear Values'!$A$2:$E$13, IF(COUNTBLANK('Attributes & Prefixes'!$B$4:$C$4)>0, "4", "5"), 0)), "")} -> 85 | N13: {=IF(COUNTIF($B$4:$E$4, N$2)>0, _xlfn.IFS(COUNTIF($B$4:$C$4, N$2)>0, VLOOKUP($J13,'Gear Values'!$A$2:$E$13, IF(COUNTBLANK('Attributes & Prefixes'!$B$4:$C$4)>0, "2", "3"), 0), COUNTIF($D$4:$E$4, N$2)>0, VLOOKUP($J13,'Gear Values'!$A$2:$E$13, IF(COUNTBLANK('Attributes & Prefixes'!$B$4:$C$4)>0, "4", "5"), 0)), "")} | O13: {=IF(COUNTIF($B$4:$E$4, O$2)>0, _xlfn.IFS(COUNTIF($B$4:$C$4, O$2)>0, VLOOKUP($J13,'Gear Values'!$A$2:$E$13, IF(COUNTBLANK('Attributes & Prefixes'!$B$4:$C$4)>0, "2", "3"), 0), COUNTIF($D$4:$E$4, O$2)>0, VLOOKUP($J13,'Gear Values'!$A$2:$E$13, IF(COUNTBLANK('Attributes & Prefixes'!$B$4:$C$4)>0, "4", "5"), 0)), "")} | P13: {=IF(COUNTIF($B$4:$E$4, P$2)>0, _xlfn.IFS(COUNTIF($B$4:$C$4, P$2)>0, VLOOKUP($J13,'Gear Values'!$A$2:$E$13, IF(COUNTBLANK('Attributes & Prefixes'!$B$4:$C$4)>0, "2", "3"), 0), COUNTIF($D$4:$E$4, P$2)>0, VLOOKUP($J13,'Gear Values'!$A$2:$E$13, IF(COUNTBLANK('Attributes & Prefixes'!$B$4:$C$4)>0, "4", "5"), 0)), "")} -> 120 | Q13: {=IF(COUNTIF($B$4:$E$4, Q$2)>0, _xlfn.IFS(COUNTIF($B$4:$C$4, Q$2)>0, VLOOKUP($J13,'Gear Values'!$A$2:$E$13, IF(COUNTBLANK('Attributes & Prefixes'!$B$4:$C$4)>0, "2", "3"), 0), COUNTIF($D$4:$E$4, Q$2)>0, VLOOKUP($J13,'Gear Values'!$A$2:$E$13, IF(COUNTBLANK('Attributes & Prefixes'!$B$4:$C$4)>0, "4", "5"), 0)), "")} | R13: {=IF(COUNTIF($B$4:$E$4, R$2)>0, _xlfn.IFS(COUNTIF($B$4:$C$4, R$2)>0, VLOOKUP($J13,'Gear Values'!$A$2:$E$13, IF(COUNTBLANK('Attributes & Prefixes'!$B$4:$C$4)>0, "2", "3"), 0), COUNTIF($D$4:$E$4, R$2)>0, VLOOKUP($J13,'Gear Values'!$A$2:$E$13, IF(COUNTBLANK('Attributes & Prefixes'!$B$4:$C$4)>0, "4", "5"), 0)), "")} | S13: {=IF(COUNTIF($B$4:$E$4, S$2)>0, _xlfn.IFS(COUNTIF($B$4:$C$4, S$2)>0, VLOOKUP($J13,'Gear Values'!$A$2:$E$13, IF(COUNTBLANK('Attributes & Prefixes'!$B$4:$C$4)>0, "2", "3"), 0), COUNTIF($D$4:$E$4, S$2)>0, VLOOKUP($J13,'Gear Values'!$A$2:$E$13, IF(COUNTBLANK('Attributes & Prefixes'!$B$4:$C$4)>0, "4", "5"), 0)), "")} -> 85
A14: Cleric | B14: Healing Power | D14: Power | E14: Toughness | F14: =IF(OR(COUNTBLANK(AttributeFilter) = 1,AttributeFilter="(Select)"), A14, IF(COUNTIF(B14:E14, AttributeFilter)>0, A14, "")) -> Cleric | H14: =_xlfn.CONCAT(I$3,J14) -> ApostateBack | J14: Back | K14: {=IF(COUNTIF($B$4:$E$4, K$2)>0, _xlfn.IFS(COUNTIF($B$4:$C$4, K$2)>0, VLOOKUP($J14,'Gear Values'!$A$2:$E$13, IF(COUNTBLANK('Attributes & Prefixes'!$B$4:$C$4)>0, "2", "3"), 0), COUNTIF($D$4:$E$4, K$2)>0, VLOOKUP($J14,'Gear Values'!$A$2:$E$13, IF(COUNTBLANK('Attributes & Prefixes'!$B$4:$C$4)>0, "4", "5"), 0)), "")} | L14: {=IF(COUNTIF($B$4:$E$4, L$2)>0, _xlfn.IFS(COUNTIF($B$4:$C$4, L$2)>0, VLOOKUP($J14,'Gear Values'!$A$2:$E$13, IF(COUNTBLANK('Attributes & Prefixes'!$B$4:$C$4)>0, "2", "3"), 0), COUNTIF($D$4:$E$4, L$2)>0, VLOOKUP($J14,'Gear Values'!$A$2:$E$13, IF(COUNTBLANK('Attributes & Prefixes'!$B$4:$C$4)>0, "4", "5"), 0)), "")} | M14: {=IF(COUNTIF($B$4:$E$4, M$2)>0, _xlfn.IFS(COUNTIF($B$4:$C$4, M$2)>0, VLOOKUP($J14,'Gear Values'!$A$2:$E$13, IF(COUNTBLANK('Attributes & Prefixes'!$B$4:$C$4)>0, "2", "3"), 0), COUNTIF($D$4:$E$4, M$2)>0, VLOOKUP($J14,'Gear Values'!$A$2:$E$13, IF(COUNTBLANK('Attributes & Prefixes'!$B$4:$C$4)>0, "4", "5"), 0)), "")} -> 18 | N14: {=IF(COUNTIF($B$4:$E$4, N$2)>0, _xlfn.IFS(COUNTIF($B$4:$C$4, N$2)>0, VLOOKUP($J14,'Gear Values'!$A$2:$E$13, IF(COUNTBLANK('Attributes & Prefixes'!$B$4:$C$4)>0, "2", "3"), 0), COUNTIF($D$4:$E$4, N$2)>0, VLOOKUP($J14,'Gear Values'!$A$2:$E$13, IF(COUNTBLANK('Attributes & Prefixes'!$B$4:$C$4)>0, "4", "5"), 0)), "")} | O14: {=IF(COUNTIF($B$4:$E$4, O$2)>0, _xlfn.IFS(COUNTIF($B$4:$C$4, O$2)>0, VLOOKUP($J14,'Gear Values'!$A$2:$E$13, IF(COUNTBLANK('Attributes & Prefixes'!$B$4:$C$4)>0, "2", "3"), 0), COUNTIF($D$4:$E$4, O$2)>0, VLOOKUP($J14,'Gear Values'!$A$2:$E$13, IF(COUNTBLANK('Attributes & Prefixes'!$B$4:$C$4)>0, "4", "5"), 0)), "")} | P14: {=IF(COUNTIF($B$4:$E$4, P$2)>0, _xlfn.IFS(COUNTIF($B$4:$C$4, P$2)>0, VLOOKUP($J14,'Gear Values'!$A$2:$E$13, IF(COUNTBLANK('Attributes & Prefixes'!$B$4:$C$4)>0, "2", "3"), 0), COUNTIF($D$4:$E$4, P$2)>0, VLOOKUP($J14,'Gear Values'!$A$2:$E$13, IF(COUNTBLANK('Attributes & Prefixes'!$B$4:$C$4)>0, "4", "5"), 0)), "")} -> 32 | Q14: {=IF(COUNTIF($B$4:$E$4, Q$2)>0, _xlfn.IFS(COUNTIF($B$4:$C$4, Q$2)>0, VLOOKUP($J14,'Gear Values'!$A$2:$E$13, IF(COUNTBLANK('Attributes & Prefixes'!$B$4:$C$4)>0, "2", "3"), 0), COUNTIF($D$4:$E$4, Q$2)>0, VLOOKUP($J14,'Gear Values'!$A$2:$E$13, IF(COUNTBLANK('Attributes & Prefixes'!$B$4:$C$4)>0, "4", "5"), 0)), "")} | R14: {=IF(COUNTIF($B$4:$E$4, R$2)>0, _xlfn.IFS(COUNTIF($B$4:$C$4, R$2)>0, VLOOKUP($J14,'Gear Values'!$A$2:$E$13, IF(COUNTBLANK('Attributes & Prefixes'!$B$4:$C$4)>0, "2", "3"), 0), COUNTIF($D$4:$E$4, R$2)>0, VLOOKUP($J14,'Gear Values'!$A$2:$E$13, IF(COUNTBLANK('Attributes & Prefixes'!$B$4:$C$4)>0, "4", "5"), 0)), "")} | S14: {=IF(COUNTIF($B$4:$E$4, S$2)>0, _xlfn.IFS(COUNTIF($B$4:$C$4, S$2)>0, VLOOKUP($J14,'Gear Values'!$A$2:$E$13, IF(COUNTBLANK('Attributes & Prefixes'!$B$4:$C$4)>0, "2", "3"), 0), COUNTIF($D$4:$E$4, S$2)>0, VLOOKUP($J14,'Gear Values'!$A$2:$E$13, IF(COUNTBLANK('Attributes & Prefixes'!$B$4:$C$4)>0, "4", "5"), 0)), "")} -> 18
A15: Commander | B15: Power | C15: Precision | D15: Toughness | E15: Concentration | F15: =IF(OR(COUNTBLANK(AttributeFilter) = 1,AttributeFilter="(Select)"), A15, IF(COUNTIF(B15:E15, AttributeFilter)>0, A15, "")) -> Commander | H15: =_xlfn.CONCAT(I$15,J15) -> ApothecaryWeapon (1H) | I15: =A5 -> Apothecary | J15: Weapon (1H) | K15: {=IF(COUNTIF($B$5:$E$5, K$2)>0, _xlfn.IFS(COUNTIF($B$5:$C$5, K$2)>0, VLOOKUP($J15,'Gear Values'!$A$2:$E$13, IF(COUNTBLANK('Attributes & Prefixes'!$B$5:$C$5)>0, "2", "3"), 0), COUNTIF($D$5:$E$5, K$2)>0, VLOOKUP($J15,'Gear Values'!$A$2:$E$13, IF(COUNTBLANK('Attributes & Prefixes'!$B$5:$C$5)>0, "4", "5"), 0)), "")} | L15: {=IF(COUNTIF($B$5:$E$5, L$2)>0, _xlfn.IFS(COUNTIF($B$5:$C$5, L$2)>0, VLOOKUP($J15,'Gear Values'!$A$2:$E$13, IF(COUNTBLANK('Attributes & Prefixes'!$B$5:$C$5)>0, "2", "3"), 0), COUNTIF($D$5:$E$5, L$2)>0, VLOOKUP($J15,'Gear Values'!$A$2:$E$13, IF(COUNTBLANK('Attributes & Prefixes'!$B$5:$C$5)>0, "4", "5"), 0)), "")} | M15: {=IF(COUNTIF($B$5:$E$5, M$2)>0, _xlfn.IFS(COUNTIF($B$5:$C$5, M$2)>0, VLOOKUP($J15,'Gear Values'!$A$2:$E$13, IF(COUNTBLANK('Attributes & Prefixes'!$B$5:$C$5)>0, "2", "3"), 0), COUNTIF($D$5:$E$5, M$2)>0, VLOOKUP($J15,'Gear Values'!$A$2:$E$13, IF(COUNTBLANK('Attributes & Prefixes'!$B$5:$C$5)>0, "4", "5"), 0)), "")} -> 85 | N15: {=IF(COUNTIF($B$5:$E$5, N$2)>0, _xlfn.IFS(COUNTIF($B$5:$C$5, N$2)>0, VLOOKUP($J15,'Gear Values'!$A$2:$E$13, IF(COUNTBLANK('Attributes & Prefixes'!$B$5:$C$5)>0, "2", "3"), 0), COUNTIF($D$5:$E$5, N$2)>0, VLOOKUP($J15,'Gear Values'!$A$2:$E$13, IF(COUNTBLANK('Attributes & Prefixes'!$B$5:$C$5)>0, "4", "5"), 0)), "")} | O15: {=IF(COUNTIF($B$5:$E$5, O$2)>0, _xlfn.IFS(COUNTIF($B$5:$C$5, O$2)>0, VLOOKUP($J15,'Gear Values'!$A$2:$E$13, IF(COUNTBLANK('Attributes & Prefixes'!$B$5:$C$5)>0, "2", "3"), 0), COUNTIF($D$5:$E$5, O$2)>0, VLOOKUP($J15,'Gear Values'!$A$2:$E$13, IF(COUNTBLANK('Attributes & Prefixes'!$B$5:$C$5)>0, "4", "5"), 0)), "")} | P15: {=IF(COUNTIF($B$5:$E$5, P$2)>0, _xlfn.IFS(COUNTIF($B$5:$C$5, P$2)>0, VLOOKUP($J15,'Gear Values'!$A$2:$E$13, IF(COUNTBLANK('Attributes & Prefixes'!$B$5:$C$5)>0, "2", "3"), 0), COUNTIF($D$5:$E$5, P$2)>0, VLOOKUP($J15,'Gear Values'!$A$2:$E$13, IF(COUNTBLANK('Attributes & Prefixes'!$B$5:$C$5)>0, "4", "5"), 0)), "")} -> 85 | Q15: {=IF(COUNTIF($B$5:$E$5, Q$2)>0, _xlfn.IFS(COUNTIF($B$5:$C$5, Q$2)>0, VLOOKUP($J15,'Gear Values'!$A$2:$E$13, IF(COUNTBLANK('Attributes & Prefixes'!$B$5:$C$5)>0, "2", "3"), 0), COUNTIF($D$5:$E$5, Q$2)>0, VLOOKUP($J15,'Gear Values'!$A$2:$E$13, IF(COUNTBLANK('Attributes & Prefixes'!$B$5:$C$5)>0, "4", "5"), 0)), "")} | R15: {=IF(COUNTIF($B$5:$E$5, R$2)>0, _xlfn.IFS(COUNTIF($B$5:$C$5, R$2)>0, VLOOKUP($J15,'Gear Values'!$A$2:$E$13, IF(COUNTBLANK('Attributes & Prefixes'!$B$5:$C$5)>0, "2", "3"), 0), COUNTIF($D$5:$E$5, R$2)>0, VLOOKUP($J15,'Gear Values'!$A$2:$E$13, IF(COUNTBLANK('Attributes & Prefixes'!$B$5:$C$5)>0, "4", "5"), 0)), "")} | S15: {=IF(COUNTIF($B$5:$E$5, S$2)>0, _xlfn.IFS(COUNTIF($B$5:$C$5, S$2)>0, VLOOKUP($J15,'Gear Values'!$A$2:$E$13, IF(COUNTBLANK('Attributes & Prefixes'!$B$5:$C$5)>0, "2", "3"), 0), COUNTIF($D$5:$E$5, S$2)>0, VLOOKUP($J15,'Gear Values'!$A$2:$E$13, IF(COUNTBLANK('Attributes & Prefixes'!$B$5:$C$5)>0, "4", "5"), 0)), "")} -> 120
A16: Crusader | B16: Power | C16: Toughness | D16: Ferocity | E16: Healing Power | F16: =IF(OR(COUNTBLANK(AttributeFilter) = 1,AttributeFilter="(Select)"), A16, IF(COUNTIF(B16:E16, AttributeFilter)>0, A16, "")) -> Crusader | H16: =_xlfn.CONCAT(I$15,J16) -> ApothecaryWeapon (2H) | J16: Weapon (2H) | K16: {=IF(COUNTIF($B$5:$E$5, K$2)>0, _xlfn.IFS(COUNTIF($B$5:$C$5, K$2)>0, VLOOKUP($J16,'Gear Values'!$A$2:$E$13, IF(COUNTBLANK('Attributes & Prefixes'!$B$5:$C$5)>0, "2", "3"), 0), COUNTIF($D$5:$E$5, K$2)>0, VLOOKUP($J16,'Gear Values'!$A$2:$E$13, IF(COUNTBLANK('Attributes & Prefixes'!$B$5:$C$5)>0, "4", "5"), 0)), "")} | L16: {=IF(COUNTIF($B$5:$E$5, L$2)>0, _xlfn.IFS(COUNTIF($B$5:$C$5, L$2)>0, VLOOKUP($J16,'Gear Values'!$A$2:$E$13, IF(COUNTBLANK('Attributes & Prefixes'!$B$5:$C$5)>0, "2", "3"), 0), COUNTIF($D$5:$E$5, L$2)>0, VLOOKUP($J16,'Gear Values'!$A$2:$E$13, IF(COUNTBLANK('Attributes & Prefixes'!$B$5:$C$5)>0, "4", "5"), 0)), "")} | M16: {=IF(COUNTIF($B$5:$E$5, M$2)>0, _xlfn.IFS(COUNTIF($B$5:$C$5, M$2)>0, VLOOKUP($J16,'Gear Values'!$A$2:$E$13, IF(COUNTBLANK('Attributes & Prefixes'!$B$5:$C$5)>0, "2", "3"), 0), COUNTIF($D$5:$E$5, M$2)>0, VLOOKUP($J16,'Gear Values'!$A$2:$E$13, IF(COUNTBLANK('Attributes & Prefixes'!$B$5:$C$5)>0, "4", "5"), 0)), "")} -> 171 | N16: {=IF(COUNTIF($B$5:$E$5, N$2)>0, _xlfn.IFS(COUNTIF($B$5:$C$5, N$2)>0, VLOOKUP($J16,'Gear Values'!$A$2:$E$13, IF(COUNTBLANK('Attributes & Prefixes'!$B$5:$C$5)>0, "2", "3"), 0), COUNTIF($D$5:$E$5, N$2)>0, VLOOKUP($J16,'Gear Values'!$A$2:$E$13, IF(COUNTBLANK('Attributes & Prefixes'!$B$5:$C$5)>0, "4", "5"), 0)), "")} | O16: {=IF(COUNTIF($B$5:$E$5, O$2)>0, _xlfn.IFS(COUNTIF($B$5:$C$5, O$2)>0, VLOOKUP($J16,'Gear Values'!$A$2:$E$13, IF(COUNTBLANK('Attributes & Prefixes'!$B$5:$C$5)>0, "2", "3"), 0), COUNTIF($D$5:$E$5, O$2)>0, VLOOKUP($J16,'Gear Values'!$A$2:$E$13, IF(COUNTBLANK('Attributes & Prefixes'!$B$5:$C$5)>0, "4", "5"), 0)), "")} | P16: {=IF(COUNTIF($B$5:$E$5, P$2)>0, _xlfn.IFS(COUNTIF($B$5:$C$5, P$2)>0, VLOOKUP($J16,'Gear Values'!$A$2:$E$13, IF(COUNTBLANK('Attributes & Prefixes'!$B$5:$C$5)>0, "2", "3"), 0), COUNTIF($D$5:$E$5, P$2)>0, VLOOKUP($J16,'Gear Values'!$A$2:$E$13, IF(COUNTBLANK('Attributes & Prefixes'!$B$5:$C$5)>0, "4", "5"), 0)), "")} -> 171 | Q16: {=IF(COUNTIF($B$5:$E$5, Q$2)>0, _xlfn.IFS(COUNTIF($B$5:$C$5, Q$2)>0, VLOOKUP($J16,'Gear Values'!$A$2:$E$13, IF(COUNTBLANK('Attributes & Prefixes'!$B$5:$C$5)>0, "2", "3"), 0), COUNTIF($D$5:$E$5, Q$2)>0, VLOOKUP($J16,'Gear Values'!$A$2:$E$13, IF(COUNTBLANK('Attributes & Prefixes'!$B$5:$C$5)>0, "4", "5"), 0)), "")} | R16: {=IF(COUNTIF($B$5:$E$5, R$2)>0, _xlfn.IFS(COUNTIF($B$5:$C$5, R$2)>0, VLOOKUP($J16,'Gear Values'!$A$2:$E$13, IF(COUNTBLANK('Attributes & Prefixes'!$B$5:$C$5)>0, "2", "3"), 0), COUNTIF($D$5:$E$5, R$2)>0, VLOOKUP($J16,'Gear Values'!$A$2:$E$13, IF(COUNTBLANK('Attributes & Prefixes'!$B$5:$C$5)>0, "4", "5"), 0)), "")} | S16: {=IF(COUNTIF($B$5:$E$5, S$2)>0, _xlfn.IFS(COUNTIF($B$5:$C$5, S$2)>0, VLOOKUP($J16,'Gear Values'!$A$2:$E$13, IF(COUNTBLANK('Attributes & Prefixes'!$B$5:$C$5)>0, "2", "3"), 0), COUNTIF($D$5:$E$5, S$2)>0, VLOOKUP($J16,'Gear Values'!$A$2:$E$13, IF(COUNTBLANK('Attributes & Prefixes'!$B$5:$C$5)>0, "4", "5"), 0)), "")} -> 239
A17: Demolisher | B17: Power | C17: Precision | D17: Toughness | E17: Ferocity | F17: =IF(OR(COUNTBLANK(AttributeFilter) = 1,AttributeFilter="(Select)"), A17, IF(COUNTIF(B17:E17, AttributeFilter)>0, A17, "")) -> Demolisher | H17: =_xlfn.CONCAT(I$15,J17) -> ApothecaryHead | J17: Head | K17: {=IF(COUNTIF($B$5:$E$5, K$2)>0, _xlfn.IFS(COUNTIF($B$5:$C$5, K$2)>0, VLOOKUP($J17,'Gear Values'!$A$2:$E$13, IF(COUNTBLANK('Attributes & Prefixes'!$B$5:$C$5)>0, "2", "3"), 0), COUNTIF($D$5:$E$5, K$2)>0, VLOOKUP($J17,'Gear Values'!$A$2:$E$13, IF(COUNTBLANK('Attributes & Prefixes'!$B$5:$C$5)>0, "4", "5"), 0)), "")} | L17: {=IF(COUNTIF($B$5:$E$5, L$2)>0, _xlfn.IFS(COUNTIF($B$5:$C$5, L$2)>0, VLOOKUP($J17,'Gear Values'!$A$2:$E$13, IF(COUNTBLANK('Attributes & Prefixes'!$B$5:$C$5)>0, "2", "3"), 0), COUNTIF($D$5:$E$5, L$2)>0, VLOOKUP($J17,'Gear Values'!$A$2:$E$13, IF(COUNTBLANK('Attributes & Prefixes'!$B$5:$C$5)>0, "4", "5"), 0)), "")} | M17: {=IF(COUNTIF($B$5:$E$5, M$2)>0, _xlfn.IFS(COUNTIF($B$5:$C$5, M$2)>0, VLOOKUP($J17,'Gear Values'!$A$2:$E$13, IF(COUNTBLANK('Attributes & Prefixes'!$B$5:$C$5)>0, "2", "3"), 0), COUNTIF($D$5:$E$5, M$2)>0, VLOOKUP($J17,'Gear Values'!$A$2:$E$13, IF(COUNTBLANK('Attributes & Prefixes'!$B$5:$C$5)>0, "4", "5"), 0)), "")} -> 43 | N17: {=IF(COUNTIF($B$5:$E$5, N$2)>0, _xlfn.IFS(COUNTIF($B$5:$C$5, N$2)>0, VLOOKUP($J17,'Gear Values'!$A$2:$E$13, IF(COUNTBLANK('Attributes & Prefixes'!$B$5:$C$5)>0, "2", "3"), 0), COUNTIF($D$5:$E$5, N$2)>0, VLOOKUP($J17,'Gear Values'!$A$2:$E$13, IF(COUNTBLANK('Attributes & Prefixes'!$B$5:$C$5)>0, "4", "5"), 0)), "")} | O17: {=IF(COUNTIF($B$5:$E$5, O$2)>0, _xlfn.IFS(COUNTIF($B$5:$C$5, O$2)>0, VLOOKUP($J17,'Gear Values'!$A$2:$E$13, IF(COUNTBLANK('Attributes & Prefixes'!$B$5:$C$5)>0, "2", "3"), 0), COUNTIF($D$5:$E$5, O$2)>0, VLOOKUP($J17,'Gear Values'!$A$2:$E$13, IF(COUNTBLANK('Attributes & Prefixes'!$B$5:$C$5)>0, "4", "5"), 0)), "")} | P17: {=IF(COUNTIF($B$5:$E$5, P$2)>0, _xlfn.IFS(COUNTIF($B$5:$C$5, P$2)>0, VLOOKUP($J17,'Gear Values'!$A$2:$E$13, IF(COUNTBLANK('Attributes & Prefixes'!$B$5:$C$5)>0, "2", "3"), 0), COUNTIF($D$5:$E$5, P$2)>0, VLOOKUP($J17,'Gear Values'!$A$2:$E$13, IF(COUNTBLANK('Attributes & Prefixes'!$B$5:$C$5)>0, "4", "5"), 0)), "")} -> 43 | Q17: {=IF(COUNTIF($B$5:$E$5, Q$2)>0, _xlfn.IFS(COUNTIF($B$5:$C$5, Q$2)>0, VLOOKUP($J17,'Gear Values'!$A$2:$E$13, IF(COUNTBLANK('Attributes & Prefixes'!$B$5:$C$5)>0, "2", "3"), 0), COUNTIF($D$5:$E$5, Q$2)>0, VLOOKUP($J17,'Gear Values'!$A$2:$E$13, IF(COUNTBLANK('Attributes & Prefixes'!$B$5:$C$5)>0, "4", "5"), 0)), "")} | R17: {=IF(COUNTIF($B$5:$E$5, R$2)>0, _xlfn.IFS(COUNTIF($B$5:$C$5, R$2)>0, VLOOKUP($J17,'Gear Values'!$A$2:$E$13, IF(COUNTBLANK('Attributes & Prefixes'!$B$5:$C$5)>0, "2", "3"), 0), COUNTIF($D$5:$E$5, R$2)>0, VLOOKUP($J17,'Gear Values'!$A$2:$E$13, IF(COUNTBLANK('Attributes & Prefixes'!$B$5:$C$5)>0, "4", "5"), 0)), "")} | S17: {=IF(COUNTIF($B$5:$E$5, S$2)>0, _xlfn.IFS(COUNTIF($B$5:$C$5, S$2)>0, VLOOKUP($J17,'Gear Values'!$A$2:$E$13, IF(COUNTBLANK('Attributes & Prefixes'!$B$5:$C$5)>0, "2", "3"), 0), COUNTIF($D$5:$E$5, S$2)>0, VLOOKUP($J17,'Gear Values'!$A$2:$E$13, IF(COUNTBLANK('Attributes & Prefixes'!$B$5:$C$5)>0, "4", "5"), 0)), "")} -> 60
A18: Destroyer | B18: Power | C18: Precision | D18: Condition Damage | E18: Ferocity | F18: =IF(OR(COUNTBLANK(AttributeFilter) = 1,AttributeFilter="(Select)"), A18, IF(COUNTIF(B18:E18, AttributeFilter)>0, A18, "")) -> Destroyer | H18: =_xlfn.CONCAT(I$15,J18) -> ApothecaryShoulders | J18: Shoulders | K18: {=IF(COUNTIF($B$5:$E$5, K$2)>0, _xlfn.IFS(COUNTIF($B$5:$C$5, K$2)>0, VLOOKUP($J18,'Gear Values'!$A$2:$E$13, IF(COUNTBLANK('Attributes & Prefixes'!$B$5:$C$5)>0, "2", "3"), 0), COUNTIF($D$5:$E$5, K$2)>0, VLOOKUP($J18,'Gear Values'!$A$2:$E$13, IF(COUNTBLANK('Attributes & Prefixes'!$B$5:$C$5)>0, "4", "5"), 0)), "")} | L18: {=IF(COUNTIF($B$5:$E$5, L$2)>0, _xlfn.IFS(COUNTIF($B$5:$C$5, L$2)>0, VLOOKUP($J18,'Gear Values'!$A$2:$E$13, IF(COUNTBLANK('Attributes & Prefixes'!$B$5:$C$5)>0, "2", "3"), 0), COUNTIF($D$5:$E$5, L$2)>0, VLOOKUP($J18,'Gear Values'!$A$2:$E$13, IF(COUNTBLANK('Attributes & Prefixes'!$B$5:$C$5)>0, "4", "5"), 0)), "")} | M18: {=IF(COUNTIF($B$5:$E$5, M$2)>0, _xlfn.IFS(COUNTIF($B$5:$C$5, M$2)>0, VLOOKUP($J18,'Gear Values'!$A$2:$E$13, IF(COUNTBLANK('Attributes & Prefixes'!$B$5:$C$5)>0, "2", "3"), 0), COUNTIF($D$5:$E$5, M$2)>0, VLOOKUP($J18,'Gear Values'!$A$2:$E$13, IF(COUNTBLANK('Attributes & Prefixes'!$B$5:$C$5)>0, "4", "5"), 0)), "")} -> 32 | N18: {=IF(COUNTIF($B$5:$E$5, N$2)>0, _xlfn.IFS(COUNTIF($B$5:$C$5, N$2)>0, VLOOKUP($J18,'Gear Values'!$A$2:$E$13, IF(COUNTBLANK('Attributes & Prefixes'!$B$5:$C$5)>0, "2", "3"), 0), COUNTIF($D$5:$E$5, N$2)>0, VLOOKUP($J18,'Gear Values'!$A$2:$E$13, IF(COUNTBLANK('Attributes & Prefixes'!$B$5:$C$5)>0, "4", "5"), 0)), "")} | O18: {=IF(COUNTIF($B$5:$E$5, O$2)>0, _xlfn.IFS(COUNTIF($B$5:$C$5, O$2)>0, VLOOKUP($J18,'Gear Values'!$A$2:$E$13, IF(COUNTBLANK('Attributes & Prefixes'!$B$5:$C$5)>0, "2", "3"), 0), COUNTIF($D$5:$E$5, O$2)>0, VLOOKUP($J18,'Gear Values'!$A$2:$E$13, IF(COUNTBLANK('Attributes & Prefixes'!$B$5:$C$5)>0, "4", "5"), 0)), "")} | P18: {=IF(COUNTIF($B$5:$E$5, P$2)>0, _xlfn.IFS(COUNTIF($B$5:$C$5, P$2)>0, VLOOKUP($J18,'Gear Values'!$A$2:$E$13, IF(COUNTBLANK('Attributes & Prefixes'!$B$5:$C$5)>0, "2", "3"), 0), COUNTIF($D$5:$E$5, P$2)>0, VLOOKUP($J18,'Gear Values'!$A$2:$E$13, IF(COUNTBLANK('Attributes & Prefixes'!$B$5:$C$5)>0, "4", "5"), 0)), "")} -> 32 | Q18: {=IF(COUNTIF($B$5:$E$5, Q$2)>0, _xlfn.IFS(COUNTIF($B$5:$C$5, Q$2)>0, VLOOKUP($J18,'Gear Values'!$A$2:$E$13, IF(COUNTBLANK('Attributes & Prefixes'!$B$5:$C$5)>0, "2", "3"), 0), COUNTIF($D$5:$E$5, Q$2)>0, VLOOKUP($J18,'Gear Values'!$A$2:$E$13, IF(COUNTBLANK('Attributes & Prefixes'!$B$5:$C$5)>0, "4", "5"), 0)), "")} | R18: {=IF(COUNTIF($B$5:$E$5, R$2)>0, _xlfn.IFS(COUNTIF($B$5:$C$5, R$2)>0, VLOOKUP($J18,'Gear Values'!$A$2:$E$13, IF(COUNTBLANK('Attributes & Prefixes'!$B$5:$C$5)>0, "2", "3"), 0), COUNTIF($D$5:$E$5, R$2)>0, VLOOKUP($J18,'Gear Values'!$A$2:$E$13, IF(COUNTBLANK('Attributes & Prefixes'!$B$5:$C$5)>0, "4", "5"), 0)), "")} | S18: {=IF(COUNTIF($B$5:$E$5, S$2)>0, _xlfn.IFS(COUNTIF($B$5:$C$5, S$2)>0, VLOOKUP($J18,'Gear Values'!$A$2:$E$13, IF(COUNTBLANK('Attributes & Prefixes'!$B$5:$C$5)>0, "2", "3"), 0), COUNTIF($D$5:$E$5, S$2)>0, VLOOKUP($J18,'Gear Values'!$A$2:$E$13, IF(COUNTBLANK('Attributes & Prefixes'!$B$5:$C$5)>0, "4", "5"), 0)), "")} -> 45
A19: Dire | B19: Condition Damage | D19: Toughness | E19: Vitality | F19: =IF(OR(COUNTBLANK(AttributeFilter) = 1,AttributeFilter="(Select)"), A19, IF(COUNTIF(B19:E19, AttributeFilter)>0, A19, "")) -> Dire | H19: =_xlfn.CONCAT(I$15,J19) -> ApothecaryChest | J19: Chest | K19: {=IF(COUNTIF($B$5:$E$5, K$2)>0, _xlfn.IFS(COUNTIF($B$5:$C$5, K$2)>0, VLOOKUP($J19,'Gear Values'!$A$2:$E$13, IF(COUNTBLANK('Attributes & Prefixes'!$B$5:$C$5)>0, "2", "3"), 0), COUNTIF($D$5:$E$5, K$2)>0, VLOOKUP($J19,'Gear Values'!$A$2:$E$13, IF(COUNTBLANK('Attributes & Prefixes'!$B$5:$C$5)>0, "4", "5"), 0)), "")} | L19: {=IF(COUNTIF($B$5:$E$5, L$2)>0, _xlfn.IFS(COUNTIF($B$5:$C$5, L$2)>0, VLOOKUP($J19,'Gear Values'!$A$2:$E$13, IF(COUNTBLANK('Attributes & Prefixes'!$B$5:$C$5)>0, "2", "3"), 0), COUNTIF($D$5:$E$5, L$2)>0, VLOOKUP($J19,'Gear Values'!$A$2:$E$13, IF(COUNTBLANK('Attributes & Prefixes'!$B$5:$C$5)>0, "4", "5"), 0)), "")} | M19: {=IF(COUNTIF($B$5:$E$5, M$2)>0, _xlfn.IFS(COUNTIF($B$5:$C$5, M$2)>0, VLOOKUP($J19,'Gear Values'!$A$2:$E$13, IF(COUNTBLANK('Attributes & Prefixes'!$B$5:$C$5)>0, "2", "3"), 0), COUNTIF($D$5:$E$5, M$2)>0, VLOOKUP($J19,'Gear Values'!$A$2:$E$13, IF(COUNTBLANK('Attributes & Prefixes'!$B$5:$C$5)>0, "4", "5"), 0)), "")} -> 96 | N19: {=IF(COUNTIF($B$5:$E$5, N$2)>0, _xlfn.IFS(COUNTIF($B$5:$C$5, N$2)>0, VLOOKUP($J19,'Gear Values'!$A$2:$E$13, IF(COUNTBLANK('Attributes & Prefixes'!$B$5:$C$5)>0, "2", "3"), 0), COUNTIF($D$5:$E$5, N$2)>0, VLOOKUP($J19,'Gear Values'!$A$2:$E$13, IF(COUNTBLANK('Attributes & Prefixes'!$B$5:$C$5)>0, "4", "5"), 0)), "")} | O19: {=IF(COUNTIF($B$5:$E$5, O$2)>0, _xlfn.IFS(COUNTIF($B$5:$C$5, O$2)>0, VLOOKUP($J19,'Gear Values'!$A$2:$E$13, IF(COUNTBLANK('Attributes & Prefixes'!$B$5:$C$5)>0, "2", "3"), 0), COUNTIF($D$5:$E$5, O$2)>0, VLOOKUP($J19,'Gear Values'!$A$2:$E$13, IF(COUNTBLANK('Attributes & Prefixes'!$B$5:$C$5)>0, "4", "5"), 0)), "")} | P19: {=IF(COUNTIF($B$5:$E$5, P$2)>0, _xlfn.IFS(COUNTIF($B$5:$C$5, P$2)>0, VLOOKUP($J19,'Gear Values'!$A$2:$E$13, IF(COUNTBLANK('Attributes & Prefixes'!$B$5:$C$5)>0, "2", "3"), 0), COUNTIF($D$5:$E$5, P$2)>0, VLOOKUP($J19,'Gear Values'!$A$2:$E$13, IF(COUNTBLANK('Attributes & Prefixes'!$B$5:$C$5)>0, "4", "5"), 0)), "")} -> 96 | Q19: {=IF(COUNTIF($B$5:$E$5, Q$2)>0, _xlfn.IFS(COUNTIF($B$5:$C$5, Q$2)>0, VLOOKUP($J19,'Gear Values'!$A$2:$E$13, IF(COUNTBLANK('Attributes & Prefixes'!$B$5:$C$5)>0, "2", "3"), 0), COUNTIF($D$5:$E$5, Q$2)>0, VLOOKUP($J19,'Gear Values'!$A$2:$E$13, IF(COUNTBLANK('Attributes & Prefixes'!$B$5:$C$5)>0, "4", "5"), 0)), "")} | R19: {=IF(COUNTIF($B$5:$E$5, R$2)>0, _xlfn.IFS(COUNTIF($B$5:$C$5, R$2)>0, VLOOKUP($J19,'Gear Values'!$A$2:$E$13, IF(COUNTBLANK('Attributes & Prefixes'!$B$5:$C$5)>0, "2", "3"), 0), COUNTIF($D$5:$E$5, R$2)>0, VLOOKUP($J19,'Gear Values'!$A$2:$E$13, IF(COUNTBLANK('Attributes & Prefixes'!$B$5:$C$5)>0, "4", "5"), 0)), "")} | S19: {=IF(COUNTIF($B$5:$E$5, S$2)>0, _xlfn.IFS(COUNTIF($B$5:$C$5, S$2)>0, VLOOKUP($J19,'Gear Values'!$A$2:$E$13, IF(COUNTBLANK('Attributes & Prefixes'!$B$5:$C$5)>0, "2", "3"), 0), COUNTIF($D$5:$E$5, S$2)>0, VLOOKUP($J19,'Gear Values'!$A$2:$E$13, IF(COUNTBLANK('Attributes & Prefixes'!$B$5:$C$5)>0, "4", "5"), 0)), "")} -> 134
A20: Diviner | B20: Power | C20: Concentration | D20: Precision | E20: Ferocity | F20: =IF(OR(COUNTBLANK(AttributeFilter) = 1,AttributeFilter="(Select)"), A20, IF(COUNTIF(B20:E20, AttributeFilter)>0, A20, "")) -> Diviner | H20: =_xlfn.CONCAT(I$15,J20) -> ApothecaryHands | J20: Hands | K20: {=IF(COUNTIF($B$5:$E$5, K$2)>0, _xlfn.IFS(COUNTIF($B$5:$C$5, K$2)>0, VLOOKUP($J20,'Gear Values'!$A$2:$E$13, IF(COUNTBLANK('Attributes & Prefixes'!$B$5:$C$5)>0, "2", "3"), 0), COUNTIF($D$5:$E$5, K$2)>0, VLOOKUP($J20,'Gear Values'!$A$2:$E$13, IF(COUNTBLANK('Attributes & Prefixes'!$B$5:$C$5)>0, "4", "5"), 0)), "")} | L20: {=IF(COUNTIF($B$5:$E$5, L$2)>0, _xlfn.IFS(COUNTIF($B$5:$C$5, L$2)>0, VLOOKUP($J20,'Gear Values'!$A$2:$E$13, IF(COUNTBLANK('Attributes & Prefixes'!$B$5:$C$5)>0, "2", "3"), 0), COUNTIF($D$5:$E$5, L$2)>0, VLOOKUP($J20,'Gear Values'!$A$2:$E$13, IF(COUNTBLANK('Attributes & Prefixes'!$B$5:$C$5)>0, "4", "5"), 0)), "")} | M20: {=IF(COUNTIF($B$5:$E$5, M$2)>0, _xlfn.IFS(COUNTIF($B$5:$C$5, M$2)>0, VLOOKUP($J20,'Gear Values'!$A$2:$E$13, IF(COUNTBLANK('Attributes & Prefixes'!$B$5:$C$5)>0, "2", "3"), 0), COUNTIF($D$5:$E$5, M$2)>0, VLOOKUP($J20,'Gear Values'!$A$2:$E$13, IF(COUNTBLANK('Attributes & Prefixes'!$B$5:$C$5)>0, "4", "5"), 0)), "")} -> 32 | N20: {=IF(COUNTIF($B$5:$E$5, N$2)>0, _xlfn.IFS(COUNTIF($B$5:$C$5, N$2)>0, VLOOKUP($J20,'Gear Values'!$A$2:$E$13, IF(COUNTBLANK('Attributes & Prefixes'!$B$5:$C$5)>0, "2", "3"), 0), COUNTIF($D$5:$E$5, N$2)>0, VLOOKUP($J20,'Gear Values'!$A$2:$E$13, IF(COUNTBLANK('Attributes & Prefixes'!$B$5:$C$5)>0, "4", "5"), 0)), "")} | O20: {=IF(COUNTIF($B$5:$E$5, O$2)>0, _xlfn.IFS(COUNTIF($B$5:$C$5, O$2)>0, VLOOKUP($J20,'Gear Values'!$A$2:$E$13, IF(COUNTBLANK('Attributes & Prefixes'!$B$5:$C$5)>0, "2", "3"), 0), COUNTIF($D$5:$E$5, O$2)>0, VLOOKUP($J20,'Gear Values'!$A$2:$E$13, IF(COUNTBLANK('Attributes & Prefixes'!$B$5:$C$5)>0, "4", "5"), 0)), "")} | P20: {=IF(COUNTIF($B$5:$E$5, P$2)>0, _xlfn.IFS(COUNTIF($B$5:$C$5, P$2)>0, VLOOKUP($J20,'Gear Values'!$A$2:$E$13, IF(COUNTBLANK('Attributes & Prefixes'!$B$5:$C$5)>0, "2", "3"), 0), COUNTIF($D$5:$E$5, P$2)>0, VLOOKUP($J20,'Gear Values'!$A$2:$E$13, IF(COUNTBLANK('Attributes & Prefixes'!$B$5:$C$5)>0, "4", "5"), 0)), "")} -> 32 | Q20: {=IF(COUNTIF($B$5:$E$5, Q$2)>0, _xlfn.IFS(COUNTIF($B$5:$C$5, Q$2)>0, VLOOKUP($J20,'Gear Values'!$A$2:$E$13, IF(COUNTBLANK('Attributes & Prefixes'!$B$5:$C$5)>0, "2", "3"), 0), COUNTIF($D$5:$E$5, Q$2)>0, VLOOKUP($J20,'Gear Values'!$A$2:$E$13, IF(COUNTBLANK('Attributes & Prefixes'!$B$5:$C$5)>0, "4", "5"), 0)), "")} | R20: {=IF(COUNTIF($B$5:$E$5, R$2)>0, _xlfn.IFS(COUNTIF($B$5:$C$5, R$2)>0, VLOOKUP($J20,'Gear Values'!$A$2:$E$13, IF(COUNTBLANK('Attributes & Prefixes'!$B$5:$C$5)>0, "2", "3"), 0), COUNTIF($D$5:$E$5, R$2)>0, VLOOKUP($J20,'Gear Values'!$A$2:$E$13, IF(COUNTBLANK('Attributes & Prefixes'!$B$5:$C$5)>0, "4", "5"), 0)), "")} | S20: {=IF(COUNTIF($B$5:$E$5, S$2)>0, _xlfn.IFS(COUNTIF($B$5:$C$5, S$2)>0, VLOOKUP($J20,'Gear Values'!$A$2:$E$13, IF(COUNTBLANK('Attributes & Prefixes'!$B$5:$C$5)>0, "2", "3"), 0), COUNTIF($D$5:$E$5, S$2)>0, VLOOKUP($J20,'Gear Values'!$A$2:$E$13, IF(COUNTBLANK('Attributes & Prefixes'!$B$5:$C$5)>0, "4", "5"), 0)), "")} -> 45
A21: Dragon | B21: Power | C21: Ferocity | D21: Precision | E21: Vitality | F21: =IF(OR(COUNTBLANK(AttributeFilter) = 1,AttributeFilter="(Select)"), A21, IF(COUNTIF(B21:E21, AttributeFilter)>0, A21, "")) -> Dragon | H21: =_xlfn.CONCAT(I$15,J21) -> ApothecaryLegs | J21: Legs | K21: {=IF(COUNTIF($B$5:$E$5, K$2)>0, _xlfn.IFS(COUNTIF($B$5:$C$5, K$2)>0, VLOOKUP($J21,'Gear Values'!$A$2:$E$13, IF(COUNTBLANK('Attributes & Prefixes'!$B$5:$C$5)>0, "2", "3"), 0), COUNTIF($D$5:$E$5, K$2)>0, VLOOKUP($J21,'Gear Values'!$A$2:$E$13, IF(COUNTBLANK('Attributes & Prefixes'!$B$5:$C$5)>0, "4", "5"), 0)), "")} | L21: {=IF(COUNTIF($B$5:$E$5, L$2)>0, _xlfn.IFS(COUNTIF($B$5:$C$5, L$2)>0, VLOOKUP($J21,'Gear Values'!$A$2:$E$13, IF(COUNTBLANK('Attributes & Prefixes'!$B$5:$C$5)>0, "2", "3"), 0), COUNTIF($D$5:$E$5, L$2)>0, VLOOKUP($J21,'Gear Values'!$A$2:$E$13, IF(COUNTBLANK('Attributes & Prefixes'!$B$5:$C$5)>0, "4", "5"), 0)), "")} | M21: {=IF(COUNTIF($B$5:$E$5, M$2)>0, _xlfn.IFS(COUNTIF($B$5:$C$5, M$2)>0, VLOOKUP($J21,'Gear Values'!$A$2:$E$13, IF(COUNTBLANK('Attributes & Prefixes'!$B$5:$C$5)>0, "2", "3"), 0), COUNTIF($D$5:$E$5, M$2)>0, VLOOKUP($J21,'Gear Values'!$A$2:$E$13, IF(COUNTBLANK('Attributes & Prefixes'!$B$5:$C$5)>0, "4", "5"), 0)), "")} -> 64 | N21: {=IF(COUNTIF($B$5:$E$5, N$2)>0, _xlfn.IFS(COUNTIF($B$5:$C$5, N$2)>0, VLOOKUP($J21,'Gear Values'!$A$2:$E$13, IF(COUNTBLANK('Attributes & Prefixes'!$B$5:$C$5)>0, "2", "3"), 0), COUNTIF($D$5:$E$5, N$2)>0, VLOOKUP($J21,'Gear Values'!$A$2:$E$13, IF(COUNTBLANK('Attributes & Prefixes'!$B$5:$C$5)>0, "4", "5"), 0)), "")} | O21: {=IF(COUNTIF($B$5:$E$5, O$2)>0, _xlfn.IFS(COUNTIF($B$5:$C$5, O$2)>0, VLOOKUP($J21,'Gear Values'!$A$2:$E$13, IF(COUNTBLANK('Attributes & Prefixes'!$B$5:$C$5)>0, "2", "3"), 0), COUNTIF($D$5:$E$5, O$2)>0, VLOOKUP($J21,'Gear Values'!$A$2:$E$13, IF(COUNTBLANK('Attributes & Prefixes'!$B$5:$C$5)>0, "4", "5"), 0)), "")} | P21: {=IF(COUNTIF($B$5:$E$5, P$2)>0, _xlfn.IFS(COUNTIF($B$5:$C$5, P$2)>0, VLOOKUP($J21,'Gear Values'!$A$2:$E$13, IF(COUNTBLANK('Attributes & Prefixes'!$B$5:$C$5)>0, "2", "3"), 0), COUNTIF($D$5:$E$5, P$2)>0, VLOOKUP($J21,'Gear Values'!$A$2:$E$13, IF(COUNTBLANK('Attributes & Prefixes'!$B$5:$C$5)>0, "4", "5"), 0)), "")} -> 64 | Q21: {=IF(COUNTIF($B$5:$E$5, Q$2)>0, _xlfn.IFS(COUNTIF($B$5:$C$5, Q$2)>0, VLOOKUP($J21,'Gear Values'!$A$2:$E$13, IF(COUNTBLANK('Attributes & Prefixes'!$B$5:$C$5)>0, "2", "3"), 0), COUNTIF($D$5:$E$5, Q$2)>0, VLOOKUP($J21,'Gear Values'!$A$2:$E$13, IF(COUNTBLANK('Attributes & Prefixes'!$B$5:$C$5)>0, "4", "5"), 0)), "")} | R21: {=IF(COUNTIF($B$5:$E$5, R$2)>0, _xlfn.IFS(COUNTIF($B$5:$C$5, R$2)>0, VLOOKUP($J21,'Gear Values'!$A$2:$E$13, IF(COUNTBLANK('Attributes & Prefixes'!$B$5:$C$5)>0, "2", "3"), 0), COUNTIF($D$5:$E$5, R$2)>0, VLOOKUP($J21,'Gear Values'!$A$2:$E$13, IF(COUNTBLANK('Attributes & Prefixes'!$B$5:$C$5)>0, "4", "5"), 0)), "")} | S21: {=IF(COUNTIF($B$5:$E$5, S$2)>0, _xlfn.IFS(COUNTIF($B$5:$C$5, S$2)>0, VLOOKUP($J21,'Gear Values'!$A$2:$E$13, IF(COUNTBLANK('Attributes & Prefixes'!$B$5:$C$5)>0, "2", "3"), 0), COUNTIF($D$5:$E$5, S$2)>0, VLOOKUP($J21,'Gear Values'!$A$2:$E$13, IF(COUNTBLANK('Attributes & Prefixes'!$B$5:$C$5)>0, "4", "5"), 0)), "")} -> 90
A22: Forsaken | B22: Power | D22: Toughness | E22: Healing Power | F22: =IF(OR(COUNTBLANK(AttributeFilter) = 1,AttributeFilter="(Select)"), A22, IF(COUNTIF(B22:E22, AttributeFilter)>0, A22, "")) -> Forsaken | H22: =_xlfn.CONCAT(I$15,J22) -> ApothecaryFeet | J22: Feet | K22: {=IF(COUNTIF($B$5:$E$5, K$2)>0, _xlfn.IFS(COUNTIF($B$5:$C$5, K$2)>0, VLOOKUP($J22,'Gear Values'!$A$2:$E$13, IF(COUNTBLANK('Attributes & Prefixes'!$B$5:$C$5)>0, "2", "3"), 0), COUNTIF($D$5:$E$5, K$2)>0, VLOOKUP($J22,'Gear Values'!$A$2:$E$13, IF(COUNTBLANK('Attributes & Prefixes'!$B$5:$C$5)>0, "4", "5"), 0)), "")} | L22: {=IF(COUNTIF($B$5:$E$5, L$2)>0, _xlfn.IFS(COUNTIF($B$5:$C$5, L$2)>0, VLOOKUP($J22,'Gear Values'!$A$2:$E$13, IF(COUNTBLANK('Attributes & Prefixes'!$B$5:$C$5)>0, "2", "3"), 0), COUNTIF($D$5:$E$5, L$2)>0, VLOOKUP($J22,'Gear Values'!$A$2:$E$13, IF(COUNTBLANK('Attributes & Prefixes'!$B$5:$C$5)>0, "4", "5"), 0)), "")} | M22: {=IF(COUNTIF($B$5:$E$5, M$2)>0, _xlfn.IFS(COUNTIF($B$5:$C$5, M$2)>0, VLOOKUP($J22,'Gear Values'!$A$2:$E$13, IF(COUNTBLANK('Attributes & Prefixes'!$B$5:$C$5)>0, "2", "3"), 0), COUNTIF($D$5:$E$5, M$2)>0, VLOOKUP($J22,'Gear Values'!$A$2:$E$13, IF(COUNTBLANK('Attributes & Prefixes'!$B$5:$C$5)>0, "4", "5"), 0)), "")} -> 32 | N22: {=IF(COUNTIF($B$5:$E$5, N$2)>0, _xlfn.IFS(COUNTIF($B$5:$C$5, N$2)>0, VLOOKUP($J22,'Gear Values'!$A$2:$E$13, IF(COUNTBLANK('Attributes & Prefixes'!$B$5:$C$5)>0, "2", "3"), 0), COUNTIF($D$5:$E$5, N$2)>0, VLOOKUP($J22,'Gear Values'!$A$2:$E$13, IF(COUNTBLANK('Attributes & Prefixes'!$B$5:$C$5)>0, "4", "5"), 0)), "")} | O22: {=IF(COUNTIF($B$5:$E$5, O$2)>0, _xlfn.IFS(COUNTIF($B$5:$C$5, O$2)>0, VLOOKUP($J22,'Gear Values'!$A$2:$E$13, IF(COUNTBLANK('Attributes & Prefixes'!$B$5:$C$5)>0, "2", "3"), 0), COUNTIF($D$5:$E$5, O$2)>0, VLOOKUP($J22,'Gear Values'!$A$2:$E$13, IF(COUNTBLANK('Attributes & Prefixes'!$B$5:$C$5)>0, "4", "5"), 0)), "")} | P22: {=IF(COUNTIF($B$5:$E$5, P$2)>0, _xlfn.IFS(COUNTIF($B$5:$C$5, P$2)>0, VLOOKUP($J22,'Gear Values'!$A$2:$E$13, IF(COUNTBLANK('Attributes & Prefixes'!$B$5:$C$5)>0, "2", "3"), 0), COUNTIF($D$5:$E$5, P$2)>0, VLOOKUP($J22,'Gear Values'!$A$2:$E$13, IF(COUNTBLANK('Attributes & Prefixes'!$B$5:$C$5)>0, "4", "5"), 0)), "")} -> 32 | Q22: {=IF(COUNTIF($B$5:$E$5, Q$2)>0, _xlfn.IFS(COUNTIF($B$5:$C$5, Q$2)>0, VLOOKUP($J22,'Gear Values'!$A$2:$E$13, IF(COUNTBLANK('Attributes & Prefixes'!$B$5:$C$5)>0, "2", "3"), 0), COUNTIF($D$5:$E$5, Q$2)>0, VLOOKUP($J22,'Gear Values'!$A$2:$E$13, IF(COUNTBLANK('Attributes & Prefixes'!$B$5:$C$5)>0, "4", "5"), 0)), "")} | R22: {=IF(COUNTIF($B$5:$E$5, R$2)>0, _xlfn.IFS(COUNTIF($B$5:$C$5, R$2)>0, VLOOKUP($J22,'Gear Values'!$A$2:$E$13, IF(COUNTBLANK('Attributes & Prefixes'!$B$5:$C$5)>0, "2", "3"), 0), COUNTIF($D$5:$E$5, R$2)>0, VLOOKUP($J22,'Gear Values'!$A$2:$E$13, IF(COUNTBLANK('Attributes & Prefixes'!$B$5:$C$5)>0, "4", "5"), 0)), "")} | S22: {=IF(COUNTIF($B$5:$E$5, S$2)>0, _xlfn.IFS(COUNTIF($B$5:$C$5, S$2)>0, VLOOKUP($J22,'Gear Values'!$A$2:$E$13, IF(COUNTBLANK('Attributes & Prefixes'!$B$5:$C$5)>0, "2", "3"), 0), COUNTIF($D$5:$E$5, S$2)>0, VLOOKUP($J22,'Gear Values'!$A$2:$E$13, IF(COUNTBLANK('Attributes & Prefixes'!$B$5:$C$5)>0, "4", "5"), 0)), "")} -> 45
A23: Giver | B23: Toughness | D23: Healing Power | E23: Concentration | F23: =IF(OR(COUNTBLANK(AttributeFilter) = 1,AttributeFilter="(Select)"), A23, IF(COUNTIF(B23:E23, AttributeFilter)>0, A23, "")) -> Giver | H23: =_xlfn.CONCAT(A$73,J23) -> PassifloraEar | J23: Ear | K23: {=IF(COUNTIF($B$5:$E$5, K$2)>0, _xlfn.IFS(COUNTIF($B$5:$C$5, K$2)>0, VLOOKUP($J23,'Gear Values'!$A$2:$E$13, IF(COUNTBLANK('Attributes & Prefixes'!$B$5:$C$5)>0, "2", "3"), 0), COUNTIF($D$5:$E$5, K$2)>0, VLOOKUP($J23,'Gear Values'!$A$2:$E$13, IF(COUNTBLANK('Attributes & Prefixes'!$B$5:$C$5)>0, "4", "5"), 0)), "")} | L23: {=IF(COUNTIF($B$5:$E$5, L$2)>0, _xlfn.IFS(COUNTIF($B$5:$C$5, L$2)>0, VLOOKUP($J23,'Gear Values'!$A$2:$E$13, IF(COUNTBLANK('Attributes & Prefixes'!$B$5:$C$5)>0, "2", "3"), 0), COUNTIF($D$5:$E$5, L$2)>0, VLOOKUP($J23,'Gear Values'!$A$2:$E$13, IF(COUNTBLANK('Attributes & Prefixes'!$B$5:$C$5)>0, "4", "5"), 0)), "")} | M23: {=IF(COUNTIF($B$5:$E$5, M$2)>0, _xlfn.IFS(COUNTIF($B$5:$C$5, M$2)>0, VLOOKUP($J23,'Gear Values'!$A$2:$E$13, IF(COUNTBLANK('Attributes & Prefixes'!$B$5:$C$5)>0, "2", "3"), 0), COUNTIF($D$5:$E$5, M$2)>0, VLOOKUP($J23,'Gear Values'!$A$2:$E$13, IF(COUNTBLANK('Attributes & Prefixes'!$B$5:$C$5)>0, "4", "5"), 0)), "")} -> 53 | N23: {=IF(COUNTIF($B$5:$E$5, N$2)>0, _xlfn.IFS(COUNTIF($B$5:$C$5, N$2)>0, VLOOKUP($J23,'Gear Values'!$A$2:$E$13, IF(COUNTBLANK('Attributes & Prefixes'!$B$5:$C$5)>0, "2", "3"), 0), COUNTIF($D$5:$E$5, N$2)>0, VLOOKUP($J23,'Gear Values'!$A$2:$E$13, IF(COUNTBLANK('Attributes & Prefixes'!$B$5:$C$5)>0, "4", "5"), 0)), "")} | O23: {=IF(COUNTIF($B$5:$E$5, O$2)>0, _xlfn.IFS(COUNTIF($B$5:$C$5, O$2)>0, VLOOKUP($J23,'Gear Values'!$A$2:$E$13, IF(COUNTBLANK('Attributes & Prefixes'!$B$5:$C$5)>0, "2", "3"), 0), COUNTIF($D$5:$E$5, O$2)>0, VLOOKUP($J23,'Gear Values'!$A$2:$E$13, IF(COUNTBLANK('Attributes & Prefixes'!$B$5:$C$5)>0, "4", "5"), 0)), "")} | P23: {=IF(COUNTIF($B$5:$E$5, P$2)>0, _xlfn.IFS(COUNTIF($B$5:$C$5, P$2)>0, VLOOKUP($J23,'Gear Values'!$A$2:$E$13, IF(COUNTBLANK('Attributes & Prefixes'!$B$5:$C$5)>0, "2", "3"), 0), COUNTIF($D$5:$E$5, P$2)>0, VLOOKUP($J23,'Gear Values'!$A$2:$E$13, IF(COUNTBLANK('Attributes & Prefixes'!$B$5:$C$5)>0, "4", "5"), 0)), "")} -> 53 | Q23: {=IF(COUNTIF($B$5:$E$5, Q$2)>0, _xlfn.IFS(COUNTIF($B$5:$C$5, Q$2)>0, VLOOKUP($J23,'Gear Values'!$A$2:$E$13, IF(COUNTBLANK('Attributes & Prefixes'!$B$5:$C$5)>0, "2", "3"), 0), COUNTIF($D$5:$E$5, Q$2)>0, VLOOKUP($J23,'Gear Values'!$A$2:$E$13, IF(COUNTBLANK('Attributes & Prefixes'!$B$5:$C$5)>0, "4", "5"), 0)), "")} | R23: {=IF(COUNTIF($B$5:$E$5, R$2)>0, _xlfn.IFS(COUNTIF($B$5:$C$5, R$2)>0, VLOOKUP($J23,'Gear Values'!$A$2:$E$13, IF(COUNTBLANK('Attributes & Prefixes'!$B$5:$C$5)>0, "2", "3"), 0), COUNTIF($D$5:$E$5, R$2)>0, VLOOKUP($J23,'Gear Values'!$A$2:$E$13, IF(COUNTBLANK('Attributes & Prefixes'!$B$5:$C$5)>0, "4", "5"), 0)), "")} | S23: {=IF(COUNTIF($B$5:$E$5, S$2)>0, _xlfn.IFS(COUNTIF($B$5:$C$5, S$2)>0, VLOOKUP($J23,'Gear Values'!$A$2:$E$13, IF(COUNTBLANK('Attributes & Prefixes'!$B$5:$C$5)>0, "2", "3"), 0), COUNTIF($D$5:$E$5, S$2)>0, VLOOKUP($J23,'Gear Values'!$A$2:$E$13, IF(COUNTBLANK('Attributes & Prefixes'!$B$5:$C$5)>0, "4", "5"), 0)), "")} -> 75
A24: Grieving | B24: Power | C24: Condition Damage | D24: Precision | E24: Ferocity | F24: =IF(OR(COUNTBLANK(AttributeFilter) = 1,AttributeFilter="(Select)"), A24, IF(COUNTIF(B24:E24, AttributeFilter)>0, A24, "")) -> Grieving | H24: =_xlfn.CONCAT(A$73,J24) -> PassifloraFinger | J24: Finger | K24: {=IF(COUNTIF($B$5:$E$5, K$2)>0, _xlfn.IFS(COUNTIF($B$5:$C$5, K$2)>0, VLOOKUP($J24,'Gear Values'!$A$2:$E$13, IF(COUNTBLANK('Attributes & Prefixes'!$B$5:$C$5)>0, "2", "3"), 0), COUNTIF($D$5:$E$5, K$2)>0, VLOOKUP($J24,'Gear Values'!$A$2:$E$13, IF(COUNTBLANK('Attributes & Prefixes'!$B$5:$C$5)>0, "4", "5"), 0)), "")} | L24: {=IF(COUNTIF($B$5:$E$5, L$2)>0, _xlfn.IFS(COUNTIF($B$5:$C$5, L$2)>0, VLOOKUP($J24,'Gear Values'!$A$2:$E$13, IF(COUNTBLANK('Attributes & Prefixes'!$B$5:$C$5)>0, "2", "3"), 0), COUNTIF($D$5:$E$5, L$2)>0, VLOOKUP($J24,'Gear Values'!$A$2:$E$13, IF(COUNTBLANK('Attributes & Prefixes'!$B$5:$C$5)>0, "4", "5"), 0)), "")} | M24: {=IF(COUNTIF($B$5:$E$5, M$2)>0, _xlfn.IFS(COUNTIF($B$5:$C$5, M$2)>0, VLOOKUP($J24,'Gear Values'!$A$2:$E$13, IF(COUNTBLANK('Attributes & Prefixes'!$B$5:$C$5)>0, "2", "3"), 0), COUNTIF($D$5:$E$5, M$2)>0, VLOOKUP($J24,'Gear Values'!$A$2:$E$13, IF(COUNTBLANK('Attributes & Prefixes'!$B$5:$C$5)>0, "4", "5"), 0)), "")} -> 64 | N24: {=IF(COUNTIF($B$5:$E$5, N$2)>0, _xlfn.IFS(COUNTIF($B$5:$C$5, N$2)>0, VLOOKUP($J24,'Gear Values'!$A$2:$E$13, IF(COUNTBLANK('Attributes & Prefixes'!$B$5:$C$5)>0, "2", "3"), 0), COUNTIF($D$5:$E$5, N$2)>0, VLOOKUP($J24,'Gear Values'!$A$2:$E$13, IF(COUNTBLANK('Attributes & Prefixes'!$B$5:$C$5)>0, "4", "5"), 0)), "")} | O24: {=IF(COUNTIF($B$5:$E$5, O$2)>0, _xlfn.IFS(COUNTIF($B$5:$C$5, O$2)>0, VLOOKUP($J24,'Gear Values'!$A$2:$E$13, IF(COUNTBLANK('Attributes & Prefixes'!$B$5:$C$5)>0, "2", "3"), 0), COUNTIF($D$5:$E$5, O$2)>0, VLOOKUP($J24,'Gear Values'!$A$2:$E$13, IF(COUNTBLANK('Attributes & Prefixes'!$B$5:$C$5)>0, "4", "5"), 0)), "")} | P24: {=IF(COUNTIF($B$5:$E$5, P$2)>0, _xlfn.IFS(COUNTIF($B$5:$C$5, P$2)>0, VLOOKUP($J24,'Gear Values'!$A$2:$E$13, IF(COUNTBLANK('Attributes & Prefixes'!$B$5:$C$5)>0, "2", "3"), 0), COUNTIF($D$5:$E$5, P$2)>0, VLOOKUP($J24,'Gear Values'!$A$2:$E$13, IF(COUNTBLANK('Attributes & Prefixes'!$B$5:$C$5)>0, "4", "5"), 0)), "")} -> 64 | Q24: {=IF(COUNTIF($B$5:$E$5, Q$2)>0, _xlfn.IFS(COUNTIF($B$5:$C$5, Q$2)>0, VLOOKUP($J24,'Gear Values'!$A$2:$E$13, IF(COUNTBLANK('Attributes & Prefixes'!$B$5:$C$5)>0, "2", "3"), 0), COUNTIF($D$5:$E$5, Q$2)>0, VLOOKUP($J24,'Gear Values'!$A$2:$E$13, IF(COUNTBLANK('Attributes & Prefixes'!$B$5:$C$5)>0, "4", "5"), 0)), "")} | R24: {=IF(COUNTIF($B$5:$E$5, R$2)>0, _xlfn.IFS(COUNTIF($B$5:$C$5, R$2)>0, VLOOKUP($J24,'Gear Values'!$A$2:$E$13, IF(COUNTBLANK('Attributes & Prefixes'!$B$5:$C$5)>0, "2", "3"), 0), COUNTIF($D$5:$E$5, R$2)>0, VLOOKUP($J24,'Gear Values'!$A$2:$E$13, IF(COUNTBLANK('Attributes & Prefixes'!$B$5:$C$5)>0, "4", "5"), 0)), "")} | S24: {=IF(COUNTIF($B$5:$E$5, S$2)>0, _xlfn.IFS(COUNTIF($B$5:$C$5, S$2)>0, VLOOKUP($J24,'Gear Values'!$A$2:$E$13, IF(COUNTBLANK('Attributes & Prefixes'!$B$5:$C$5)>0, "2", "3"), 0), COUNTIF($D$5:$E$5, S$2)>0, VLOOKUP($J24,'Gear Values'!$A$2:$E$13, IF(COUNTBLANK('Attributes & Prefixes'!$B$5:$C$5)>0, "4", "5"), 0)), "")} -> 90
A25: Harrier | B25: Power | D25: Healing Power | E25: Concentration | F25: =IF(OR(COUNTBLANK(AttributeFilter) = 1,AttributeFilter="(Select)"), A25, IF(COUNTIF(B25:E25, AttributeFilter)>0, A25, "")) -> Harrier | H25: =_xlfn.CONCAT(A$73,J25) -> PassifloraNeck | J25: Neck | K25: {=IF(COUNTIF($B$5:$E$5, K$2)>0, _xlfn.IFS(COUNTIF($B$5:$C$5, K$2)>0, VLOOKUP($J25,'Gear Values'!$A$2:$E$13, IF(COUNTBLANK('Attributes & Prefixes'!$B$5:$C$5)>0, "2", "3"), 0), COUNTIF($D$5:$E$5, K$2)>0, VLOOKUP($J25,'Gear Values'!$A$2:$E$13, IF(COUNTBLANK('Attributes & Prefixes'!$B$5:$C$5)>0, "4", "5"), 0)), "")} | L25: {=IF(COUNTIF($B$5:$E$5, L$2)>0, _xlfn.IFS(COUNTIF($B$5:$C$5, L$2)>0, VLOOKUP($J25,'Gear Values'!$A$2:$E$13, IF(COUNTBLANK('Attributes & Prefixes'!$B$5:$C$5)>0, "2", "3"), 0), COUNTIF($D$5:$E$5, L$2)>0, VLOOKUP($J25,'Gear Values'!$A$2:$E$13, IF(COUNTBLANK('Attributes & Prefixes'!$B$5:$C$5)>0, "4", "5"), 0)), "")} | M25: {=IF(COUNTIF($B$5:$E$5, M$2)>0, _xlfn.IFS(COUNTIF($B$5:$C$5, M$2)>0, VLOOKUP($J25,'Gear Values'!$A$2:$E$13, IF(COUNTBLANK('Attributes & Prefixes'!$B$5:$C$5)>0, "2", "3"), 0), COUNTIF($D$5:$E$5, M$2)>0, VLOOKUP($J25,'Gear Values'!$A$2:$E$13, IF(COUNTBLANK('Attributes & Prefixes'!$B$5:$C$5)>0, "4", "5"), 0)), "")} -> 85 | N25: {=IF(COUNTIF($B$5:$E$5, N$2)>0, _xlfn.IFS(COUNTIF($B$5:$C$5, N$2)>0, VLOOKUP($J25,'Gear Values'!$A$2:$E$13, IF(COUNTBLANK('Attributes & Prefixes'!$B$5:$C$5)>0, "2", "3"), 0), COUNTIF($D$5:$E$5, N$2)>0, VLOOKUP($J25,'Gear Values'!$A$2:$E$13, IF(COUNTBLANK('Attributes & Prefixes'!$B$5:$C$5)>0, "4", "5"), 0)), "")} | O25: {=IF(COUNTIF($B$5:$E$5, O$2)>0, _xlfn.IFS(COUNTIF($B$5:$C$5, O$2)>0, VLOOKUP($J25,'Gear Values'!$A$2:$E$13, IF(COUNTBLANK('Attributes & Prefixes'!$B$5:$C$5)>0, "2", "3"), 0), COUNTIF($D$5:$E$5, O$2)>0, VLOOKUP($J25,'Gear Values'!$A$2:$E$13, IF(COUNTBLANK('Attributes & Prefixes'!$B$5:$C$5)>0, "4", "5"), 0)), "")} | P25: {=IF(COUNTIF($B$5:$E$5, P$2)>0, _xlfn.IFS(COUNTIF($B$5:$C$5, P$2)>0, VLOOKUP($J25,'Gear Values'!$A$2:$E$13, IF(COUNTBLANK('Attributes & Prefixes'!$B$5:$C$5)>0, "2", "3"), 0), COUNTIF($D$5:$E$5, P$2)>0, VLOOKUP($J25,'Gear Values'!$A$2:$E$13, IF(COUNTBLANK('Attributes & Prefixes'!$B$5:$C$5)>0, "4", "5"), 0)), "")} -> 85 | Q25: {=IF(COUNTIF($B$5:$E$5, Q$2)>0, _xlfn.IFS(COUNTIF($B$5:$C$5, Q$2)>0, VLOOKUP($J25,'Gear Values'!$A$2:$E$13, IF(COUNTBLANK('Attributes & Prefixes'!$B$5:$C$5)>0, "2", "3"), 0), COUNTIF($D$5:$E$5, Q$2)>0, VLOOKUP($J25,'Gear Values'!$A$2:$E$13, IF(COUNTBLANK('Attributes & Prefixes'!$B$5:$C$5)>0, "4", "5"), 0)), "")} | R25: {=IF(COUNTIF($B$5:$E$5, R$2)>0, _xlfn.IFS(COUNTIF($B$5:$C$5, R$2)>0, VLOOKUP($J25,'Gear Values'!$A$2:$E$13, IF(COUNTBLANK('Attributes & Prefixes'!$B$5:$C$5)>0, "2", "3"), 0), COUNTIF($D$5:$E$5, R$2)>0, VLOOKUP($J25,'Gear Values'!$A$2:$E$13, IF(COUNTBLANK('Attributes & Prefixes'!$B$5:$C$5)>0, "4", "5"), 0)), "")} | S25: {=IF(COUNTIF($B$5:$E$5, S$2)>0, _xlfn.IFS(COUNTIF($B$5:$C$5, S$2)>0, VLOOKUP($J25,'Gear Values'!$A$2:$E$13, IF(COUNTBLANK('Attributes & Prefixes'!$B$5:$C$5)>0, "2", "3"), 0), COUNTIF($D$5:$E$5, S$2)>0, VLOOKUP($J25,'Gear Values'!$A$2:$E$13, IF(COUNTBLANK('Attributes & Prefixes'!$B$5:$C$5)>0, "4", "5"), 0)), "")} -> 120
A26: Heretic | B26: Power | C26: Precision | D26: Healing Power | E26: Ferocity | F26: =IF(OR(COUNTBLANK(AttributeFilter) = 1,AttributeFilter="(Select)"), A26, IF(COUNTIF(B26:E26, AttributeFilter)>0, A26, "")) -> Heretic | H26: =_xlfn.CONCAT(I$15,J26) -> ApothecaryBack | J26: Back | K26: {=IF(COUNTIF($B$5:$E$5, K$2)>0, _xlfn.IFS(COUNTIF($B$5:$C$5, K$2)>0, VLOOKUP($J26,'Gear Values'!$A$2:$E$13, IF(COUNTBLANK('Attributes & Prefixes'!$B$5:$C$5)>0, "2", "3"), 0), COUNTIF($D$5:$E$5, K$2)>0, VLOOKUP($J26,'Gear Values'!$A$2:$E$13, IF(COUNTBLANK('Attributes & Prefixes'!$B$5:$C$5)>0, "4", "5"), 0)), "")} | L26: {=IF(COUNTIF($B$5:$E$5, L$2)>0, _xlfn.IFS(COUNTIF($B$5:$C$5, L$2)>0, VLOOKUP($J26,'Gear Values'!$A$2:$E$13, IF(COUNTBLANK('Attributes & Prefixes'!$B$5:$C$5)>0, "2", "3"), 0), COUNTIF($D$5:$E$5, L$2)>0, VLOOKUP($J26,'Gear Values'!$A$2:$E$13, IF(COUNTBLANK('Attributes & Prefixes'!$B$5:$C$5)>0, "4", "5"), 0)), "")} | M26: {=IF(COUNTIF($B$5:$E$5, M$2)>0, _xlfn.IFS(COUNTIF($B$5:$C$5, M$2)>0, VLOOKUP($J26,'Gear Values'!$A$2:$E$13, IF(COUNTBLANK('Attributes & Prefixes'!$B$5:$C$5)>0, "2", "3"), 0), COUNTIF($D$5:$E$5, M$2)>0, VLOOKUP($J26,'Gear Values'!$A$2:$E$13, IF(COUNTBLANK('Attributes & Prefixes'!$B$5:$C$5)>0, "4", "5"), 0)), "")} -> 18 | N26: {=IF(COUNTIF($B$5:$E$5, N$2)>0, _xlfn.IFS(COUNTIF($B$5:$C$5, N$2)>0, VLOOKUP($J26,'Gear Values'!$A$2:$E$13, IF(COUNTBLANK('Attributes & Prefixes'!$B$5:$C$5)>0, "2", "3"), 0), COUNTIF($D$5:$E$5, N$2)>0, VLOOKUP($J26,'Gear Values'!$A$2:$E$13, IF(COUNTBLANK('Attributes & Prefixes'!$B$5:$C$5)>0, "4", "5"), 0)), "")} | O26: {=IF(COUNTIF($B$5:$E$5, O$2)>0, _xlfn.IFS(COUNTIF($B$5:$C$5, O$2)>0, VLOOKUP($J26,'Gear Values'!$A$2:$E$13, IF(COUNTBLANK('Attributes & Prefixes'!$B$5:$C$5)>0, "2", "3"), 0), COUNTIF($D$5:$E$5, O$2)>0, VLOOKUP($J26,'Gear Values'!$A$2:$E$13, IF(COUNTBLANK('Attributes & Prefixes'!$B$5:$C$5)>0, "4", "5"), 0)), "")} | P26: {=IF(COUNTIF($B$5:$E$5, P$2)>0, _xlfn.IFS(COUNTIF($B$5:$C$5, P$2)>0, VLOOKUP($J26,'Gear Values'!$A$2:$E$13, IF(COUNTBLANK('Attributes & Prefixes'!$B$5:$C$5)>0, "2", "3"), 0), COUNTIF($D$5:$E$5, P$2)>0, VLOOKUP($J26,'Gear Values'!$A$2:$E$13, IF(COUNTBLANK('Attributes & Prefixes'!$B$5:$C$5)>0, "4", "5"), 0)), "")} -> 18 | Q26: {=IF(COUNTIF($B$5:$E$5, Q$2)>0, _xlfn.IFS(COUNTIF($B$5:$C$5, Q$2)>0, VLOOKUP($J26,'Gear Values'!$A$2:$E$13, IF(COUNTBLANK('Attributes & Prefixes'!$B$5:$C$5)>0, "2", "3"), 0), COUNTIF($D$5:$E$5, Q$2)>0, VLOOKUP($J26,'Gear Values'!$A$2:$E$13, IF(COUNTBLANK('Attributes & Prefixes'!$B$5:$C$5)>0, "4", "5"), 0)), "")} | R26: {=IF(COUNTIF($B$5:$E$5, R$2)>0, _xlfn.IFS(COUNTIF($B$5:$C$5, R$2)>0, VLOOKUP($J26,'Gear Values'!$A$2:$E$13, IF(COUNTBLANK('Attributes & Prefixes'!$B$5:$C$5)>0, "2", "3"), 0), COUNTIF($D$5:$E$5, R$2)>0, VLOOKUP($J26,'Gear Values'!$A$2:$E$13, IF(COUNTBLANK('Attributes & Prefixes'!$B$5:$C$5)>0, "4", "5"), 0)), "")} | S26: {=IF(COUNTIF($B$5:$E$5, S$2)>0, _xlfn.IFS(COUNTIF($B$5:$C$5, S$2)>0, VLOOKUP($J26,'Gear Values'!$A$2:$E$13, IF(COUNTBLANK('Attributes & Prefixes'!$B$5:$C$5)>0, "2", "3"), 0), COUNTIF($D$5:$E$5, S$2)>0, VLOOKUP($J26,'Gear Values'!$A$2:$E$13, IF(COUNTBLANK('Attributes & Prefixes'!$B$5:$C$5)>0, "4", "5"), 0)), "")} -> 32
A27: Knight | B27: Toughness | D27: Power | E27: Precision | F27: =IF(OR(COUNTBLANK(AttributeFilter) = 1,AttributeFilter="(Select)"), A27, IF(COUNTIF(B27:E27, AttributeFilter)>0, A27, "")) -> Knight | H27: =_xlfn.CONCAT(I$27,J27) -> AssassinWeapon (1H) | I27: =A6 -> Assassin | J27: Weapon (1H) | K27: {=IF(COUNTIF($B$6:$E$6, K$2)>0, _xlfn.IFS(COUNTIF($B$6:$C$6, K$2)>0, VLOOKUP($J27,'Gear Values'!$A$2:$E$13, IF(COUNTBLANK('Attributes & Prefixes'!$B$6:$C$6)>0, "2", "3"), 0), COUNTIF($D$6:$E$6, K$2)>0, VLOOKUP($J27,'Gear Values'!$A$2:$E$13, IF(COUNTBLANK('Attributes & Prefixes'!$B$6:$C$6)>0, "4", "5"), 0)), "")} -> 85 | L27: {=IF(COUNTIF($B$6:$E$6, L$2)>0, _xlfn.IFS(COUNTIF($B$6:$C$6, L$2)>0, VLOOKUP($J27,'Gear Values'!$A$2:$E$13, IF(COUNTBLANK('Attributes & Prefixes'!$B$6:$C$6)>0, "2", "3"), 0), COUNTIF($D$6:$E$6, L$2)>0, VLOOKUP($J27,'Gear Values'!$A$2:$E$13, IF(COUNTBLANK('Attributes & Prefixes'!$B$6:$C$6)>0, "4", "5"), 0)), "")} -> 120 | M27: {=IF(COUNTIF($B$6:$E$6, M$2)>0, _xlfn.IFS(COUNTIF($B$6:$C$6, M$2)>0, VLOOKUP($J27,'Gear Values'!$A$2:$E$13, IF(COUNTBLANK('Attributes & Prefixes'!$B$6:$C$6)>0, "2", "3"), 0), COUNTIF($D$6:$E$6, M$2)>0, VLOOKUP($J27,'Gear Values'!$A$2:$E$13, IF(COUNTBLANK('Attributes & Prefixes'!$B$6:$C$6)>0, "4", "5"), 0)), "")} | N27: {=IF(COUNTIF($B$6:$E$6, N$2)>0, _xlfn.IFS(COUNTIF($B$6:$C$6, N$2)>0, VLOOKUP($J27,'Gear Values'!$A$2:$E$13, IF(COUNTBLANK('Attributes & Prefixes'!$B$6:$C$6)>0, "2", "3"), 0), COUNTIF($D$6:$E$6, N$2)>0, VLOOKUP($J27,'Gear Values'!$A$2:$E$13, IF(COUNTBLANK('Attributes & Prefixes'!$B$6:$C$6)>0, "4", "5"), 0)), "")} | O27: {=IF(COUNTIF($B$6:$E$6, O$2)>0, _xlfn.IFS(COUNTIF($B$6:$C$6, O$2)>0, VLOOKUP($J27,'Gear Values'!$A$2:$E$13, IF(COUNTBLANK('Attributes & Prefixes'!$B$6:$C$6)>0, "2", "3"), 0), COUNTIF($D$6:$E$6, O$2)>0, VLOOKUP($J27,'Gear Values'!$A$2:$E$13, IF(COUNTBLANK('Attributes & Prefixes'!$B$6:$C$6)>0, "4", "5"), 0)), "")} | P27: {=IF(COUNTIF($B$6:$E$6, P$2)>0, _xlfn.IFS(COUNTIF($B$6:$C$6, P$2)>0, VLOOKUP($J27,'Gear Values'!$A$2:$E$13, IF(COUNTBLANK('Attributes & Prefixes'!$B$6:$C$6)>0, "2", "3"), 0), COUNTIF($D$6:$E$6, P$2)>0, VLOOKUP($J27,'Gear Values'!$A$2:$E$13, IF(COUNTBLANK('Attributes & Prefixes'!$B$6:$C$6)>0, "4", "5"), 0)), "")} | Q27: {=IF(COUNTIF($B$6:$E$6, Q$2)>0, _xlfn.IFS(COUNTIF($B$6:$C$6, Q$2)>0, VLOOKUP($J27,'Gear Values'!$A$2:$E$13, IF(COUNTBLANK('Attributes & Prefixes'!$B$6:$C$6)>0, "2", "3"), 0), COUNTIF($D$6:$E$6, Q$2)>0, VLOOKUP($J27,'Gear Values'!$A$2:$E$13, IF(COUNTBLANK('Attributes & Prefixes'!$B$6:$C$6)>0, "4", "5"), 0)), "")} | R27: {=IF(COUNTIF($B$6:$E$6, R$2)>0, _xlfn.IFS(COUNTIF($B$6:$C$6, R$2)>0, VLOOKUP($J27,'Gear Values'!$A$2:$E$13, IF(COUNTBLANK('Attributes & Prefixes'!$B$6:$C$6)>0, "2", "3"), 0), COUNTIF($D$6:$E$6, R$2)>0, VLOOKUP($J27,'Gear Values'!$A$2:$E$13, IF(COUNTBLANK('Attributes & Prefixes'!$B$6:$C$6)>0, "4", "5"), 0)), "")} -> 85 | S27: {=IF(COUNTIF($B$6:$E$6, S$2)>0, _xlfn.IFS(COUNTIF($B$6:$C$6, S$2)>0, VLOOKUP($J27,'Gear Values'!$A$2:$E$13, IF(COUNTBLANK('Attributes & Prefixes'!$B$6:$C$6)>0, "2", "3"), 0), COUNTIF($D$6:$E$6, S$2)>0, VLOOKUP($J27,'Gear Values'!$A$2:$E$13, IF(COUNTBLANK('Attributes & Prefixes'!$B$6:$C$6)>0, "4", "5"), 0)), "")}
A28: Magi | B28: Healing Power | D28: Precision | E28: Vitality | F28: =IF(OR(COUNTBLANK(AttributeFilter) = 1,AttributeFilter="(Select)"), A28, IF(COUNTIF(B28:E28, AttributeFilter)>0, A28, "")) -> Magi | H28: =_xlfn.CONCAT(I$27,J28) -> AssassinWeapon (2H) | J28: Weapon (2H) | K28: {=IF(COUNTIF($B$6:$E$6, K$2)>0, _xlfn.IFS(COUNTIF($B$6:$C$6, K$2)>0, VLOOKUP($J28,'Gear Values'!$A$2:$E$13, IF(COUNTBLANK('Attributes & Prefixes'!$B$6:$C$6)>0, "2", "3"), 0), COUNTIF($D$6:$E$6, K$2)>0, VLOOKUP($J28,'Gear Values'!$A$2:$E$13, IF(COUNTBLANK('Attributes & Prefixes'!$B$6:$C$6)>0, "4", "5"), 0)), "")} -> 171 | L28: {=IF(COUNTIF($B$6:$E$6, L$2)>0, _xlfn.IFS(COUNTIF($B$6:$C$6, L$2)>0, VLOOKUP($J28,'Gear Values'!$A$2:$E$13, IF(COUNTBLANK('Attributes & Prefixes'!$B$6:$C$6)>0, "2", "3"), 0), COUNTIF($D$6:$E$6, L$2)>0, VLOOKUP($J28,'Gear Values'!$A$2:$E$13, IF(COUNTBLANK('Attributes & Prefixes'!$B$6:$C$6)>0, "4", "5"), 0)), "")} -> 239 | M28: {=IF(COUNTIF($B$6:$E$6, M$2)>0, _xlfn.IFS(COUNTIF($B$6:$C$6, M$2)>0, VLOOKUP($J28,'Gear Values'!$A$2:$E$13, IF(COUNTBLANK('Attributes & Prefixes'!$B$6:$C$6)>0, "2", "3"), 0), COUNTIF($D$6:$E$6, M$2)>0, VLOOKUP($J28,'Gear Values'!$A$2:$E$13, IF(COUNTBLANK('Attributes & Prefixes'!$B$6:$C$6)>0, "4", "5"), 0)), "")} | N28: {=IF(COUNTIF($B$6:$E$6, N$2)>0, _xlfn.IFS(COUNTIF($B$6:$C$6, N$2)>0, VLOOKUP($J28,'Gear Values'!$A$2:$E$13, IF(COUNTBLANK('Attributes & Prefixes'!$B$6:$C$6)>0, "2", "3"), 0), COUNTIF($D$6:$E$6, N$2)>0, VLOOKUP($J28,'Gear Values'!$A$2:$E$13, IF(COUNTBLANK('Attributes & Prefixes'!$B$6:$C$6)>0, "4", "5"), 0)), "")} | O28: {=IF(COUNTIF($B$6:$E$6, O$2)>0, _xlfn.IFS(COUNTIF($B$6:$C$6, O$2)>0, VLOOKUP($J28,'Gear Values'!$A$2:$E$13, IF(COUNTBLANK('Attributes & Prefixes'!$B$6:$C$6)>0, "2", "3"), 0), COUNTIF($D$6:$E$6, O$2)>0, VLOOKUP($J28,'Gear Values'!$A$2:$E$13, IF(COUNTBLANK('Attributes & Prefixes'!$B$6:$C$6)>0, "4", "5"), 0)), "")} | P28: {=IF(COUNTIF($B$6:$E$6, P$2)>0, _xlfn.IFS(COUNTIF($B$6:$C$6, P$2)>0, VLOOKUP($J28,'Gear Values'!$A$2:$E$13, IF(COUNTBLANK('Attributes & Prefixes'!$B$6:$C$6)>0, "2", "3"), 0), COUNTIF($D$6:$E$6, P$2)>0, VLOOKUP($J28,'Gear Values'!$A$2:$E$13, IF(COUNTBLANK('Attributes & Prefixes'!$B$6:$C$6)>0, "4", "5"), 0)), "")} | Q28: {=IF(COUNTIF($B$6:$E$6, Q$2)>0, _xlfn.IFS(COUNTIF($B$6:$C$6, Q$2)>0, VLOOKUP($J28,'Gear Values'!$A$2:$E$13, IF(COUNTBLANK('Attributes & Prefixes'!$B$6:$C$6)>0, "2", "3"), 0), COUNTIF($D$6:$E$6, Q$2)>0, VLOOKUP($J28,'Gear Values'!$A$2:$E$13, IF(COUNTBLANK('Attributes & Prefixes'!$B$6:$C$6)>0, "4", "5"), 0)), "")} | R28: {=IF(COUNTIF($B$6:$E$6, R$2)>0, _xlfn.IFS(COUNTIF($B$6:$C$6, R$2)>0, VLOOKUP($J28,'Gear Values'!$A$2:$E$13, IF(COUNTBLANK('Attributes & Prefixes'!$B$6:$C$6)>0, "2", "3"), 0), COUNTIF($D$6:$E$6, R$2)>0, VLOOKUP($J28,'Gear Values'!$A$2:$E$13, IF(COUNTBLANK('Attributes & Prefixes'!$B$6:$C$6)>0, "4", "5"), 0)), "")} -> 171 | S28: {=IF(COUNTIF($B$6:$E$6, S$2)>0, _xlfn.IFS(COUNTIF($B$6:$C$6, S$2)>0, VLOOKUP($J28,'Gear Values'!$A$2:$E$13, IF(COUNTBLANK('Attributes & Prefixes'!$B$6:$C$6)>0, "2", "3"), 0), COUNTIF($D$6:$E$6, S$2)>0, VLOOKUP($J28,'Gear Values'!$A$2:$E$13, IF(COUNTBLANK('Attributes & Prefixes'!$B$6:$C$6)>0, "4", "5"), 0)), "")}
A29: Marauder | B29: Power | C29: Precision | D29: Vitality | E29: Ferocity | F29: =IF(OR(COUNTBLANK(AttributeFilter) = 1,AttributeFilter="(Select)"), A29, IF(COUNTIF(B29:E29, AttributeFilter)>0, A29, "")) -> Marauder | H29: =_xlfn.CONCAT(I$27,J29) -> AssassinHead | J29: Head | K29: {=IF(COUNTIF($B$6:$E$6, K$2)>0, _xlfn.IFS(COUNTIF($B$6:$C$6, K$2)>0, VLOOKUP($J29,'Gear Values'!$A$2:$E$13, IF(COUNTBLANK('Attributes & Prefixes'!$B$6:$C$6)>0, "2", "3"), 0), COUNTIF($D$6:$E$6, K$2)>0, VLOOKUP($J29,'Gear Values'!$A$2:$E$13, IF(COUNTBLANK('Attributes & Prefixes'!$B$6:$C$6)>0, "4", "5"), 0)), "")} -> 43 | L29: {=IF(COUNTIF($B$6:$E$6, L$2)>0, _xlfn.IFS(COUNTIF($B$6:$C$6, L$2)>0, VLOOKUP($J29,'Gear Values'!$A$2:$E$13, IF(COUNTBLANK('Attributes & Prefixes'!$B$6:$C$6)>0, "2", "3"), 0), COUNTIF($D$6:$E$6, L$2)>0, VLOOKUP($J29,'Gear Values'!$A$2:$E$13, IF(COUNTBLANK('Attributes & Prefixes'!$B$6:$C$6)>0, "4", "5"), 0)), "")} -> 60 | M29: {=IF(COUNTIF($B$6:$E$6, M$2)>0, _xlfn.IFS(COUNTIF($B$6:$C$6, M$2)>0, VLOOKUP($J29,'Gear Values'!$A$2:$E$13, IF(COUNTBLANK('Attributes & Prefixes'!$B$6:$C$6)>0, "2", "3"), 0), COUNTIF($D$6:$E$6, M$2)>0, VLOOKUP($J29,'Gear Values'!$A$2:$E$13, IF(COUNTBLANK('Attributes & Prefixes'!$B$6:$C$6)>0, "4", "5"), 0)), "")} | N29: {=IF(COUNTIF($B$6:$E$6, N$2)>0, _xlfn.IFS(COUNTIF($B$6:$C$6, N$2)>0, VLOOKUP($J29,'Gear Values'!$A$2:$E$13, IF(COUNTBLANK('Attributes & Prefixes'!$B$6:$C$6)>0, "2", "3"), 0), COUNTIF($D$6:$E$6, N$2)>0, VLOOKUP($J29,'Gear Values'!$A$2:$E$13, IF(COUNTBLANK('Attributes & Prefixes'!$B$6:$C$6)>0, "4", "5"), 0)), "")} | O29: {=IF(COUNTIF($B$6:$E$6, O$2)>0, _xlfn.IFS(COUNTIF($B$6:$C$6, O$2)>0, VLOOKUP($J29,'Gear Values'!$A$2:$E$13, IF(COUNTBLANK('Attributes & Prefixes'!$B$6:$C$6)>0, "2", "3"), 0), COUNTIF($D$6:$E$6, O$2)>0, VLOOKUP($J29,'Gear Values'!$A$2:$E$13, IF(COUNTBLANK('Attributes & Prefixes'!$B$6:$C$6)>0, "4", "5"), 0)), "")} | P29: {=IF(COUNTIF($B$6:$E$6, P$2)>0, _xlfn.IFS(COUNTIF($B$6:$C$6, P$2)>0, VLOOKUP($J29,'Gear Values'!$A$2:$E$13, IF(COUNTBLANK('Attributes & Prefixes'!$B$6:$C$6)>0, "2", "3"), 0), COUNTIF($D$6:$E$6, P$2)>0, VLOOKUP($J29,'Gear Values'!$A$2:$E$13, IF(COUNTBLANK('Attributes & Prefixes'!$B$6:$C$6)>0, "4", "5"), 0)), "")} | Q29: {=IF(COUNTIF($B$6:$E$6, Q$2)>0, _xlfn.IFS(COUNTIF($B$6:$C$6, Q$2)>0, VLOOKUP($J29,'Gear Values'!$A$2:$E$13, IF(COUNTBLANK('Attributes & Prefixes'!$B$6:$C$6)>0, "2", "3"), 0), COUNTIF($D$6:$E$6, Q$2)>0, VLOOKUP($J29,'Gear Values'!$A$2:$E$13, IF(COUNTBLANK('Attributes & Prefixes'!$B$6:$C$6)>0, "4", "5"), 0)), "")} | R29: {=IF(COUNTIF($B$6:$E$6, R$2)>0, _xlfn.IFS(COUNTIF($B$6:$C$6, R$2)>0, VLOOKUP($J29,'Gear Values'!$A$2:$E$13, IF(COUNTBLANK('Attributes & Prefixes'!$B$6:$C$6)>0, "2", "3"), 0), COUNTIF($D$6:$E$6, R$2)>0, VLOOKUP($J29,'Gear Values'!$A$2:$E$13, IF(COUNTBLANK('Attributes & Prefixes'!$B$6:$C$6)>0, "4", "5"), 0)), "")} -> 43 | S29: {=IF(COUNTIF($B$6:$E$6, S$2)>0, _xlfn.IFS(COUNTIF($B$6:$C$6, S$2)>0, VLOOKUP($J29,'Gear Values'!$A$2:$E$13, IF(COUNTBLANK('Attributes & Prefixes'!$B$6:$C$6)>0, "2", "3"), 0), COUNTIF($D$6:$E$6, S$2)>0, VLOOKUP($J29,'Gear Values'!$A$2:$E$13, IF(COUNTBLANK('Attributes & Prefixes'!$B$6:$C$6)>0, "4", "5"), 0)), "")}
A30: Marshal | B30: Power | C30: Healing Power | D30: Precision | E30: Condition Damage | F30: =IF(OR(COUNTBLANK(AttributeFilter) = 1,AttributeFilter="(Select)"), A30, IF(COUNTIF(B30:E30, AttributeFilter)>0, A30, "")) -> Marshal | H30: =_xlfn.CONCAT(I$27,J30) -> AssassinShoulders | J30: Shoulders | K30: {=IF(COUNTIF($B$6:$E$6, K$2)>0, _xlfn.IFS(COUNTIF($B$6:$C$6, K$2)>0, VLOOKUP($J30,'Gear Values'!$A$2:$E$13, IF(COUNTBLANK('Attributes & Prefixes'!$B$6:$C$6)>0, "2", "3"), 0), COUNTIF($D$6:$E$6, K$2)>0, VLOOKUP($J30,'Gear Values'!$A$2:$E$13, IF(COUNTBLANK('Attributes & Prefixes'!$B$6:$C$6)>0, "4", "5"), 0)), "")} -> 32 | L30: {=IF(COUNTIF($B$6:$E$6, L$2)>0, _xlfn.IFS(COUNTIF($B$6:$C$6, L$2)>0, VLOOKUP($J30,'Gear Values'!$A$2:$E$13, IF(COUNTBLANK('Attributes & Prefixes'!$B$6:$C$6)>0, "2", "3"), 0), COUNTIF($D$6:$E$6, L$2)>0, VLOOKUP($J30,'Gear Values'!$A$2:$E$13, IF(COUNTBLANK('Attributes & Prefixes'!$B$6:$C$6)>0, "4", "5"), 0)), "")} -> 45 | M30: {=IF(COUNTIF($B$6:$E$6, M$2)>0, _xlfn.IFS(COUNTIF($B$6:$C$6, M$2)>0, VLOOKUP($J30,'Gear Values'!$A$2:$E$13, IF(COUNTBLANK('Attributes & Prefixes'!$B$6:$C$6)>0, "2", "3"), 0), COUNTIF($D$6:$E$6, M$2)>0, VLOOKUP($J30,'Gear Values'!$A$2:$E$13, IF(COUNTBLANK('Attributes & Prefixes'!$B$6:$C$6)>0, "4", "5"), 0)), "")} | N30: {=IF(COUNTIF($B$6:$E$6, N$2)>0, _xlfn.IFS(COUNTIF($B$6:$C$6, N$2)>0, VLOOKUP($J30,'Gear Values'!$A$2:$E$13, IF(COUNTBLANK('Attributes & Prefixes'!$B$6:$C$6)>0, "2", "3"), 0), COUNTIF($D$6:$E$6, N$2)>0, VLOOKUP($J30,'Gear Values'!$A$2:$E$13, IF(COUNTBLANK('Attributes & Prefixes'!$B$6:$C$6)>0, "4", "5"), 0)), "")} | O30: {=IF(COUNTIF($B$6:$E$6, O$2)>0, _xlfn.IFS(COUNTIF($B$6:$C$6, O$2)>0, VLOOKUP($J30,'Gear Values'!$A$2:$E$13, IF(COUNTBLANK('Attributes & Prefixes'!$B$6:$C$6)>0, "2", "3"), 0), COUNTIF($D$6:$E$6, O$2)>0, VLOOKUP($J30,'Gear Values'!$A$2:$E$13, IF(COUNTBLANK('Attributes & Prefixes'!$B$6:$C$6)>0, "4", "5"), 0)), "")} | P30: {=IF(COUNTIF($B$6:$E$6, P$2)>0, _xlfn.IFS(COUNTIF($B$6:$C$6, P$2)>0, VLOOKUP($J30,'Gear Values'!$A$2:$E$13, IF(COUNTBLANK('Attributes & Prefixes'!$B$6:$C$6)>0, "2", "3"), 0), COUNTIF($D$6:$E$6, P$2)>0, VLOOKUP($J30,'Gear Values'!$A$2:$E$13, IF(COUNTBLANK('Attributes & Prefixes'!$B$6:$C$6)>0, "4", "5"), 0)), "")} | Q30: {=IF(COUNTIF($B$6:$E$6, Q$2)>0, _xlfn.IFS(COUNTIF($B$6:$C$6, Q$2)>0, VLOOKUP($J30,'Gear Values'!$A$2:$E$13, IF(COUNTBLANK('Attributes & Prefixes'!$B$6:$C$6)>0, "2", "3"), 0), COUNTIF($D$6:$E$6, Q$2)>0, VLOOKUP($J30,'Gear Values'!$A$2:$E$13, IF(COUNTBLANK('Attributes & Prefixes'!$B$6:$C$6)>0, "4", "5"), 0)), "")} | R30: {=IF(COUNTIF($B$6:$E$6, R$2)>0, _xlfn.IFS(COUNTIF($B$6:$C$6, R$2)>0, VLOOKUP($J30,'Gear Values'!$A$2:$E$13, IF(COUNTBLANK('Attributes & Prefixes'!$B$6:$C$6)>0, "2", "3"), 0), COUNTIF($D$6:$E$6, R$2)>0, VLOOKUP($J30,'Gear Values'!$A$2:$E$13, IF(COUNTBLANK('Attributes & Prefixes'!$B$6:$C$6)>0, "4", "5"), 0)), "")} -> 32 | S30: {=IF(COUNTIF($B$6:$E$6, S$2)>0, _xlfn.IFS(COUNTIF($B$6:$C$6, S$2)>0, VLOOKUP($J30,'Gear Values'!$A$2:$E$13, IF(COUNTBLANK('Attributes & Prefixes'!$B$6:$C$6)>0, "2", "3"), 0), COUNTIF($D$6:$E$6, S$2)>0, VLOOKUP($J30,'Gear Values'!$A$2:$E$13, IF(COUNTBLANK('Attributes & Prefixes'!$B$6:$C$6)>0, "4", "5"), 0)), "")}
A31: Minstrel | B31: Toughness | C31: Healing Power | D31: Vitality | E31: Concentration | F31: =IF(OR(COUNTBLANK(AttributeFilter) = 1,AttributeFilter="(Select)"), A31, IF(COUNTIF(B31:E31, AttributeFilter)>0, A31, "")) -> Minstrel | H31: =_xlfn.CONCAT(I$27,J31) -> AssassinChest | J31: Chest | K31: {=IF(COUNTIF($B$6:$E$6, K$2)>0, _xlfn.IFS(COUNTIF($B$6:$C$6, K$2)>0, VLOOKUP($J31,'Gear Values'!$A$2:$E$13, IF(COUNTBLANK('Attributes & Prefixes'!$B$6:$C$6)>0, "2", "3"), 0), COUNTIF($D$6:$E$6, K$2)>0, VLOOKUP($J31,'Gear Values'!$A$2:$E$13, IF(COUNTBLANK('Attributes & Prefixes'!$B$6:$C$6)>0, "4", "5"), 0)), "")} -> 96 | L31: {=IF(COUNTIF($B$6:$E$6, L$2)>0, _xlfn.IFS(COUNTIF($B$6:$C$6, L$2)>0, VLOOKUP($J31,'Gear Values'!$A$2:$E$13, IF(COUNTBLANK('Attributes & Prefixes'!$B$6:$C$6)>0, "2", "3"), 0), COUNTIF($D$6:$E$6, L$2)>0, VLOOKUP($J31,'Gear Values'!$A$2:$E$13, IF(COUNTBLANK('Attributes & Prefixes'!$B$6:$C$6)>0, "4", "5"), 0)), "")} -> 134 | M31: {=IF(COUNTIF($B$6:$E$6, M$2)>0, _xlfn.IFS(COUNTIF($B$6:$C$6, M$2)>0, VLOOKUP($J31,'Gear Values'!$A$2:$E$13, IF(COUNTBLANK('Attributes & Prefixes'!$B$6:$C$6)>0, "2", "3"), 0), COUNTIF($D$6:$E$6, M$2)>0, VLOOKUP($J31,'Gear Values'!$A$2:$E$13, IF(COUNTBLANK('Attributes & Prefixes'!$B$6:$C$6)>0, "4", "5"), 0)), "")} | N31: {=IF(COUNTIF($B$6:$E$6, N$2)>0, _xlfn.IFS(COUNTIF($B$6:$C$6, N$2)>0, VLOOKUP($J31,'Gear Values'!$A$2:$E$13, IF(COUNTBLANK('Attributes & Prefixes'!$B$6:$C$6)>0, "2", "3"), 0), COUNTIF($D$6:$E$6, N$2)>0, VLOOKUP($J31,'Gear Values'!$A$2:$E$13, IF(COUNTBLANK('Attributes & Prefixes'!$B$6:$C$6)>0, "4", "5"), 0)), "")} | O31: {=IF(COUNTIF($B$6:$E$6, O$2)>0, _xlfn.IFS(COUNTIF($B$6:$C$6, O$2)>0, VLOOKUP($J31,'Gear Values'!$A$2:$E$13, IF(COUNTBLANK('Attributes & Prefixes'!$B$6:$C$6)>0, "2", "3"), 0), COUNTIF($D$6:$E$6, O$2)>0, VLOOKUP($J31,'Gear Values'!$A$2:$E$13, IF(COUNTBLANK('Attributes & Prefixes'!$B$6:$C$6)>0, "4", "5"), 0)), "")} | P31: {=IF(COUNTIF($B$6:$E$6, P$2)>0, _xlfn.IFS(COUNTIF($B$6:$C$6, P$2)>0, VLOOKUP($J31,'Gear Values'!$A$2:$E$13, IF(COUNTBLANK('Attributes & Prefixes'!$B$6:$C$6)>0, "2", "3"), 0), COUNTIF($D$6:$E$6, P$2)>0, VLOOKUP($J31,'Gear Values'!$A$2:$E$13, IF(COUNTBLANK('Attributes & Prefixes'!$B$6:$C$6)>0, "4", "5"), 0)), "")} | Q31: {=IF(COUNTIF($B$6:$E$6, Q$2)>0, _xlfn.IFS(COUNTIF($B$6:$C$6, Q$2)>0, VLOOKUP($J31,'Gear Values'!$A$2:$E$13, IF(COUNTBLANK('Attributes & Prefixes'!$B$6:$C$6)>0, "2", "3"), 0), COUNTIF($D$6:$E$6, Q$2)>0, VLOOKUP($J31,'Gear Values'!$A$2:$E$13, IF(COUNTBLANK('Attributes & Prefixes'!$B$6:$C$6)>0, "4", "5"), 0)), "")} | R31: {=IF(COUNTIF($B$6:$E$6, R$2)>0, _xlfn.IFS(COUNTIF($B$6:$C$6, R$2)>0, VLOOKUP($J31,'Gear Values'!$A$2:$E$13, IF(COUNTBLANK('Attributes & Prefixes'!$B$6:$C$6)>0, "2", "3"), 0), COUNTIF($D$6:$E$6, R$2)>0, VLOOKUP($J31,'Gear Values'!$A$2:$E$13, IF(COUNTBLANK('Attributes & Prefixes'!$B$6:$C$6)>0, "4", "5"), 0)), "")} -> 96 | S31: {=IF(COUNTIF($B$6:$E$6, S$2)>0, _xlfn.IFS(COUNTIF($B$6:$C$6, S$2)>0, VLOOKUP($J31,'Gear Values'!$A$2:$E$13, IF(COUNTBLANK('Attributes & Prefixes'!$B$6:$C$6)>0, "2", "3"), 0), COUNTIF($D$6:$E$6, S$2)>0, VLOOKUP($J31,'Gear Values'!$A$2:$E$13, IF(COUNTBLANK('Attributes & Prefixes'!$B$6:$C$6)>0, "4", "5"), 0)), "")}
A32: Nomad | B32: Toughness | D32: Healing Power | E32: Vitality | F32: =IF(OR(COUNTBLANK(AttributeFilter) = 1,AttributeFilter="(Select)"), A32, IF(COUNTIF(B32:E32, AttributeFilter)>0, A32, "")) -> Nomad | H32: =_xlfn.CONCAT(I$27,J32) -> AssassinHands | J32: Hands | K32: {=IF(COUNTIF($B$6:$E$6, K$2)>0, _xlfn.IFS(COUNTIF($B$6:$C$6, K$2)>0, VLOOKUP($J32,'Gear Values'!$A$2:$E$13, IF(COUNTBLANK('Attributes & Prefixes'!$B$6:$C$6)>0, "2", "3"), 0), COUNTIF($D$6:$E$6, K$2)>0, VLOOKUP($J32,'Gear Values'!$A$2:$E$13, IF(COUNTBLANK('Attributes & Prefixes'!$B$6:$C$6)>0, "4", "5"), 0)), "")} -> 32 | L32: {=IF(COUNTIF($B$6:$E$6, L$2)>0, _xlfn.IFS(COUNTIF($B$6:$C$6, L$2)>0, VLOOKUP($J32,'Gear Values'!$A$2:$E$13, IF(COUNTBLANK('Attributes & Prefixes'!$B$6:$C$6)>0, "2", "3"), 0), COUNTIF($D$6:$E$6, L$2)>0, VLOOKUP($J32,'Gear Values'!$A$2:$E$13, IF(COUNTBLANK('Attributes & Prefixes'!$B$6:$C$6)>0, "4", "5"), 0)), "")} -> 45 | M32: {=IF(COUNTIF($B$6:$E$6, M$2)>0, _xlfn.IFS(COUNTIF($B$6:$C$6, M$2)>0, VLOOKUP($J32,'Gear Values'!$A$2:$E$13, IF(COUNTBLANK('Attributes & Prefixes'!$B$6:$C$6)>0, "2", "3"), 0), COUNTIF($D$6:$E$6, M$2)>0, VLOOKUP($J32,'Gear Values'!$A$2:$E$13, IF(COUNTBLANK('Attributes & Prefixes'!$B$6:$C$6)>0, "4", "5"), 0)), "")} | N32: {=IF(COUNTIF($B$6:$E$6, N$2)>0, _xlfn.IFS(COUNTIF($B$6:$C$6, N$2)>0, VLOOKUP($J32,'Gear Values'!$A$2:$E$13, IF(COUNTBLANK('Attributes & Prefixes'!$B$6:$C$6)>0, "2", "3"), 0), COUNTIF($D$6:$E$6, N$2)>0, VLOOKUP($J32,'Gear Values'!$A$2:$E$13, IF(COUNTBLANK('Attributes & Prefixes'!$B$6:$C$6)>0, "4", "5"), 0)), "")} | O32: {=IF(COUNTIF($B$6:$E$6, O$2)>0, _xlfn.IFS(COUNTIF($B$6:$C$6, O$2)>0, VLOOKUP($J32,'Gear Values'!$A$2:$E$13, IF(COUNTBLANK('Attributes & Prefixes'!$B$6:$C$6)>0, "2", "3"), 0), COUNTIF($D$6:$E$6, O$2)>0, VLOOKUP($J32,'Gear Values'!$A$2:$E$13, IF(COUNTBLANK('Attributes & Prefixes'!$B$6:$C$6)>0, "4", "5"), 0)), "")} | P32: {=IF(COUNTIF($B$6:$E$6, P$2)>0, _xlfn.IFS(COUNTIF($B$6:$C$6, P$2)>0, VLOOKUP($J32,'Gear Values'!$A$2:$E$13, IF(COUNTBLANK('Attributes & Prefixes'!$B$6:$C$6)>0, "2", "3"), 0), COUNTIF($D$6:$E$6, P$2)>0, VLOOKUP($J32,'Gear Values'!$A$2:$E$13, IF(COUNTBLANK('Attributes & Prefixes'!$B$6:$C$6)>0, "4", "5"), 0)), "")} | Q32: {=IF(COUNTIF($B$6:$E$6, Q$2)>0, _xlfn.IFS(COUNTIF($B$6:$C$6, Q$2)>0, VLOOKUP($J32,'Gear Values'!$A$2:$E$13, IF(COUNTBLANK('Attributes & Prefixes'!$B$6:$C$6)>0, "2", "3"), 0), COUNTIF($D$6:$E$6, Q$2)>0, VLOOKUP($J32,'Gear Values'!$A$2:$E$13, IF(COUNTBLANK('Attributes & Prefixes'!$B$6:$C$6)>0, "4", "5"), 0)), "")} | R32: {=IF(COUNTIF($B$6:$E$6, R$2)>0, _xlfn.IFS(COUNTIF($B$6:$C$6, R$2)>0, VLOOKUP($J32,'Gear Values'!$A$2:$E$13, IF(COUNTBLANK('Attributes & Prefixes'!$B$6:$C$6)>0, "2", "3"), 0), COUNTIF($D$6:$E$6, R$2)>0, VLOOKUP($J32,'Gear Values'!$A$2:$E$13, IF(COUNTBLANK('Attributes & Prefixes'!$B$6:$C$6)>0, "4", "5"), 0)), "")} -> 32 | S32: {=IF(COUNTIF($B$6:$E$6, S$2)>0, _xlfn.IFS(COUNTIF($B$6:$C$6, S$2)>0, VLOOKUP($J32,'Gear Values'!$A$2:$E$13, IF(COUNTBLANK('Attributes & Prefixes'!$B$6:$C$6)>0, "2", "3"), 0), COUNTIF($D$6:$E$6, S$2)>0, VLOOKUP($J32,'Gear Values'!$A$2:$E$13, IF(COUNTBLANK('Attributes & Prefixes'!$B$6:$C$6)>0, "4", "5"), 0)), "")}
A33: Paladin | B33: Power | C33: Precision | D33: Toughness | E33: Vitality | F33: =IF(OR(COUNTBLANK(AttributeFilter) = 1,AttributeFilter="(Select)"), A33, IF(COUNTIF(B33:E33, AttributeFilter)>0, A33, "")) -> Paladin | H33: =_xlfn.CONCAT(I$27,J33) -> AssassinLegs | J33: Legs | K33: {=IF(COUNTIF($B$6:$E$6, K$2)>0, _xlfn.IFS(COUNTIF($B$6:$C$6, K$2)>0, VLOOKUP($J33,'Gear Values'!$A$2:$E$13, IF(COUNTBLANK('Attributes & Prefixes'!$B$6:$C$6)>0, "2", "3"), 0), COUNTIF($D$6:$E$6, K$2)>0, VLOOKUP($J33,'Gear Values'!$A$2:$E$13, IF(COUNTBLANK('Attributes & Prefixes'!$B$6:$C$6)>0, "4", "5"), 0)), "")} -> 64 | L33: {=IF(COUNTIF($B$6:$E$6, L$2)>0, _xlfn.IFS(COUNTIF($B$6:$C$6, L$2)>0, VLOOKUP($J33,'Gear Values'!$A$2:$E$13, IF(COUNTBLANK('Attributes & Prefixes'!$B$6:$C$6)>0, "2", "3"), 0), COUNTIF($D$6:$E$6, L$2)>0, VLOOKUP($J33,'Gear Values'!$A$2:$E$13, IF(COUNTBLANK('Attributes & Prefixes'!$B$6:$C$6)>0, "4", "5"), 0)), "")} -> 90 | M33: {=IF(COUNTIF($B$6:$E$6, M$2)>0, _xlfn.IFS(COUNTIF($B$6:$C$6, M$2)>0, VLOOKUP($J33,'Gear Values'!$A$2:$E$13, IF(COUNTBLANK('Attributes & Prefixes'!$B$6:$C$6)>0, "2", "3"), 0), COUNTIF($D$6:$E$6, M$2)>0, VLOOKUP($J33,'Gear Values'!$A$2:$E$13, IF(COUNTBLANK('Attributes & Prefixes'!$B$6:$C$6)>0, "4", "5"), 0)), "")} | N33: {=IF(COUNTIF($B$6:$E$6, N$2)>0, _xlfn.IFS(COUNTIF($B$6:$C$6, N$2)>0, VLOOKUP($J33,'Gear Values'!$A$2:$E$13, IF(COUNTBLANK('Attributes & Prefixes'!$B$6:$C$6)>0, "2", "3"), 0), COUNTIF($D$6:$E$6, N$2)>0, VLOOKUP($J33,'Gear Values'!$A$2:$E$13, IF(COUNTBLANK('Attributes & Prefixes'!$B$6:$C$6)>0, "4", "5"), 0)), "")} | O33: {=IF(COUNTIF($B$6:$E$6, O$2)>0, _xlfn.IFS(COUNTIF($B$6:$C$6, O$2)>0, VLOOKUP($J33,'Gear Values'!$A$2:$E$13, IF(COUNTBLANK('Attributes & Prefixes'!$B$6:$C$6)>0, "2", "3"), 0), COUNTIF($D$6:$E$6, O$2)>0, VLOOKUP($J33,'Gear Values'!$A$2:$E$13, IF(COUNTBLANK('Attributes & Prefixes'!$B$6:$C$6)>0, "4", "5"), 0)), "")} | P33: {=IF(COUNTIF($B$6:$E$6, P$2)>0, _xlfn.IFS(COUNTIF($B$6:$C$6, P$2)>0, VLOOKUP($J33,'Gear Values'!$A$2:$E$13, IF(COUNTBLANK('Attributes & Prefixes'!$B$6:$C$6)>0, "2", "3"), 0), COUNTIF($D$6:$E$6, P$2)>0, VLOOKUP($J33,'Gear Values'!$A$2:$E$13, IF(COUNTBLANK('Attributes & Prefixes'!$B$6:$C$6)>0, "4", "5"), 0)), "")} | Q33: {=IF(COUNTIF($B$6:$E$6, Q$2)>0, _xlfn.IFS(COUNTIF($B$6:$C$6, Q$2)>0, VLOOKUP($J33,'Gear Values'!$A$2:$E$13, IF(COUNTBLANK('Attributes & Prefixes'!$B$6:$C$6)>0, "2", "3"), 0), COUNTIF($D$6:$E$6, Q$2)>0, VLOOKUP($J33,'Gear Values'!$A$2:$E$13, IF(COUNTBLANK('Attributes & Prefixes'!$B$6:$C$6)>0, "4", "5"), 0)), "")} | R33: {=IF(COUNTIF($B$6:$E$6, R$2)>0, _xlfn.IFS(COUNTIF($B$6:$C$6, R$2)>0, VLOOKUP($J33,'Gear Values'!$A$2:$E$13, IF(COUNTBLANK('Attributes & Prefixes'!$B$6:$C$6)>0, "2", "3"), 0), COUNTIF($D$6:$E$6, R$2)>0, VLOOKUP($J33,'Gear Values'!$A$2:$E$13, IF(COUNTBLANK('Attributes & Prefixes'!$B$6:$C$6)>0, "4", "5"), 0)), "")} -> 64 | S33: {=IF(COUNTIF($B$6:$E$6, S$2)>0, _xlfn.IFS(COUNTIF($B$6:$C$6, S$2)>0, VLOOKUP($J33,'Gear Values'!$A$2:$E$13, IF(COUNTBLANK('Attributes & Prefixes'!$B$6:$C$6)>0, "2", "3"), 0), COUNTIF($D$6:$E$6, S$2)>0, VLOOKUP($J33,'Gear Values'!$A$2:$E$13, IF(COUNTBLANK('Attributes & Prefixes'!$B$6:$C$6)>0, "4", "5"), 0)), "")}
A34: Plaguedoctor | B34: Vitality | C34: Condition Damage | D34: Healing Power | E34: Concentration | F34: =IF(OR(COUNTBLANK(AttributeFilter) = 1,AttributeFilter="(Select)"), A34, IF(COUNTIF(B34:E34, AttributeFilter)>0, A34, "")) -> Plaguedoctor | H34: =_xlfn.CONCAT(I$27,J34) -> AssassinFeet | J34: Feet | K34: {=IF(COUNTIF($B$6:$E$6, K$2)>0, _xlfn.IFS(COUNTIF($B$6:$C$6, K$2)>0, VLOOKUP($J34,'Gear Values'!$A$2:$E$13, IF(COUNTBLANK('Attributes & Prefixes'!$B$6:$C$6)>0, "2", "3"), 0), COUNTIF($D$6:$E$6, K$2)>0, VLOOKUP($J34,'Gear Values'!$A$2:$E$13, IF(COUNTBLANK('Attributes & Prefixes'!$B$6:$C$6)>0, "4", "5"), 0)), "")} -> 32 | L34: {=IF(COUNTIF($B$6:$E$6, L$2)>0, _xlfn.IFS(COUNTIF($B$6:$C$6, L$2)>0, VLOOKUP($J34,'Gear Values'!$A$2:$E$13, IF(COUNTBLANK('Attributes & Prefixes'!$B$6:$C$6)>0, "2", "3"), 0), COUNTIF($D$6:$E$6, L$2)>0, VLOOKUP($J34,'Gear Values'!$A$2:$E$13, IF(COUNTBLANK('Attributes & Prefixes'!$B$6:$C$6)>0, "4", "5"), 0)), "")} -> 45 | M34: {=IF(COUNTIF($B$6:$E$6, M$2)>0, _xlfn.IFS(COUNTIF($B$6:$C$6, M$2)>0, VLOOKUP($J34,'Gear Values'!$A$2:$E$13, IF(COUNTBLANK('Attributes & Prefixes'!$B$6:$C$6)>0, "2", "3"), 0), COUNTIF($D$6:$E$6, M$2)>0, VLOOKUP($J34,'Gear Values'!$A$2:$E$13, IF(COUNTBLANK('Attributes & Prefixes'!$B$6:$C$6)>0, "4", "5"), 0)), "")} | N34: {=IF(COUNTIF($B$6:$E$6, N$2)>0, _xlfn.IFS(COUNTIF($B$6:$C$6, N$2)>0, VLOOKUP($J34,'Gear Values'!$A$2:$E$13, IF(COUNTBLANK('Attributes & Prefixes'!$B$6:$C$6)>0, "2", "3"), 0), COUNTIF($D$6:$E$6, N$2)>0, VLOOKUP($J34,'Gear Values'!$A$2:$E$13, IF(COUNTBLANK('Attributes & Prefixes'!$B$6:$C$6)>0, "4", "5"), 0)), "")} | O34: {=IF(COUNTIF($B$6:$E$6, O$2)>0, _xlfn.IFS(COUNTIF($B$6:$C$6, O$2)>0, VLOOKUP($J34,'Gear Values'!$A$2:$E$13, IF(COUNTBLANK('Attributes & Prefixes'!$B$6:$C$6)>0, "2", "3"), 0), COUNTIF($D$6:$E$6, O$2)>0, VLOOKUP($J34,'Gear Values'!$A$2:$E$13, IF(COUNTBLANK('Attributes & Prefixes'!$B$6:$C$6)>0, "4", "5"), 0)), "")} | P34: {=IF(COUNTIF($B$6:$E$6, P$2)>0, _xlfn.IFS(COUNTIF($B$6:$C$6, P$2)>0, VLOOKUP($J34,'Gear Values'!$A$2:$E$13, IF(COUNTBLANK('Attributes & Prefixes'!$B$6:$C$6)>0, "2", "3"), 0), COUNTIF($D$6:$E$6, P$2)>0, VLOOKUP($J34,'Gear Values'!$A$2:$E$13, IF(COUNTBLANK('Attributes & Prefixes'!$B$6:$C$6)>0, "4", "5"), 0)), "")} | Q34: {=IF(COUNTIF($B$6:$E$6, Q$2)>0, _xlfn.IFS(COUNTIF($B$6:$C$6, Q$2)>0, VLOOKUP($J34,'Gear Values'!$A$2:$E$13, IF(COUNTBLANK('Attributes & Prefixes'!$B$6:$C$6)>0, "2", "3"), 0), COUNTIF($D$6:$E$6, Q$2)>0, VLOOKUP($J34,'Gear Values'!$A$2:$E$13, IF(COUNTBLANK('Attributes & Prefixes'!$B$6:$C$6)>0, "4", "5"), 0)), "")} | R34: {=IF(COUNTIF($B$6:$E$6, R$2)>0, _xlfn.IFS(COUNTIF($B$6:$C$6, R$2)>0, VLOOKUP($J34,'Gear Values'!$A$2:$E$13, IF(COUNTBLANK('Attributes & Prefixes'!$B$6:$C$6)>0, "2", "3"), 0), COUNTIF($D$6:$E$6, R$2)>0, VLOOKUP($J34,'Gear Values'!$A$2:$E$13, IF(COUNTBLANK('Attributes & Prefixes'!$B$6:$C$6)>0, "4", "5"), 0)), "")} -> 32 | S34: {=IF(COUNTIF($B$6:$E$6, S$2)>0, _xlfn.IFS(COUNTIF($B$6:$C$6, S$2)>0, VLOOKUP($J34,'Gear Values'!$A$2:$E$13, IF(COUNTBLANK('Attributes & Prefixes'!$B$6:$C$6)>0, "2", "3"), 0), COUNTIF($D$6:$E$6, S$2)>0, VLOOKUP($J34,'Gear Values'!$A$2:$E$13, IF(COUNTBLANK('Attributes & Prefixes'!$B$6:$C$6)>0, "4", "5"), 0)), "")}
A35: Rabid | B35: Condition Damage | D35: Precision | E35: Toughness | F35: =IF(OR(COUNTBLANK(AttributeFilter) = 1,AttributeFilter="(Select)"), A35, IF(COUNTIF(B35:E35, AttributeFilter)>0, A35, "")) -> Rabid | H35: =_xlfn.CONCAT(A$72,J35) -> OpalEar | J35: Ear | K35: {=IF(COUNTIF($B$6:$E$6, K$2)>0, _xlfn.IFS(COUNTIF($B$6:$C$6, K$2)>0, VLOOKUP($J35,'Gear Values'!$A$2:$E$13, IF(COUNTBLANK('Attributes & Prefixes'!$B$6:$C$6)>0, "2", "3"), 0), COUNTIF($D$6:$E$6, K$2)>0, VLOOKUP($J35,'Gear Values'!$A$2:$E$13, IF(COUNTBLANK('Attributes & Prefixes'!$B$6:$C$6)>0, "4", "5"), 0)), "")} -> 53 | L35: {=IF(COUNTIF($B$6:$E$6, L$2)>0, _xlfn.IFS(COUNTIF($B$6:$C$6, L$2)>0, VLOOKUP($J35,'Gear Values'!$A$2:$E$13, IF(COUNTBLANK('Attributes & Prefixes'!$B$6:$C$6)>0, "2", "3"), 0), COUNTIF($D$6:$E$6, L$2)>0, VLOOKUP($J35,'Gear Values'!$A$2:$E$13, IF(COUNTBLANK('Attributes & Prefixes'!$B$6:$C$6)>0, "4", "5"), 0)), "")} -> 75 | M35: {=IF(COUNTIF($B$6:$E$6, M$2)>0, _xlfn.IFS(COUNTIF($B$6:$C$6, M$2)>0, VLOOKUP($J35,'Gear Values'!$A$2:$E$13, IF(COUNTBLANK('Attributes & Prefixes'!$B$6:$C$6)>0, "2", "3"), 0), COUNTIF($D$6:$E$6, M$2)>0, VLOOKUP($J35,'Gear Values'!$A$2:$E$13, IF(COUNTBLANK('Attributes & Prefixes'!$B$6:$C$6)>0, "4", "5"), 0)), "")} | N35: {=IF(COUNTIF($B$6:$E$6, N$2)>0, _xlfn.IFS(COUNTIF($B$6:$C$6, N$2)>0, VLOOKUP($J35,'Gear Values'!$A$2:$E$13, IF(COUNTBLANK('Attributes & Prefixes'!$B$6:$C$6)>0, "2", "3"), 0), COUNTIF($D$6:$E$6, N$2)>0, VLOOKUP($J35,'Gear Values'!$A$2:$E$13, IF(COUNTBLANK('Attributes & Prefixes'!$B$6:$C$6)>0, "4", "5"), 0)), "")} | O35: {=IF(COUNTIF($B$6:$E$6, O$2)>0, _xlfn.IFS(COUNTIF($B$6:$C$6, O$2)>0, VLOOKUP($J35,'Gear Values'!$A$2:$E$13, IF(COUNTBLANK('Attributes & Prefixes'!$B$6:$C$6)>0, "2", "3"), 0), COUNTIF($D$6:$E$6, O$2)>0, VLOOKUP($J35,'Gear Values'!$A$2:$E$13, IF(COUNTBLANK('Attributes & Prefixes'!$B$6:$C$6)>0, "4", "5"), 0)), "")} | P35: {=IF(COUNTIF($B$6:$E$6, P$2)>0, _xlfn.IFS(COUNTIF($B$6:$C$6, P$2)>0, VLOOKUP($J35,'Gear Values'!$A$2:$E$13, IF(COUNTBLANK('Attributes & Prefixes'!$B$6:$C$6)>0, "2", "3"), 0), COUNTIF($D$6:$E$6, P$2)>0, VLOOKUP($J35,'Gear Values'!$A$2:$E$13, IF(COUNTBLANK('Attributes & Prefixes'!$B$6:$C$6)>0, "4", "5"), 0)), "")} | Q35: {=IF(COUNTIF($B$6:$E$6, Q$2)>0, _xlfn.IFS(COUNTIF($B$6:$C$6, Q$2)>0, VLOOKUP($J35,'Gear Values'!$A$2:$E$13, IF(COUNTBLANK('Attributes & Prefixes'!$B$6:$C$6)>0, "2", "3"), 0), COUNTIF($D$6:$E$6, Q$2)>0, VLOOKUP($J35,'Gear Values'!$A$2:$E$13, IF(COUNTBLANK('Attributes & Prefixes'!$B$6:$C$6)>0, "4", "5"), 0)), "")} | R35: {=IF(COUNTIF($B$6:$E$6, R$2)>0, _xlfn.IFS(COUNTIF($B$6:$C$6, R$2)>0, VLOOKUP($J35,'Gear Values'!$A$2:$E$13, IF(COUNTBLANK('Attributes & Prefixes'!$B$6:$C$6)>0, "2", "3"), 0), COUNTIF($D$6:$E$6, R$2)>0, VLOOKUP($J35,'Gear Values'!$A$2:$E$13, IF(COUNTBLANK('Attributes & Prefixes'!$B$6:$C$6)>0, "4", "5"), 0)), "")} -> 53 | S35: {=IF(COUNTIF($B$6:$E$6, S$2)>0, _xlfn.IFS(COUNTIF($B$6:$C$6, S$2)>0, VLOOKUP($J35,'Gear Values'!$A$2:$E$13, IF(COUNTBLANK('Attributes & Prefixes'!$B$6:$C$6)>0, "2", "3"), 0), COUNTIF($D$6:$E$6, S$2)>0, VLOOKUP($J35,'Gear Values'!$A$2:$E$13, IF(COUNTBLANK('Attributes & Prefixes'!$B$6:$C$6)>0, "4", "5"), 0)), "")}
A36: Rampager | B36: Precision | D36: Power | E36: Condition Damage | F36: =IF(OR(COUNTBLANK(AttributeFilter) = 1,AttributeFilter="(Select)"), A36, IF(COUNTIF(B36:E36, AttributeFilter)>0, A36, "")) -> Rampager | H36: =_xlfn.CONCAT(A$72,J36) -> OpalFinger | J36: Finger | K36: {=IF(COUNTIF($B$6:$E$6, K$2)>0, _xlfn.IFS(COUNTIF($B$6:$C$6, K$2)>0, VLOOKUP($J36,'Gear Values'!$A$2:$E$13, IF(COUNTBLANK('Attributes & Prefixes'!$B$6:$C$6)>0, "2", "3"), 0), COUNTIF($D$6:$E$6, K$2)>0, VLOOKUP($J36,'Gear Values'!$A$2:$E$13, IF(COUNTBLANK('Attributes & Prefixes'!$B$6:$C$6)>0, "4", "5"), 0)), "")} -> 64 | L36: {=IF(COUNTIF($B$6:$E$6, L$2)>0, _xlfn.IFS(COUNTIF($B$6:$C$6, L$2)>0, VLOOKUP($J36,'Gear Values'!$A$2:$E$13, IF(COUNTBLANK('Attributes & Prefixes'!$B$6:$C$6)>0, "2", "3"), 0), COUNTIF($D$6:$E$6, L$2)>0, VLOOKUP($J36,'Gear Values'!$A$2:$E$13, IF(COUNTBLANK('Attributes & Prefixes'!$B$6:$C$6)>0, "4", "5"), 0)), "")} -> 90 | M36: {=IF(COUNTIF($B$6:$E$6, M$2)>0, _xlfn.IFS(COUNTIF($B$6:$C$6, M$2)>0, VLOOKUP($J36,'Gear Values'!$A$2:$E$13, IF(COUNTBLANK('Attributes & Prefixes'!$B$6:$C$6)>0, "2", "3"), 0), COUNTIF($D$6:$E$6, M$2)>0, VLOOKUP($J36,'Gear Values'!$A$2:$E$13, IF(COUNTBLANK('Attributes & Prefixes'!$B$6:$C$6)>0, "4", "5"), 0)), "")} | N36: {=IF(COUNTIF($B$6:$E$6, N$2)>0, _xlfn.IFS(COUNTIF($B$6:$C$6, N$2)>0, VLOOKUP($J36,'Gear Values'!$A$2:$E$13, IF(COUNTBLANK('Attributes & Prefixes'!$B$6:$C$6)>0, "2", "3"), 0), COUNTIF($D$6:$E$6, N$2)>0, VLOOKUP($J36,'Gear Values'!$A$2:$E$13, IF(COUNTBLANK('Attributes & Prefixes'!$B$6:$C$6)>0, "4", "5"), 0)), "")} | O36: {=IF(COUNTIF($B$6:$E$6, O$2)>0, _xlfn.IFS(COUNTIF($B$6:$C$6, O$2)>0, VLOOKUP($J36,'Gear Values'!$A$2:$E$13, IF(COUNTBLANK('Attributes & Prefixes'!$B$6:$C$6)>0, "2", "3"), 0), COUNTIF($D$6:$E$6, O$2)>0, VLOOKUP($J36,'Gear Values'!$A$2:$E$13, IF(COUNTBLANK('Attributes & Prefixes'!$B$6:$C$6)>0, "4", "5"), 0)), "")} | P36: {=IF(COUNTIF($B$6:$E$6, P$2)>0, _xlfn.IFS(COUNTIF($B$6:$C$6, P$2)>0, VLOOKUP($J36,'Gear Values'!$A$2:$E$13, IF(COUNTBLANK('Attributes & Prefixes'!$B$6:$C$6)>0, "2", "3"), 0), COUNTIF($D$6:$E$6, P$2)>0, VLOOKUP($J36,'Gear Values'!$A$2:$E$13, IF(COUNTBLANK('Attributes & Prefixes'!$B$6:$C$6)>0, "4", "5"), 0)), "")} | Q36: {=IF(COUNTIF($B$6:$E$6, Q$2)>0, _xlfn.IFS(COUNTIF($B$6:$C$6, Q$2)>0, VLOOKUP($J36,'Gear Values'!$A$2:$E$13, IF(COUNTBLANK('Attributes & Prefixes'!$B$6:$C$6)>0, "2", "3"), 0), COUNTIF($D$6:$E$6, Q$2)>0, VLOOKUP($J36,'Gear Values'!$A$2:$E$13, IF(COUNTBLANK('Attributes & Prefixes'!$B$6:$C$6)>0, "4", "5"), 0)), "")} | R36: {=IF(COUNTIF($B$6:$E$6, R$2)>0, _xlfn.IFS(COUNTIF($B$6:$C$6, R$2)>0, VLOOKUP($J36,'Gear Values'!$A$2:$E$13, IF(COUNTBLANK('Attributes & Prefixes'!$B$6:$C$6)>0, "2", "3"), 0), COUNTIF($D$6:$E$6, R$2)>0, VLOOKUP($J36,'Gear Values'!$A$2:$E$13, IF(COUNTBLANK('Attributes & Prefixes'!$B$6:$C$6)>0, "4", "5"), 0)), "")} -> 64 | S36: {=IF(COUNTIF($B$6:$E$6, S$2)>0, _xlfn.IFS(COUNTIF($B$6:$C$6, S$2)>0, VLOOKUP($J36,'Gear Values'!$A$2:$E$13, IF(COUNTBLANK('Attributes & Prefixes'!$B$6:$C$6)>0, "2", "3"), 0), COUNTIF($D$6:$E$6, S$2)>0, VLOOKUP($J36,'Gear Values'!$A$2:$E$13, IF(COUNTBLANK('Attributes & Prefixes'!$B$6:$C$6)>0, "4", "5"), 0)), "")}
A37: Ritualist | B37: Vitality | C37: Condition Damage | D37: Concentration | E37: Expertise | F37: =IF(OR(COUNTBLANK(AttributeFilter) = 1,AttributeFilter="(Select)"), A37, IF(COUNTIF(B37:E37, AttributeFilter)>0, A37, "")) -> Ritualist | H37: =_xlfn.CONCAT(A$72,J37) -> OpalNeck | J37: Neck | K37: {=IF(COUNTIF($B$6:$E$6, K$2)>0, _xlfn.IFS(COUNTIF($B$6:$C$6, K$2)>0, VLOOKUP($J37,'Gear Values'!$A$2:$E$13, IF(COUNTBLANK('Attributes & Prefixes'!$B$6:$C$6)>0, "2", "3"), 0), COUNTIF($D$6:$E$6, K$2)>0, VLOOKUP($J37,'Gear Values'!$A$2:$E$13, IF(COUNTBLANK('Attributes & Prefixes'!$B$6:$C$6)>0, "4", "5"), 0)), "")} -> 85 | L37: {=IF(COUNTIF($B$6:$E$6, L$2)>0, _xlfn.IFS(COUNTIF($B$6:$C$6, L$2)>0, VLOOKUP($J37,'Gear Values'!$A$2:$E$13, IF(COUNTBLANK('Attributes & Prefixes'!$B$6:$C$6)>0, "2", "3"), 0), COUNTIF($D$6:$E$6, L$2)>0, VLOOKUP($J37,'Gear Values'!$A$2:$E$13, IF(COUNTBLANK('Attributes & Prefixes'!$B$6:$C$6)>0, "4", "5"), 0)), "")} -> 120 | M37: {=IF(COUNTIF($B$6:$E$6, M$2)>0, _xlfn.IFS(COUNTIF($B$6:$C$6, M$2)>0, VLOOKUP($J37,'Gear Values'!$A$2:$E$13, IF(COUNTBLANK('Attributes & Prefixes'!$B$6:$C$6)>0, "2", "3"), 0), COUNTIF($D$6:$E$6, M$2)>0, VLOOKUP($J37,'Gear Values'!$A$2:$E$13, IF(COUNTBLANK('Attributes & Prefixes'!$B$6:$C$6)>0, "4", "5"), 0)), "")} | N37: {=IF(COUNTIF($B$6:$E$6, N$2)>0, _xlfn.IFS(COUNTIF($B$6:$C$6, N$2)>0, VLOOKUP($J37,'Gear Values'!$A$2:$E$13, IF(COUNTBLANK('Attributes & Prefixes'!$B$6:$C$6)>0, "2", "3"), 0), COUNTIF($D$6:$E$6, N$2)>0, VLOOKUP($J37,'Gear Values'!$A$2:$E$13, IF(COUNTBLANK('Attributes & Prefixes'!$B$6:$C$6)>0, "4", "5"), 0)), "")} | O37: {=IF(COUNTIF($B$6:$E$6, O$2)>0, _xlfn.IFS(COUNTIF($B$6:$C$6, O$2)>0, VLOOKUP($J37,'Gear Values'!$A$2:$E$13, IF(COUNTBLANK('Attributes & Prefixes'!$B$6:$C$6)>0, "2", "3"), 0), COUNTIF($D$6:$E$6, O$2)>0, VLOOKUP($J37,'Gear Values'!$A$2:$E$13, IF(COUNTBLANK('Attributes & Prefixes'!$B$6:$C$6)>0, "4", "5"), 0)), "")} | P37: {=IF(COUNTIF($B$6:$E$6, P$2)>0, _xlfn.IFS(COUNTIF($B$6:$C$6, P$2)>0, VLOOKUP($J37,'Gear Values'!$A$2:$E$13, IF(COUNTBLANK('Attributes & Prefixes'!$B$6:$C$6)>0, "2", "3"), 0), COUNTIF($D$6:$E$6, P$2)>0, VLOOKUP($J37,'Gear Values'!$A$2:$E$13, IF(COUNTBLANK('Attributes & Prefixes'!$B$6:$C$6)>0, "4", "5"), 0)), "")} | Q37: {=IF(COUNTIF($B$6:$E$6, Q$2)>0, _xlfn.IFS(COUNTIF($B$6:$C$6, Q$2)>0, VLOOKUP($J37,'Gear Values'!$A$2:$E$13, IF(COUNTBLANK('Attributes & Prefixes'!$B$6:$C$6)>0, "2", "3"), 0), COUNTIF($D$6:$E$6, Q$2)>0, VLOOKUP($J37,'Gear Values'!$A$2:$E$13, IF(COUNTBLANK('Attributes & Prefixes'!$B$6:$C$6)>0, "4", "5"), 0)), "")} | R37: {=IF(COUNTIF($B$6:$E$6, R$2)>0, _xlfn.IFS(COUNTIF($B$6:$C$6, R$2)>0, VLOOKUP($J37,'Gear Values'!$A$2:$E$13, IF(COUNTBLANK('Attributes & Prefixes'!$B$6:$C$6)>0, "2", "3"), 0), COUNTIF($D$6:$E$6, R$2)>0, VLOOKUP($J37,'Gear Values'!$A$2:$E$13, IF(COUNTBLANK('Attributes & Prefixes'!$B$6:$C$6)>0, "4", "5"), 0)), "")} -> 85 | S37: {=IF(COUNTIF($B$6:$E$6, S$2)>0, _xlfn.IFS(COUNTIF($B$6:$C$6, S$2)>0, VLOOKUP($J37,'Gear Values'!$A$2:$E$13, IF(COUNTBLANK('Attributes & Prefixes'!$B$6:$C$6)>0, "2", "3"), 0), COUNTIF($D$6:$E$6, S$2)>0, VLOOKUP($J37,'Gear Values'!$A$2:$E$13, IF(COUNTBLANK('Attributes & Prefixes'!$B$6:$C$6)>0, "4", "5"), 0)), "")}
A38: Sage | B38: Power | C38: Condition Damage | D38: Vitality | E38: Healing Power | F38: =IF(OR(COUNTBLANK(AttributeFilter) = 1,AttributeFilter="(Select)"), A38, IF(COUNTIF(B38:E38, AttributeFilter)>0, A38, "")) -> Sage | H38: =_xlfn.CONCAT(I$27,J38) -> AssassinBack | J38: Back | K38: {=IF(COUNTIF($B$6:$E$6, K$2)>0, _xlfn.IFS(COUNTIF($B$6:$C$6, K$2)>0, VLOOKUP($J38,'Gear Values'!$A$2:$E$13, IF(COUNTBLANK('Attributes & Prefixes'!$B$6:$C$6)>0, "2", "3"), 0), COUNTIF($D$6:$E$6, K$2)>0, VLOOKUP($J38,'Gear Values'!$A$2:$E$13, IF(COUNTBLANK('Attributes & Prefixes'!$B$6:$C$6)>0, "4", "5"), 0)), "")} -> 18 | L38: {=IF(COUNTIF($B$6:$E$6, L$2)>0, _xlfn.IFS(COUNTIF($B$6:$C$6, L$2)>0, VLOOKUP($J38,'Gear Values'!$A$2:$E$13, IF(COUNTBLANK('Attributes & Prefixes'!$B$6:$C$6)>0, "2", "3"), 0), COUNTIF($D$6:$E$6, L$2)>0, VLOOKUP($J38,'Gear Values'!$A$2:$E$13, IF(COUNTBLANK('Attributes & Prefixes'!$B$6:$C$6)>0, "4", "5"), 0)), "")} -> 32 | M38: {=IF(COUNTIF($B$6:$E$6, M$2)>0, _xlfn.IFS(COUNTIF($B$6:$C$6, M$2)>0, VLOOKUP($J38,'Gear Values'!$A$2:$E$13, IF(COUNTBLANK('Attributes & Prefixes'!$B$6:$C$6)>0, "2", "3"), 0), COUNTIF($D$6:$E$6, M$2)>0, VLOOKUP($J38,'Gear Values'!$A$2:$E$13, IF(COUNTBLANK('Attributes & Prefixes'!$B$6:$C$6)>0, "4", "5"), 0)), "")} | N38: {=IF(COUNTIF($B$6:$E$6, N$2)>0, _xlfn.IFS(COUNTIF($B$6:$C$6, N$2)>0, VLOOKUP($J38,'Gear Values'!$A$2:$E$13, IF(COUNTBLANK('Attributes & Prefixes'!$B$6:$C$6)>0, "2", "3"), 0), COUNTIF($D$6:$E$6, N$2)>0, VLOOKUP($J38,'Gear Values'!$A$2:$E$13, IF(COUNTBLANK('Attributes & Prefixes'!$B$6:$C$6)>0, "4", "5"), 0)), "")} | O38: {=IF(COUNTIF($B$6:$E$6, O$2)>0, _xlfn.IFS(COUNTIF($B$6:$C$6, O$2)>0, VLOOKUP($J38,'Gear Values'!$A$2:$E$13, IF(COUNTBLANK('Attributes & Prefixes'!$B$6:$C$6)>0, "2", "3"), 0), COUNTIF($D$6:$E$6, O$2)>0, VLOOKUP($J38,'Gear Values'!$A$2:$E$13, IF(COUNTBLANK('Attributes & Prefixes'!$B$6:$C$6)>0, "4", "5"), 0)), "")} | P38: {=IF(COUNTIF($B$6:$E$6, P$2)>0, _xlfn.IFS(COUNTIF($B$6:$C$6, P$2)>0, VLOOKUP($J38,'Gear Values'!$A$2:$E$13, IF(COUNTBLANK('Attributes & Prefixes'!$B$6:$C$6)>0, "2", "3"), 0), COUNTIF($D$6:$E$6, P$2)>0, VLOOKUP($J38,'Gear Values'!$A$2:$E$13, IF(COUNTBLANK('Attributes & Prefixes'!$B$6:$C$6)>0, "4", "5"), 0)), "")} | Q38: {=IF(COUNTIF($B$6:$E$6, Q$2)>0, _xlfn.IFS(COUNTIF($B$6:$C$6, Q$2)>0, VLOOKUP($J38,'Gear Values'!$A$2:$E$13, IF(COUNTBLANK('Attributes & Prefixes'!$B$6:$C$6)>0, "2", "3"), 0), COUNTIF($D$6:$E$6, Q$2)>0, VLOOKUP($J38,'Gear Values'!$A$2:$E$13, IF(COUNTBLANK('Attributes & Prefixes'!$B$6:$C$6)>0, "4", "5"), 0)), "")} | R38: {=IF(COUNTIF($B$6:$E$6, R$2)>0, _xlfn.IFS(COUNTIF($B$6:$C$6, R$2)>0, VLOOKUP($J38,'Gear Values'!$A$2:$E$13, IF(COUNTBLANK('Attributes & Prefixes'!$B$6:$C$6)>0, "2", "3"), 0), COUNTIF($D$6:$E$6, R$2)>0, VLOOKUP($J38,'Gear Values'!$A$2:$E$13, IF(COUNTBLANK('Attributes & Prefixes'!$B$6:$C$6)>0, "4", "5"), 0)), "")} -> 18 | S38: {=IF(COUNTIF($B$6:$E$6, S$2)>0, _xlfn.IFS(COUNTIF($B$6:$C$6, S$2)>0, VLOOKUP($J38,'Gear Values'!$A$2:$E$13, IF(COUNTBLANK('Attributes & Prefixes'!$B$6:$C$6)>0, "2", "3"), 0), COUNTIF($D$6:$E$6, S$2)>0, VLOOKUP($J38,'Gear Values'!$A$2:$E$13, IF(COUNTBLANK('Attributes & Prefixes'!$B$6:$C$6)>0, "4", "5"), 0)), "")}
A39: Sentinel | B39: Vitality | D39: Power | E39: Toughness | F39: =IF(OR(COUNTBLANK(AttributeFilter) = 1,AttributeFilter="(Select)"), A39, IF(COUNTIF(B39:E39, AttributeFilter)>0, A39, "")) -> Sentinel | H39: =_xlfn.CONCAT(I$39,J39) -> AvatarWeapon (1H) | I39: =A7 -> Avatar | J39: Weapon (1H) | K39: {=IF(COUNTIF($B$7:$E$7, K$2)>0, _xlfn.IFS(COUNTIF($B$7:$C$7, K$2)>0, VLOOKUP($J39,'Gear Values'!$A$2:$E$13, IF(COUNTBLANK('Attributes & Prefixes'!$B$7:$C$7)>0, "2", "3"), 0), COUNTIF($D$7:$E$7, K$2)>0, VLOOKUP($J39,'Gear Values'!$A$2:$E$13, IF(COUNTBLANK('Attributes & Prefixes'!$B$7:$C$7)>0, "4", "5"), 0)), "")} -> 102 | L39: {=IF(COUNTIF($B$7:$E$7, L$2)>0, _xlfn.IFS(COUNTIF($B$7:$C$7, L$2)>0, VLOOKUP($J39,'Gear Values'!$A$2:$E$13, IF(COUNTBLANK('Attributes & Prefixes'!$B$7:$C$7)>0, "2", "3"), 0), COUNTIF($D$7:$E$7, L$2)>0, VLOOKUP($J39,'Gear Values'!$A$2:$E$13, IF(COUNTBLANK('Attributes & Prefixes'!$B$7:$C$7)>0, "4", "5"), 0)), "")} -> 102 | M39: {=IF(COUNTIF($B$7:$E$7, M$2)>0, _xlfn.IFS(COUNTIF($B$7:$C$7, M$2)>0, VLOOKUP($J39,'Gear Values'!$A$2:$E$13, IF(COUNTBLANK('Attributes & Prefixes'!$B$7:$C$7)>0, "2", "3"), 0), COUNTIF($D$7:$E$7, M$2)>0, VLOOKUP($J39,'Gear Values'!$A$2:$E$13, IF(COUNTBLANK('Attributes & Prefixes'!$B$7:$C$7)>0, "4", "5"), 0)), "")} | N39: {=IF(COUNTIF($B$7:$E$7, N$2)>0, _xlfn.IFS(COUNTIF($B$7:$C$7, N$2)>0, VLOOKUP($J39,'Gear Values'!$A$2:$E$13, IF(COUNTBLANK('Attributes & Prefixes'!$B$7:$C$7)>0, "2", "3"), 0), COUNTIF($D$7:$E$7, N$2)>0, VLOOKUP($J39,'Gear Values'!$A$2:$E$13, IF(COUNTBLANK('Attributes & Prefixes'!$B$7:$C$7)>0, "4", "5"), 0)), "")} -> 56 | O39: {=IF(COUNTIF($B$7:$E$7, O$2)>0, _xlfn.IFS(COUNTIF($B$7:$C$7, O$2)>0, VLOOKUP($J39,'Gear Values'!$A$2:$E$13, IF(COUNTBLANK('Attributes & Prefixes'!$B$7:$C$7)>0, "2", "3"), 0), COUNTIF($D$7:$E$7, O$2)>0, VLOOKUP($J39,'Gear Values'!$A$2:$E$13, IF(COUNTBLANK('Attributes & Prefixes'!$B$7:$C$7)>0, "4", "5"), 0)), "")} | P39: {=IF(COUNTIF($B$7:$E$7, P$2)>0, _xlfn.IFS(COUNTIF($B$7:$C$7, P$2)>0, VLOOKUP($J39,'Gear Values'!$A$2:$E$13, IF(COUNTBLANK('Attributes & Prefixes'!$B$7:$C$7)>0, "2", "3"), 0), COUNTIF($D$7:$E$7, P$2)>0, VLOOKUP($J39,'Gear Values'!$A$2:$E$13, IF(COUNTBLANK('Attributes & Prefixes'!$B$7:$C$7)>0, "4", "5"), 0)), "")} | Q39: {=IF(COUNTIF($B$7:$E$7, Q$2)>0, _xlfn.IFS(COUNTIF($B$7:$C$7, Q$2)>0, VLOOKUP($J39,'Gear Values'!$A$2:$E$13, IF(COUNTBLANK('Attributes & Prefixes'!$B$7:$C$7)>0, "2", "3"), 0), COUNTIF($D$7:$E$7, Q$2)>0, VLOOKUP($J39,'Gear Values'!$A$2:$E$13, IF(COUNTBLANK('Attributes & Prefixes'!$B$7:$C$7)>0, "4", "5"), 0)), "")} | R39: {=IF(COUNTIF($B$7:$E$7, R$2)>0, _xlfn.IFS(COUNTIF($B$7:$C$7, R$2)>0, VLOOKUP($J39,'Gear Values'!$A$2:$E$13, IF(COUNTBLANK('Attributes & Prefixes'!$B$7:$C$7)>0, "2", "3"), 0), COUNTIF($D$7:$E$7, R$2)>0, VLOOKUP($J39,'Gear Values'!$A$2:$E$13, IF(COUNTBLANK('Attributes & Prefixes'!$B$7:$C$7)>0, "4", "5"), 0)), "")} | S39: {=IF(COUNTIF($B$7:$E$7, S$2)>0, _xlfn.IFS(COUNTIF($B$7:$C$7, S$2)>0, VLOOKUP($J39,'Gear Values'!$A$2:$E$13, IF(COUNTBLANK('Attributes & Prefixes'!$B$7:$C$7)>0, "2", "3"), 0), COUNTIF($D$7:$E$7, S$2)>0, VLOOKUP($J39,'Gear Values'!$A$2:$E$13, IF(COUNTBLANK('Attributes & Prefixes'!$B$7:$C$7)>0, "4", "5"), 0)), "")} -> 56
